Workbook

Sheet Raw Data
B1: Security | C1: LyondellBasell Industries NV | D1: American Express Co | E1: Verizon Communications Inc | F1: Texas Pacific Land Corp | G1: Broadcom Inc | H1: Boeing Co/The | I1: Caterpillar Inc | J1: JPMorgan Chase & Co | K1: Chevron Corp | L1: Coca-Cola Co/The | M1: AbbVie Inc | N1: Walt Disney Co/The | O1: Corpay Inc | P1: Extra Space Storage Inc | Q1: Exxon Mobil Corp | R1: Phillips 66 | S1: General Electric Co | T1: HP Inc | U1: Home Depot Inc/The | V1: Monolithic Power Systems Inc | W1: International Business Machines Corp | X1: Johnson & Johnson | Y1: Lululemon Athletica Inc | Z1: McDonald's Corp | AA1: Merck & Co Inc | AB1: 3M Co | AC1: American Water Works Co Inc | AD1: Bank of America Corp | AE1: Pfizer Inc | AF1: Procter & Gamble Co/The | AG1: AT&T Inc | AH1: Travelers Cos Inc/The | AI1: RTX Corp | AJ1: Analog Devices Inc | AK1: Walmart Inc | AL1: Cisco Systems Inc | AM1: Intel Corp | AN1: General Motors Co | AO1: Microsoft Corp | AP1: Dollar General Corp | AQ1: Cigna Group/The | AR1: Kinder Morgan Inc | AS1: Citigroup Inc | AT1: American International Group Inc | AU1: Altria Group Inc | AV1: HCA Healthcare Inc | AW1: International Paper Co | AX1: Hewlett Packard Enterprise Co | AY1: Abbott Laboratories | AZ1: Aflac Inc | BA1: Air Products and Chemicals Inc | BB1: Royal Caribbean Cruises Ltd | BC1: Interactive Brokers Group Inc | BD1: Lennox International Inc | BE1: Archer-Daniels-Midland Co | BF1: EMCOR Group Inc | BG1: Automatic Data Processing Inc | BH1: Verisk Analytics Inc | BI1: AutoZone Inc | BJ1: Avery Dennison Corp | BK1: MSCI Inc | BL1: Ball Corp | BM1: Axon Enterprise Inc | BN1: Dayforce Inc | BO1: Bank of New York Mellon Corp/The | BP1: Baxter International Inc | BQ1: Becton Dickinson & Co | BR1: Berkshire Hathaway Inc | BS1: Best Buy Co Inc | BT1: Boston Scientific Corp | BU1: Bristol-Myers Squibb Co | BV1: Brown-Forman Corp | BW1: Coterra Energy Inc | BX1: Hilton Worldwide Holdings Inc | BY1: Carnival Corp | BZ1: Builders FirstSource Inc | CA1: UDR Inc | CB1: Clorox Co/The | CC1: Paycom Software Inc | CD1: CMS Energy Corp | CE1: Colgate-Palmolive Co | CF1: EPAM Systems Inc | CG1: Conagra Brands Inc | CH1: Consolidated Edison Inc | CI1: Corning Inc | CJ1: GoDaddy Inc | CK1: Cummins Inc | CL1: Danaher Corp | CM1: Target Corp | CN1: Williams-Sonoma Inc | CO1: Deere & Co | CP1: Dominion Energy Inc | CQ1: Trade Desk Inc/The | CR1: Dover Corp | CS1: Alliant Energy Corp | CT1: Steel Dynamics Inc | CU1: Duke Energy Corp | CV1: Regency Centers Corp | CW1: Eaton Corp PLC | CX1: Ecolab Inc | CY1: Revvity Inc | CZ1: Dell Technologies Inc | DA1: Emerson Electric Co | DB1: EOG Resources Inc | DC1: Aon PLC | DD1: Entergy Corp | DE1: Equifax Inc | DF1: EQT Corp | DG1: IQVIA Holdings Inc | DH1: Gartner Inc | DI1: FedEx Corp | DJ1: Brown & Brown Inc | DK1: Ford Motor Co | DL1: NextEra Energy Inc | DM1: Franklin Resources Inc | DN1: Garmin Ltd | DO1: Freeport-McMoRan Inc | DP1: Dexcom Inc | DQ1: General Dynamics Corp | DR1: General Mills Inc | DS1: Genuine Parts Co | DT1: Atmos Energy Corp | DU1: WW Grainger Inc | DV1: Halliburton Co | DW1: L3Harris Technologies Inc | DX1: Healthpeak Properties Inc | DY1: Insulet Corp | DZ1: Fortive Corp | EA1: Hershey Co/The | EB1: Synchrony Financial | EC1: Hormel Foods Corp | ED1: Arthur J Gallagher & Co | EE1: Mondelez International Inc | EF1: CenterPoint Energy Inc | EG1: Humana Inc | EH1: Willis Towers Watson PLC | EI1: Illinois Tool Works Inc | EJ1: CDW Corp/DE | EK1: Trane Technologies PLC | EL1: International Flavors & Fragrances Inc | EM1: Generac Holdings Inc | EN1: NXP Semiconductors NV | EO1: Kellanova | EP1: Broadridge Financial Solutions Inc | EQ1: Kimco Realty Corp | ER1: Oracle Corp | ES1: Kroger Co/The | ET1: Lennar Corp | EU1: Eli Lilly & Co | EV1: Charter Communications Inc | EW1: Loews Corp | EX1: Lowe's Cos Inc | EY1: Hubbell Inc | EZ1: IDEX Corp | FA1: Marsh & McLennan Cos Inc | FB1: Masco Corp | FC1: S&P Global Inc | FD1: Medtronic PLC | FE1: Viatris Inc | FF1: CVS Health Corp | FG1: DuPont de Nemours Inc | FH1: Micron Technology Inc | FI1: Motorola Solutions Inc | FJ1: Cboe Global Markets Inc | FK1: Newmont Corp | FL1: NIKE Inc | FM1: NiSource Inc | FN1: Norfolk Southern Corp | FO1: Principal Financial Group Inc | FP1: Eversource Energy | FQ1: Northrop Grumman Corp | FR1: Wells Fargo & Co | FS1: Nucor Corp | FT1: Occidental Petroleum Corp | FU1: Omnicom Group Inc | FV1: ONEOK Inc | FW1: Raymond James Financial Inc | FX1: PG&E Corp | FY1: Parker-Hannifin Corp | FZ1: Rollins Inc | GA1: PPL Corp | GB1: Aptiv PLC | GC1: ConocoPhillips | GD1: PulteGroup Inc | GE1: Pinnacle West Capital Corp | GF1: PNC Financial Services Group Inc/The | GG1: PPG Industries Inc | GH1: Progressive Corp/The | GI1: Public Service Enterprise Group Inc | GJ1: Edison International | GK1: SLB Ltd | GL1: Charles Schwab Corp/The | GM1: Sherwin-Williams Co/The | GN1: West Pharmaceutical Services Inc | GO1: J M Smucker Co/The | GP1: Snap-on Inc | GQ1: AMETEK Inc | GR1: Uber Technologies Inc | GS1: Southern Co/The | GT1: Truist Financial Corp | GU1: Southwest Airlines Co | GV1: W R Berkley Corp | GW1: Stanley Black & Decker Inc | GX1: Public Storage | GY1: Arista Networks Inc | GZ1: Sysco Corp | HA1: Corteva Inc | HB1: Texas Instruments Inc | HC1: Textron Inc | HD1: Thermo Fisher Scientific Inc | HE1: TJX Cos Inc/The | HF1: Globe Life Inc | HG1: Johnson Controls International plc | HH1: Ulta Beauty Inc | HI1: Union Pacific Corp | HJ1: Keysight Technologies Inc | HK1: UnitedHealth Group Inc | HL1: Blackstone Inc | HM1: Ventas Inc | HN1: Labcorp Holdings Inc | HO1: Vulcan Materials Co | HP1: Weyerhaeuser Co | HQ1: Williams Cos Inc/The | HR1: WEC Energy Group Inc | HS1: Adobe Inc | HT1: Vistra Corp | HU1: AES Corp/The | HV1: Expeditors International of Washington Inc | HW1: Amgen Inc | HX1: Apple Inc | HY1: Autodesk Inc | HZ1: Cintas Corp | IA1: Comcast Corp | IB1: Molson Coors Beverage Co | IC1: KLA Corp | ID1: Marriott International Inc/MD | IE1: McCormick & Co Inc/MD | IF1: PACCAR Inc | IG1: Costco Wholesale Corp | IH1: Stryker Corp | II1: Tyson Foods Inc | IJ1: Lamb Weston Holdings Inc | IK1: Applied Materials Inc | IL1: Cardinal Health Inc | IM1: Cincinnati Financial Corp | IN1: DR Horton Inc | IO1: Electronic Arts Inc | IP1: Erie Indemnity Co | IQ1: Fair Isaac Corp | IR1: Fastenal Co | IS1: M&T Bank Corp | IT1: Xcel Energy Inc | IU1: Fifth Third Bancorp | IV1: Gilead Sciences Inc | IW1: Hasbro Inc | IX1: Huntington Bancshares Inc/OH | IY1: Welltower Inc | IZ1: Biogen Inc | JA1: Northern Trust Corp | JB1: Packaging Corp of America | JC1: Paychex Inc | JD1: QUALCOMM Inc | JE1: Ross Stores Inc | JF1: IDEXX Laboratories Inc | JG1: Starbucks Corp | JH1: KeyCorp | JI1: Fox Corp (Class A) | JJ1: Fox Corp | JK1: State Street Corp | JL1: Norwegian Cruise Line Holdings Ltd | JM1: US Bancorp | JN1: A O Smith Corp | JO1: Gen Digital Inc | JP1: T Rowe Price Group Inc | JQ1: Waste Management Inc | JR1: Constellation Brands Inc | JS1: Invesco Ltd | JT1: Intuit Inc | JU1: Morgan Stanley | JV1: Microchip Technology Inc | JW1: Crowdstrike Holdings Inc | JX1: Chubb Ltd | JY1: Hologic Inc | JZ1: Citizens Financial Group Inc | KA1: Jabil Inc | KB1: O'Reilly Automotive Inc | KC1: Allstate Corp/The | KD1: Equity Residential | KE1: Incyte Corp | KF1: Simon Property Group Inc | KG1: AvalonBay Communities Inc | KH1: Prudential Financial Inc | KI1: United Parcel Service Inc | KJ1: STERIS PLC | KK1: McKesson Corp | KL1: Lockheed Martin Corp | KM1: Cencora Inc | KN1: Capital One Financial Corp | KO1: Waters Corp | KP1: Nordson Corp | KQ1: Dollar Tree Inc | KR1: Darden Restaurants Inc | KS1: NVR Inc | KT1: NetApp Inc | KU1: Old Dominion Freight Line Inc | KV1: DaVita Inc | KW1: Hartford Insurance Group Inc/The | KX1: Iron Mountain Inc | KY1: Estee Lauder Cos Inc/The | KZ1: Cadence Design Systems Inc | LA1: Tyler Technologies Inc | LB1: Universal Health Services Inc | LC1: Skyworks Solutions Inc | LD1: Quest Diagnostics Inc | LE1: Rockwell Automation Inc | LF1: Kraft Heinz Co/The | LG1: American Tower Corp | LH1: Regeneron Pharmaceuticals Inc | LI1: Amazon.com Inc | LJ1: Jack Henry & Associates Inc | LK1: Ralph Lauren Corp | LL1: BXP Inc | LM1: Amphenol Corp | LN1: Howmet Aerospace Inc | LO1: Valero Energy Corp | LP1: Synopsys Inc | LQ1: CH Robinson Worldwide Inc | LR1: Accenture PLC | LS1: TransDigm Group Inc | LT1: Yum! Brands Inc | LU1: Prologis Inc | LV1: FirstEnergy Corp | LW1: VeriSign Inc | LX1: Quanta Services Inc | LY1: Henry Schein Inc | LZ1: Ameren Corp | MA1: FactSet Research Systems Inc | MB1: NVIDIA Corp | MC1: Cognizant Technology Solutions Corp | MD1: Intuitive Surgical Inc | ME1: Take-Two Interactive Software Inc | MF1: Republic Services Inc | MG1: eBay Inc | MH1: Goldman Sachs Group Inc/The | MI1: SBA Communications Corp | MJ1: Sempra | MK1: Moody's Corp | ML1: ON Semiconductor Corp | MM1: Booking Holdings Inc | MN1: F5 Inc | MO1: Akamai Technologies Inc | MP1: Charles River Laboratories International Inc | MQ1: Devon Energy Corp | MR1: Bio-Techne Corp | MS1: Alphabet Inc (Class A) | MT1: Allegion plc | MU1: Netflix Inc | MV1: Agilent Technologies Inc | MW1: Trimble Inc | MX1: Elevance Health Inc | MY1: CME Group Inc | MZ1: DTE Energy Co | NA1: Nasdaq Inc | NB1: Philip Morris International Inc | NC1: Ingersoll Rand Inc | ND1: Salesforce Inc | NE1: Huntington Ingalls Industries Inc | NF1: MetLife Inc | NG1: Tapestry Inc | NH1: CSX Corp | NI1: Edwards Lifesciences Corp | NJ1: Ameriprise Financial Inc | NK1: Zebra Technologies Corp | NL1: Zimmer Biomet Holdings Inc | NM1: Camden Property Trust | NN1: CBRE Group Inc | NO1: Mastercard Inc | NP1: Datadog Inc | NQ1: Intercontinental Exchange Inc | NR1: Fidelity National Information Services Inc | NS1: Chipotle Mexican Grill Inc | NT1: Wynn Resorts Ltd | NU1: Live Nation Entertainment Inc | NV1: Assurant Inc | NW1: NRG Energy Inc | NX1: Monster Beverage Corp | NY1: Regions Financial Corp | NZ1: Mosaic Co/The | OA1: Expedia Group Inc | OB1: CF Industries Holdings Inc | OC1: Leidos Holdings Inc | OD1: Alphabet Inc | OE1: TKO Group Holdings Inc | OF1: First Solar Inc | OG1: Visa Inc | OH1: Mid-America Apartment Communities Inc | OI1: Xylem Inc/NY | OJ1: Marathon Petroleum Corp | OK1: Tractor Supply Co | OL1: Advanced Micro Devices Inc | OM1: ResMed Inc | ON1: Mettler-Toledo International Inc | OO1: VICI Properties Inc | OP1: Copart Inc | OQ1: Jacobs Solutions Inc | OR1: Albemarle Corp | OS1: Fortinet Inc | OT1: Moderna Inc | OU1: Essex Property Trust Inc | OV1: CoStar Group Inc | OW1: Realty Income Corp | OX1: Westinghouse Air Brake Technologies Corp | OY1: Pool Corp | OZ1: Western Digital Corp | PA1: PepsiCo Inc | PB1: TE Connectivity PLC | PC1: Diamondback Energy Inc | PD1: ServiceNow Inc | PE1: Church & Dwight Co Inc | PF1: Federal Realty Investment Trust | PG1: MGM Resorts International | PH1: Invitation Homes Inc | PI1: PTC Inc | PJ1: JB Hunt Transport Services Inc | PK1: Lam Research Corp | PL1: Mohawk Industries Inc | PM1: Pentair PLC | PN1: Vertex Pharmaceuticals Inc | PO1: Amcor PLC | PP1: Meta Platforms Inc | PQ1: T-Mobile US Inc | PR1: United Rentals Inc | PS1: Alexandria Real Estate Equities Inc | PT1: Delta Air Lines Inc | PU1: United Airlines Holdings Inc | PV1: Seagate Technology Holdings PLC | PW1: News Corp | PX1: Centene Corp | PY1: Block Inc | PZ1: Apollo Global Management Inc | QA1: Martin Marietta Materials Inc | QB1: Teradyne Inc | QC1: PayPal Holdings Inc | QD1: Tesla Inc | QE1: Blackrock Inc | QF1: KKR & Co Inc | QG1: Arch Capital Group Ltd | QH1: Dow Inc | QI1: Everest Group Ltd | QJ1: Teledyne Technologies Inc | QK1: News Corp (Class A) | QL1: Exelon Corp | QM1: Global Payments Inc | QN1: Crown Castle Inc | QO1: Align Technology Inc | QP1: Targa Resources Corp | QQ1: Bunge Global SA | QR1: LKQ Corp | QS1: Deckers Outdoor Corp | QT1: Workday Inc | QU1: Zoetis Inc | QV1: Equinix Inc | QW1: Digital Realty Trust Inc | QX1: Molina Healthcare Inc | QY1: Las Vegas Sands Corp | QZ1: Solventum Corp | RA1: Super Micro Computer Inc | RB1: Linde PLC | RC1: Carrier Global Corp | RD1: Otis Worldwide Corp | RE1: Airbnb Inc | RF1: Expand Energy Corp | RG1: DoorDash Inc | RH1: Veralto Corp | RI1: Cooper Cos Inc/The | RJ1: Constellation Energy Corp | RK1: AppLovin Corp | RL1: Keurig Dr Pepper Inc | RM1: Host Hotels & Resorts Inc | RN1: Campbell's Company/The | RO1: Evergy Inc | RP1: Match Group Inc | RQ1: Warner Bros Discovery Inc | RR1: Roper Technologies Inc | RS1: Smurfit WestRock PLC | RT1: Baker Hughes Co | RU1: APA Corp | RV1: Palantir Technologies Inc | RW1: Palo Alto Networks Inc | RX1: American Electric Power Co Inc | RY1: GE HealthCare Technologies Inc | RZ1: Honeywell International Inc | SA1: Robinhood Markets Inc | SB1: Domino's Pizza Inc | SC1: GE Vernova Inc | SD1: Kenvue Inc | SE1: Coinbase Global Inc
B2: Ticker | C2: LYB UN Equity | D2: AXP UN Equity | E2: VZ UN Equity | F2: TPL UN Equity | G2: AVGO UW Equity | H2: BA UN Equity | I2: CAT UN Equity | J2: JPM UN Equity | K2: CVX UN Equity | L2: KO UN Equity | M2: ABBV UN Equity | N2: DIS UN Equity | O2: CPAY UN Equity | P2: EXR UN Equity | Q2: XOM UN Equity | R2: PSX UN Equity | S2: GE UN Equity | T2: HPQ UN Equity | U2: HD UN Equity | V2: MPWR UW Equity | W2: IBM UN Equity | X2: JNJ UN Equity | Y2: LULU UW Equity | Z2: MCD UN Equity | AA2: MRK UN Equity | AB2: MMM UN Equity | AC2: AWK UN Equity | AD2: BAC UN Equity | AE2: PFE UN Equity | AF2: PG UN Equity | AG2: T UN Equity | AH2: TRV UN Equity | AI2: RTX UN Equity | AJ2: ADI UW Equity | AK2: WMT UN Equity | AL2: CSCO UW Equity | AM2: INTC UW Equity | AN2: GM UN Equity | AO2: MSFT UW Equity | AP2: DG UN Equity | AQ2: CI UN Equity | AR2: KMI UN Equity | AS2: C UN Equity | AT2: AIG UN Equity | AU2: MO UN Equity | AV2: HCA UN Equity | AW2: IP UN Equity | AX2: HPE UN Equity | AY2: ABT UN Equity | AZ2: AFL UN Equity | BA2: APD UN Equity | BB2: RCL UN Equity | BC2: IBKR UW Equity | BD2: LII UN Equity | BE2: ADM UN Equity | BF2: EME UN Equity | BG2: ADP UW Equity | BH2: VRSK UW Equity | BI2: AZO UN Equity | BJ2: AVY UN Equity | BK2: MSCI UN Equity | BL2: BALL UN Equity | BM2: AXON UW Equity | BN2: DAY UN Equity | BO2: BK UN Equity | BP2: BAX UN Equity | BQ2: BDX UN Equity | BR2: BRK/B UN Equity | BS2: BBY UN Equity | BT2: BSX UN Equity | BU2: BMY UN Equity | BV2: BF/B UN Equity | BW2: CTRA UN Equity | BX2: HLT UN Equity | BY2: CCL UN Equity | BZ2: BLDR UN Equity | CA2: UDR UN Equity | CB2: CLX UN Equity | CC2: PAYC UN Equity | CD2: CMS UN Equity | CE2: CL UN Equity | CF2: EPAM UN Equity | CG2: CAG UN Equity | CH2: ED UN Equity | CI2: GLW UN Equity | CJ2: GDDY UN Equity | CK2: CMI UN Equity | CL2: DHR UN Equity | CM2: TGT UN Equity | CN2: WSM UN Equity | CO2: DE UN Equity | CP2: D UN Equity | CQ2: TTD UQ Equity | CR2: DOV UN Equity | CS2: LNT UW Equity | CT2: STLD UW Equity | CU2: DUK UN Equity | CV2: REG UW Equity | CW2: ETN UN Equity | CX2: ECL UN Equity | CY2: RVTY UN Equity | CZ2: DELL UN Equity | DA2: EMR UN Equity | DB2: EOG UN Equity | DC2: AON UN Equity | DD2: ETR UN Equity | DE2: EFX UN Equity | DF2: EQT UN Equity | DG2: IQV UN Equity | DH2: IT UN Equity | DI2: FDX UN Equity | DJ2: BRO UN Equity | DK2: F UN Equity | DL2: NEE UN Equity | DM2: BEN UN Equity | DN2: GRMN UN Equity | DO2: FCX UN Equity | DP2: DXCM UW Equity | DQ2: GD UN Equity | DR2: GIS UN Equity | DS2: GPC UN Equity | DT2: ATO UN Equity | DU2: GWW UN Equity | DV2: HAL UN Equity | DW2: LHX UN Equity | DX2: DOC UN Equity | DY2: PODD UW Equity | DZ2: FTV UN Equity | EA2: HSY UN Equity | EB2: SYF UN Equity | EC2: HRL UN Equity | ED2: AJG UN Equity | EE2: MDLZ UW Equity | EF2: CNP UN Equity | EG2: HUM UN Equity | EH2: WTW UW Equity | EI2: ITW UN Equity | EJ2: CDW UW Equity | EK2: TT UN Equity | EL2: IFF UN Equity | EM2: GNRC UN Equity | EN2: NXPI UW Equity | EO2: K UN Equity | EP2: BR UN Equity | EQ2: KIM UN Equity | ER2: ORCL UN Equity | ES2: KR UN Equity | ET2: LEN UN Equity | EU2: LLY UN Equity | EV2: CHTR UW Equity | EW2: L UN Equity | EX2: LOW UN Equity | EY2: HUBB UN Equity | EZ2: IEX UN Equity | FA2: MMC UN Equity | FB2: MAS UN Equity | FC2: SPGI UN Equity | FD2: MDT UN Equity | FE2: VTRS UW Equity | FF2: CVS UN Equity | FG2: DD UN Equity | FH2: MU UW Equity | FI2: MSI UN Equity | FJ2: CBOE UF Equity | FK2: NEM UN Equity | FL2: NKE UN Equity | FM2: NI UN Equity | FN2: NSC UN Equity | FO2: PFG UW Equity | FP2: ES UN Equity | FQ2: NOC UN Equity | FR2: WFC UN Equity | FS2: NUE UN Equity | FT2: OXY UN Equity | FU2: OMC UN Equity | FV2: OKE UN Equity | FW2: RJF UN Equity | FX2: PCG UN Equity | FY2: PH UN Equity | FZ2: ROL UN Equity | GA2: PPL UN Equity | GB2: APTV UN Equity | GC2: COP UN Equity | GD2: PHM UN Equity | GE2: PNW UN Equity | GF2: PNC UN Equity | GG2: PPG UN Equity | GH2: PGR UN Equity | GI2: PEG UN Equity | GJ2: EIX UN Equity | GK2: SLB UN Equity | GL2: SCHW UN Equity | GM2: SHW UN Equity | GN2: WST UN Equity | GO2: SJM UN Equity | GP2: SNA UN Equity | GQ2: AME UN Equity | GR2: UBER UN Equity | GS2: SO UN Equity | GT2: TFC UN Equity | GU2: LUV UN Equity | GV2: WRB UN Equity | GW2: SWK UN Equity | GX2: PSA UN Equity | GY2: ANET UN Equity | GZ2: SYY UN Equity | HA2: CTVA UN Equity | HB2: TXN UW Equity | HC2: TXT UN Equity | HD2: TMO UN Equity | HE2: TJX UN Equity | HF2: GL UN Equity | HG2: JCI UN Equity | HH2: ULTA UW Equity | HI2: UNP UN Equity | HJ2: KEYS UN Equity | HK2: UNH UN Equity | HL2: BX UN Equity | HM2: VTR UN Equity | HN2: LH UN Equity | HO2: VMC UN Equity | HP2: WY UN Equity | HQ2: WMB UN Equity | HR2: WEC UN Equity | HS2: ADBE UW Equity | HT2: VST UN Equity | HU2: AES UN Equity | HV2: EXPD UN Equity | HW2: AMGN UW Equity | HX2: AAPL UW Equity | HY2: ADSK UW Equity | HZ2: CTAS UW Equity | IA2: CMCSA UW Equity | IB2: TAP UN Equity | IC2: KLAC UW Equity | ID2: MAR UW Equity | IE2: MKC UN Equity | IF2: PCAR UW Equity | IG2: COST UW Equity | IH2: SYK UN Equity | II2: TSN UN Equity | IJ2: LW UN Equity | IK2: AMAT UW Equity | IL2: CAH UN Equity | IM2: CINF UW Equity | IN2: DHI UN Equity | IO2: EA UW Equity | IP2: ERIE UW Equity | IQ2: FICO UN Equity | IR2: FAST UW Equity | IS2: MTB UN Equity | IT2: XEL UW Equity | IU2: FITB UW Equity | IV2: GILD UW Equity | IW2: HAS UW Equity | IX2: HBAN UW Equity | IY2: WELL UN Equity | IZ2: BIIB UW Equity | JA2: NTRS UW Equity | JB2: PKG UN Equity | JC2: PAYX UW Equity | JD2: QCOM UW Equity | JE2: ROST UW Equity | JF2: IDXX UW Equity | JG2: SBUX UW Equity | JH2: KEY UN Equity | JI2: FOXA UW Equity | JJ2: FOX UW Equity | JK2: STT UN Equity | JL2: NCLH UN Equity | JM2: USB UN Equity | JN2: AOS UN Equity | JO2: GEN UW Equity | JP2: TROW UW Equity | JQ2: WM UN Equity | JR2: STZ UN Equity | JS2: IVZ UN Equity | JT2: INTU UW Equity | JU2: MS UN Equity | JV2: MCHP UW Equity | JW2: CRWD UW Equity | JX2: CB UN Equity | JY2: HOLX UW Equity | JZ2: CFG UN Equity | KA2: JBL UN Equity | KB2: ORLY UW Equity | KC2: ALL UN Equity | KD2: EQR UN Equity | KE2: INCY UW Equity | KF2: SPG UN Equity | KG2: AVB UN Equity | KH2: PRU UN Equity | KI2: UPS UN Equity | KJ2: STE UN Equity | KK2: MCK UN Equity | KL2: LMT UN Equity | KM2: COR UN Equity | KN2: COF UN Equity | KO2: WAT UN Equity | KP2: NDSN UW Equity | KQ2: DLTR UW Equity | KR2: DRI UN Equity | KS2: NVR UN Equity | KT2: NTAP UW Equity | KU2: ODFL UW Equity | KV2: DVA UN Equity | KW2: HIG UN Equity | KX2: IRM UN Equity | KY2: EL UN Equity | KZ2: CDNS UW Equity | LA2: TYL UN Equity | LB2: UHS UN Equity | LC2: SWKS UW Equity | LD2: DGX UN Equity | LE2: ROK UN Equity | LF2: KHC UW Equity | LG2: AMT UN Equity | LH2: REGN UW Equity | LI2: AMZN UW Equity | LJ2: JKHY UW Equity | LK2: RL UN Equity | LL2: BXP UN Equity | LM2: APH UN Equity | LN2: HWM UN Equity | LO2: VLO UN Equity | LP2: SNPS UW Equity | LQ2: CHRW UW Equity | LR2: ACN UN Equity | LS2: TDG UN Equity | LT2: YUM UN Equity | LU2: PLD UN Equity | LV2: FE UN Equity | LW2: VRSN UW Equity | LX2: PWR UN Equity | LY2: HSIC UW Equity | LZ2: AEE UN Equity | MA2: FDS UN Equity | MB2: NVDA UW Equity | MC2: CTSH UW Equity | MD2: ISRG UW Equity | ME2: TTWO UW Equity | MF2: RSG UN Equity | MG2: EBAY UW Equity | MH2: GS UN Equity | MI2: SBAC UW Equity | MJ2: SRE UN Equity | MK2: MCO UN Equity | ML2: ON UW Equity | MM2: BKNG UW Equity | MN2: FFIV UW Equity | MO2: AKAM UW Equity | MP2: CRL UN Equity | MQ2: DVN UN Equity | MR2: TECH UW Equity | MS2: GOOGL UW Equity | MT2: ALLE UN Equity | MU2: NFLX UW Equity | MV2: A UN Equity | MW2: TRMB UW Equity | MX2: ELV UN Equity | MY2: CME UW Equity | MZ2: DTE UN Equity | NA2: NDAQ UW Equity | NB2: PM UN Equity | NC2: IR UN Equity | ND2: CRM UN Equity | NE2: HII UN Equity | NF2: MET UN Equity | NG2: TPR UN Equity | NH2: CSX UW Equity | NI2: EW UN Equity | NJ2: AMP UN Equity | NK2: ZBRA UW Equity | NL2: ZBH UN Equity | NM2: CPT UN Equity | NN2: CBRE UN Equity | NO2: MA UN Equity | NP2: DDOG UW Equity | NQ2: ICE UN Equity | NR2: FIS UN Equity | NS2: CMG UN Equity | NT2: WYNN UW Equity | NU2: LYV UN Equity | NV2: AIZ UN Equity | NW2: NRG UN Equity | NX2: MNST UW Equity | NY2: RF UN Equity | NZ2: MOS UN Equity | OA2: EXPE UW Equity | OB2: CF UN Equity | OC2: LDOS UN Equity | OD2: GOOG UW Equity | OE2: TKO UN Equity | OF2: FSLR UW Equity | OG2: V UN Equity | OH2: MAA UN Equity | OI2: XYL UN Equity | OJ2: MPC UN Equity | OK2: TSCO UW Equity | OL2: AMD UW Equity | OM2: RMD UN Equity | ON2: MTD UN Equity | OO2: VICI UN Equity | OP2: CPRT UW Equity | OQ2: J UN Equity | OR2: ALB UN Equity | OS2: FTNT UW Equity | OT2: MRNA UW Equity | OU2: ESS UN Equity | OV2: CSGP UW Equity | OW2: O UN Equity | OX2: WAB UN Equity | OY2: POOL UW Equity | OZ2: WDC UW Equity | PA2: PEP UW Equity | PB2: TEL UN Equity | PC2: FANG UW Equity | PD2: NOW UN Equity | PE2: CHD UN Equity | PF2: FRT UN Equity | PG2: MGM UN Equity | PH2: INVH UN Equity | PI2: PTC UW Equity | PJ2: JBHT UW Equity | PK2: LRCX UW Equity | PL2: MHK UN Equity | PM2: PNR UN Equity | PN2: VRTX UW Equity | PO2: AMCR UN Equity | PP2: META UW Equity | PQ2: TMUS UW Equity | PR2: URI UN Equity | PS2: ARE UN Equity | PT2: DAL UN Equity | PU2: UAL UW Equity | PV2: STX UW Equity | PW2: NWS UW Equity | PX2: CNC UN Equity | PY2: XYZ UN Equity | PZ2: APO UN Equity | QA2: MLM UN Equity | QB2: TER UW Equity | QC2: PYPL UW Equity | QD2: TSLA UW Equity | QE2: BLK UN Equity | QF2: KKR UN Equity | QG2: ACGL UW Equity | QH2: DOW UN Equity | QI2: EG UN Equity | QJ2: TDY UN Equity | QK2: NWSA UW Equity | QL2: EXC UW Equity | QM2: GPN UN Equity | QN2: CCI UN Equity | QO2: ALGN UW Equity | QP2: TRGP UN Equity | QQ2: BG UN Equity | QR2: LKQ UW Equity | QS2: DECK UN Equity | QT2: WDAY UW Equity | QU2: ZTS UN Equity | QV2: EQIX UW Equity | QW2: DLR UN Equity | QX2: MOH UN Equity | QY2: LVS UN Equity | QZ2: SOLV UN Equity | RA2: SMCI UW Equity | RB2: LIN UW Equity | RC2: CARR UN Equity | RD2: OTIS UN Equity | RE2: ABNB UW Equity | RF2: EXE UW Equity | RG2: DASH UW Equity | RH2: VLTO UN Equity | RI2: COO UW Equity | RJ2: CEG UW Equity | RK2: APP UW Equity | RL2: KDP UW Equity | RM2: HST UW Equity | RN2: CPB UW Equity | RO2: EVRG UW Equity | RP2: MTCH UW Equity | RQ2: WBD UW Equity | RR2: ROP UW Equity | RS2: SW UN Equity | RT2: BKR UW Equity | RU2: APA UW Equity | RV2: PLTR UW Equity | RW2: PANW UW Equity | RX2: AEP UW Equity | RY2: GEHC UW Equity | RZ2: HON UW Equity | SA2: HOOD UW Equity | SB2: DPZ UW Equity | SC2: GEV UN Equity | SD2: KVUE UN Equity | SE2: COIN UW Equity
A3: Date | B3: 45657 | C3: 74.27 | D3: 296.79 | E3: 39.99 | F3: 1105.96 | G3: 231.84 | H3: 177 | I3: 362.76 | J3: 239.71 | K3: 144.84 | L3: 62.26 | M3: 177.7 | N3: 111.35 | O3: 338.42 | P3: 149.6 | Q3: 107.57 | R3: 113.93 | S3: 166.79 | T3: 32.63 | U3: 388.99 | V3: 591.7 | W3: 219.83 | X3: 144.62 | Y3: 382.41 | Z3: 289.89 | AA3: 99.48 | AB3: 129.09 | AC3: 124.49 | AD3: 43.95 | AE3: 26.53 | AF3: 167.65 | AG3: 22.77 | AH3: 240.89 | AI3: 115.72 | AJ3: 212.46 | AK3: 90.35 | AL3: 59.2 | AM3: 20.05 | AN3: 53.27 | AO3: 421.5 | AP3: 75.82 | AQ3: 276.14 | AR3: 27.4 | AS3: 70.39 | AT3: 72.8 | AU3: 52.29 | AV3: 300.15 | AW3: 53.82 | AX3: 21.35 | AY3: 113.11 | AZ3: 103.44 | BA3: 290.04 | BB3: 230.69 | BC3: 44.1675 | BD3: 609.3 | BE3: 50.52 | BF3: 453.9 | BG3: 292.73 | BH3: 275.43 | BI3: 3202 | BJ3: 187.13 | BK3: 600.01 | BL3: 55.13 | BM3: 594.32 | BN3: 72.64 | BO3: 76.83 | BP3: 29.16 | BQ3: 226.87 | BR3: 453.28 | BS3: 85.8 | BT3: 89.32 | BU3: 56.56 | BV3: 37.98 | BW3: 25.54 | BX3: 247.16 | BY3: 24.92 | BZ3: 142.93 | CA3: 43.41 | CB3: 162.41 | CC3: 204.97 | CD3: 66.65 | CE3: 90.91 | CF3: 233.82 | CG3: 27.75 | CH3: 89.23 | CI3: 47.52 | CJ3: 197.37 | CK3: 348.6 | CL3: 229.55 | CM3: 135.18 | CN3: 185.18 | CO3: 423.7 | CP3: 53.86 | CQ3: 117.53 | CR3: 187.6 | CS3: 59.14 | CT3: 114.07 | CU3: 107.74 | CV3: 73.93 | CW3: 331.87 | CX3: 234.32 | CY3: 111.61 | CZ3: 115.24 | DA3: 123.93 | DB3: 122.58 | DC3: 359.16 | DD3: 75.82 | DE3: 254.85 | DF3: 46.11 | DG3: 196.51 | DH3: 484.47 | DI3: 281.33 | DJ3: 102.02 | DK3: 9.9 | DL3: 71.69 | DM3: 20.29 | DN3: 206.26 | DO3: 38.08 | DP3: 77.77 | DQ3: 263.49 | DR3: 63.77 | DS3: 116.76 | DT3: 139.27 | DU3: 1054.05 | DV3: 27.19 | DW3: 210.28 | DX3: 20.27 | DY3: 261.07 | DZ3: 56.5014 | EA3: 169.35 | EB3: 65 | EC3: 31.37 | ED3: 283.85 | EE3: 59.73 | EF3: 31.73 | EG3: 253.71 | EH3: 313.24 | EI3: 253.56 | EJ3: 174.04 | EK3: 369.35 | EL3: 84.55 | EM3: 155.05 | EN3: 207.85 | EO3: 80.97 | EP3: 226.09 | EQ3: 23.43 | ER3: 166.64 | ES3: 61.15 | ET3: 136.37 | EU3: 772 | EV3: 342.77 | EW3: 84.69 | EX3: 246.8 | EY3: 418.89 | EZ3: 209.29 | FA3: 212.41 | FB3: 72.57 | FC3: 498.03 | FD3: 79.88 | FE3: 12.45 | FF3: 44.89 | FG3: 31.8915 | FH3: 84.16 | FI3: 462.23 | FJ3: 195.4 | FK3: 37.22 | FL3: 75.67 | FM3: 36.76 | FN3: 234.7 | FO3: 77.41 | FP3: 57.43 | FQ3: 469.29 | FR3: 70.24 | FS3: 116.71 | FT3: 49.41 | FU3: 86.04 | FV3: 100.4 | FW3: 155.33 | FX3: 20.18 | FY3: 636.03 | FZ3: 46.35 | GA3: 32.46 | GB3: 60.48 | GC3: 99.17 | GD3: 108.9 | GE3: 84.77 | GF3: 192.85 | GG3: 119.45 | GH3: 239.61 | GI3: 84.49 | GJ3: 79.84 | GK3: 38.34 | GL3: 74.01 | GM3: 339.93 | GN3: 327.56 | GO3: 110.12 | GP3: 339.48 | GQ3: 180.26 | GR3: 60.32 | GS3: 82.32 | GT3: 43.38 | GU3: 33.62 | GV3: 58.52 | GW3: 80.29 | GX3: 299.44 | GY3: 110.53 | GZ3: 76.46 | HA3: 56.96 | HB3: 187.51 | HC3: 76.49 | HD3: 520.23 | HE3: 120.81 | HF3: 111.52 | HG3: 78.93 | HH3: 434.93 | HI3: 228.04 | HJ3: 160.63 | HK3: 505.86 | HL3: 172.42 | HM3: 58.89 | HN3: 229.32 | HO3: 257.23 | HP3: 28.15 | HQ3: 54.12 | HR3: 94.04 | HS3: 444.68 | HT3: 137.87 | HU3: 12.87 | HV3: 110.77 | HW3: 260.64 | HX3: 250.42 | HY3: 295.57 | HZ3: 182.7 | IA3: 37.53 | IB3: 57.32 | IC3: 630.12 | ID3: 278.94 | IE3: 76.24 | IF3: 104.02 | IG3: 916.27 | IH3: 360.05 | II3: 57.44 | IJ3: 66.83 | IK3: 162.63 | IL3: 118.27 | IM3: 143.7 | IN3: 139.82 | IO3: 146.3 | IP3: 412.23 | IQ3: 1990.93 | IR3: 35.955 | IS3: 188.01 | IT3: 67.52 | IU3: 42.28 | IV3: 92.37 | IW3: 55.91 | IX3: 16.27 | IY3: 126.03 | IZ3: 152.92 | JA3: 102.5 | JB3: 225.13 | JC3: 140.22 | JD3: 153.62 | JE3: 151.27 | JF3: 413.44 | JG3: 91.25 | JH3: 17.14 | JI3: 48.58 | JJ3: 45.74 | JK3: 98.15 | JL3: 25.73 | JM3: 47.83 | JN3: 68.21 | JO3: 27.38 | JP3: 113.09 | JQ3: 201.79 | JR3: 221 | JS3: 17.48 | JT3: 628.5 | JU3: 125.72 | JV3: 57.35 | JW3: 342.16 | JX3: 276.3 | JY3: 72.09 | JZ3: 43.76 | KA3: 143.9 | KB3: 79.053 | KC3: 192.79 | KD3: 71.76 | KE3: 69.07 | KF3: 172.21 | KG3: 219.97 | KH3: 118.53 | KI3: 126.1 | KJ3: 205.56 | KK3: 569.91 | KL3: 485.94 | KM3: 224.68 | KN3: 178.32 | KO3: 370.98 | KP3: 209.24 | KQ3: 74.94 | KR3: 186.69 | KS3: 8178.9 | KT3: 116.08 | KU3: 176.4 | KV3: 149.55 | KW3: 109.4 | KX3: 105.11 | KY3: 74.98 | KZ3: 300.46 | LA3: 576.64 | LB3: 179.42 | LC3: 88.68 | LD3: 150.86 | LE3: 285.79 | LF3: 30.71 | LG3: 183.41 | LH3: 712.33 | LI3: 219.39 | LJ3: 175.3 | LK3: 230.98 | LL3: 74.36 | LM3: 69.45 | LN3: 109.37 | LO3: 122.59 | LP3: 485.36 | LQ3: 103.32 | LR3: 351.79 | LS3: 1267.28 | LT3: 134.16 | LU3: 105.7 | LV3: 39.78 | LW3: 206.96 | LX3: 316.05 | LY3: 69.2 | LZ3: 89.14 | MA3: 480.28 | MB3: 134.29 | MC3: 76.9 | MD3: 521.96 | ME3: 184.08 | MF3: 201.18 | MG3: 61.95 | MH3: 572.62 | MI3: 203.8 | MJ3: 87.72 | MK3: 473.37 | ML3: 63.05 | MM3: 4968.42 | MN3: 251.47 | MO3: 95.65 | MP3: 184.6 | MQ3: 32.73 | MR3: 72.03 | MS3: 189.3 | MT3: 130.68 | MU3: 89.132 | MV3: 134.34 | MW3: 70.66 | MX3: 368.9 | MY3: 232.23 | MZ3: 120.75 | NA3: 77.31 | NB3: 120.35 | NC3: 90.46 | ND3: 334.33 | NE3: 188.97 | NF3: 81.88 | NG3: 65.33 | NH3: 32.27 | NI3: 74.03 | NJ3: 532.43 | NK3: 386.22 | NL3: 105.63 | NM3: 116.04 | NN3: 131.29 | NO3: 526.57 | NP3: 142.89 | NQ3: 149.01 | NR3: 80.77 | NS3: 60.3 | NT3: 86.16 | NU3: 129.5 | NV3: 213.22 | NW3: 90.22 | NX3: 52.56 | NY3: 23.52 | NZ3: 24.58 | OA3: 186.33 | OB3: 85.32 | OC3: 144.06 | OD3: 190.44 | OE3: 142.11 | OF3: 176.24 | OG3: 316.04 | OH3: 154.57 | OI3: 116.02 | OJ3: 139.5 | OK3: 53.06 | OL3: 120.79 | OM3: 228.69 | ON3: 1223.68 | OO3: 29.21 | OP3: 57.39 | OQ3: 132.2568 | OR3: 86.08 | OS3: 94.48 | OT3: 41.58 | OU3: 285.44 | OV3: 71.59 | OW3: 53.41 | OX3: 189.59 | OY3: 340.94 | OZ3: 45.0579 | PA3: 152.06 | PB3: 142.97 | PC3: 163.83 | PD3: 1060.12 | PE3: 104.71 | PF3: 111.95 | PG3: 34.65 | PH3: 31.97 | PI3: 183.87 | PJ3: 170.66 | PK3: 72.23 | PL3: 119.13 | PM3: 100.64 | PN3: 402.7 | PO3: 9.41 | PP3: 585.51 | PQ3: 220.73 | PR3: 704.44 | PS3: 97.55 | PT3: 60.5 | PU3: 97.1 | PV3: 86.31 | PW3: 30.43 | PX3: 60.58 | PY3: 84.99 | PZ3: 165.16 | QA3: 516.5 | QB3: 125.92 | QC3: 85.35 | QD3: 403.84 | QE3: 1025.11 | QF3: 147.91 | QG3: 92.35 | QH3: 40.13 | QI3: 362.46 | QJ3: 464.13 | QK3: 27.54 | QL3: 37.64 | QM3: 112.06 | QN3: 90.76 | QO3: 208.51 | QP3: 178.5 | QQ3: 77.76 | QR3: 36.75 | QS3: 203.09 | QT3: 258.03 | QU3: 162.93 | QV3: 942.89 | QW3: 177.33 | QX3: 291.05 | QY3: 51.36 | QZ3: 66.06 | RA3: 30.48 | RB3: 418.67 | RC3: 68.26 | RD3: 92.61 | RE3: 131.41 | RF3: 99.55 | RG3: 167.75 | RH3: 101.85 | RI3: 91.93 | RJ3: 223.71 | RK3: 323.83 | RL3: 32.12 | RM3: 17.52 | RN3: 41.88 | RO3: 61.55 | RP3: 32.71 | RQ3: 10.57 | RR3: 519.85 | RS3: 53.86 | RT3: 41.02 | RU3: 23.09 | RV3: 75.63 | RW3: 181.96 | RX3: 92.23 | RY3: 78.18 | RZ3: 212.8257 | SA3: 37.26 | SB3: 419 | SC3: 328.93 | SD3: 21.35 | SE3: 248.3
B4: 45660 | C4: 72.77 | D4: 303.08 | E4: 40.26 | F4: 1211.03 | G4: 232.55 | H4: 169.9 | I4: 363.79 | J4: 243.28 | K4: 147.85 | L4: 61.75 | M4: 181.22 | N4: 111.16 | O4: 341.85 | P4: 151.04 | Q4: 107.86 | R4: 116.09 | S4: 171.96 | T4: 33.14 | U4: 389.18 | V4: 619.87 | W4: 222.65 | X4: 144.19 | Y4: 378.18 | Z4: 294.78 | AA4: 99.14 | AB4: 129.87 | AC4: 123.77 | AD4: 44.81 | AE4: 26.59 | AF4: 165.13 | AG4: 22.67 | AH4: 242.29 | AI4: 115.87 | AJ4: 215.37 | AK4: 90.78 | AL4: 58.86 | AM4: 20.56 | AN4: 51.77 | AO4: 423.35 | AP4: 74.67 | AQ4: 280.7 | AR4: 28.27 | AS4: 71 | AT4: 72.81 | AU4: 53.14 | AV4: 296.7 | AW4: 52.85 | AX4: 21.82 | AY4: 113.83 | AZ4: 103.16 | BA4: 283.91 | BB4: 228.94 | BC4: 45.93 | BD4: 612.71 | BE4: 50.05 | BF4: 473.65 | BG4: 291.69 | BH4: 276.28 | BI4: 3268.78 | BJ4: 185.09 | BK4: 601.48 | BL4: 54.03 | BM4: 601.06 | BN4: 72.52 | BO4: 76.93 | BP4: 29.5 | BQ4: 228.46 | BR4: 453.56 | BS4: 83.62 | BT4: 90.69 | BU4: 56.57 | BV4: 36.25 | BW4: 26.24 | BX4: 246.52 | BY4: 24.38 | BZ4: 144.03 | CA4: 43.08 | CB4: 162.89 | CC4: 203.86 | CD4: 66.61 | CE4: 90.15 | CF4: 230.72 | CG4: 27.65 | CH4: 89.24 | CI4: 47.5 | CJ4: 200.39 | CK4: 354.35 | CL4: 234.84 | CM4: 135.79 | CN4: 192.7 | CO4: 422.22 | CP4: 54.73 | CQ4: 121.84 | CR4: 188.03 | CS4: 58.34 | CT4: 113.15 | CU4: 107.78 | CV4: 73.03 | CW4: 342.58 | CX4: 231.93 | CY4: 113.6 | CZ4: 119.91 | DA4: 123.44 | DB4: 126.57 | DC4: 353.98 | DD4: 76.68 | DE4: 253.39 | DF4: 47.02 | DG4: 197.39 | DH4: 485.97 | DI4: 274.41 | DJ4: 101.59 | DK4: 9.88 | DL4: 71.99 | DM4: 20.41 | DN4: 207.15 | DO4: 37.71 | DP4: 81.07 | DQ4: 263.37 | DR4: 63.88 | DS4: 116.86 | DT4: 138.79 | DU4: 1053.99 | DV4: 27.68 | DW4: 209.75 | DX4: 20.42 | DY4: 266.3 | DZ4: 57.1794 | EA4: 169.03 | EB4: 66.78 | EC4: 31.36 | ED4: 280.4 | EE4: 59.86 | EF4: 31.64 | EG4: 262.47 | EH4: 309.04 | EI4: 252.29 | EJ4: 174.23 | EK4: 381.11 | EL4: 82.52 | EM4: 158.88 | EN4: 208.86 | EO4: 81.21 | EP4: 229.23 | EQ4: 23.17 | ER4: 166.32 | ES4: 61.46 | ET4: 135.88 | EU4: 781.98 | EV4: 358.35 | EW4: 84.35 | EX4: 248.48 | EY4: 430.96 | EZ4: 207.02 | FA4: 211.27 | FB4: 72.2 | FC4: 499.57 | FD4: 80.95 | FE4: 12.28 | FF4: 45.77 | FG4: 31.2641 | FH4: 89.87 | FI4: 461.84 | FJ4: 195.24 | FK4: 38.11 | FL4: 73.31 | FM4: 36.39 | FN4: 235.88 | FO4: 77.91 | FP4: 57.31 | FQ4: 467.82 | FR4: 71.31 | FS4: 115.45 | FT4: 50.51 | FU4: 85.89 | FV4: 102.9 | FW4: 157.72 | FX4: 20.4 | FY4: 637.68 | FZ4: 46.17 | GA4: 32.27 | GB4: 60.53 | GC4: 101.09 | GD4: 110.05 | GE4: 84.25 | GF4: 195.63 | GG4: 114.27 | GH4: 242.22 | GI4: 86.25 | GJ4: 79.8 | GK4: 38.59 | GL4: 74.45 | GM4: 336.54 | GN4: 335.56 | GO4: 111.53 | GP4: 336.07 | GQ4: 179.57 | GR4: 64.59 | GS4: 82.32 | GT4: 44.1 | GU4: 33.61 | GV4: 57.93 | GW4: 80.76 | GX4: 300.45 | GY4: 115.2 | GZ4: 75.43 | HA4: 55.94 | HB4: 190.51 | HC4: 75.73 | HD4: 532.02 | HE4: 120.73 | HF4: 111.51 | HG4: 79.92 | HH4: 431.35 | HI4: 231.5 | HJ4: 163.8 | HK4: 513 | HL4: 175.91 | HM4: 58.31 | HN4: 229.15 | HO4: 257.13 | HP4: 28.36 | HQ4: 56.6 | HR4: 93.79 | HS4: 430.57 | HT4: 162.36 | HU4: 13.23 | HV4: 111.28 | HW4: 261.22 | HX4: 243.36 | HY4: 294.06 | HZ4: 185.85 | IA4: 37.67 | IB4: 55.27 | IC4: 657.01 | ID4: 275.28 | IE4: 75.85 | IF4: 104.9 | IG4: 916.58 | IH4: 361.52 | II4: 58.18 | IJ4: 65.53 | IK4: 170.06 | IL4: 119.3 | IM4: 142.1 | IN4: 139.89 | IO4: 146.29 | IP4: 414.7 | IQ4: 1966.26 | IR4: 35.845 | IS4: 191.54 | IT4: 66.69 | IU4: 42.39 | IV4: 91.41 | IW4: 56.8 | IX4: 16.45 | IY4: 125.82 | IZ4: 152.21 | JA4: 103.28 | JB4: 225.88 | JC4: 139.67 | JD4: 157.83 | JE4: 154.25 | JF4: 415.53 | JG4: 92.58 | JH4: 17.29 | JI4: 49.32 | JJ4: 46.72 | JK4: 97.67 | JL4: 25.42 | JM4: 48.86 | JN4: 68.6 | JO4: 27.5 | JP4: 114.69 | JQ4: 201.65 | JR4: 221.92 | JS4: 17.75 | JT4: 630.23 | JU4: 125.94 | JV4: 57.67 | JW4: 359.02 | JX4: 271.73 | JY4: 73.19 | JZ4: 44.56 | KA4: 149.66 | KB4: 80.281 | KC4: 191.45 | KD4: 70.9 | KE4: 69.63 | KF4: 176.07 | KG4: 219.17 | KH4: 119.14 | KI4: 123.79 | KJ4: 204.12 | KK4: 577.44 | KL4: 481.82 | KM4: 229.2 | KN4: 180.43 | KO4: 371.76 | KP4: 207.56 | KQ4: 73.36 | KR4: 187.72 | KS4: 8070.6 | KT4: 116.94 | KU4: 180.91 | KV4: 152.82 | KW4: 109.5 | KX4: 105.7 | KY4: 72.16 | KZ4: 303.86 | LA4: 584.17 | LB4: 178.89 | LC4: 88.85 | LD4: 151.92 | LE4: 282.79 | LF4: 30.61 | LG4: 182.56 | LH4: 718.15 | LI4: 224.19 | LJ4: 173.7 | LK4: 234.49 | LL4: 74.91 | LM4: 70.1 | LN4: 112.76 | LO4: 124.26 | LP4: 493.71 | LQ4: 104.44 | LR4: 353.85 | LS4: 1275.56 | LT4: 133.44 | LU4: 105.63 | LV4: 39.92 | LW4: 205.62 | LX4: 326.52 | LY4: 69.09 | LZ4: 88.85 | MA4: 475.06 | MB4: 144.47 | MC4: 76.38 | MD4: 535.295 | ME4: 188.75 | MF4: 201.04 | MG4: 61.61 | MH4: 580.13 | MI4: 201.8 | MJ4: 87.67 | MK4: 479.15 | ML4: 63.91 | MM4: 4903.85 | MN4: 254.36 | MO4: 93.56 | MP4: 185.8 | MQ4: 33.93 | MR4: 73.79 | MS4: 191.79 | MT4: 130.18 | MU4: 88.105 | MV4: 135.69 | MW4: 70.57 | MX4: 371.56 | MY4: 232.5 | MZ4: 121.58 | NA4: 78.22 | NB4: 122.02 | NC4: 92.49 | ND4: 332.9 | NE4: 188.08 | NF4: 82.21 | NG4: 66.77 | NH4: 32.34 | NI4: 73.91 | NJ4: 535.84 | NK4: 391.86 | NL4: 104.47 | NM4: 117.07 | NN4: 131.5 | NO4: 521.36 | NP4: 144.83 | NQ4: 149.84 | NR4: 80.26 | NS4: 59.7 | NT4: 83.32 | NU4: 129.49 | NV4: 211.85 | NW4: 98.5 | NX4: 52.39 | NY4: 23.62 | NZ4: 25.15 | OA4: 186.09 | OB4: 88.51 | OC4: 147.15 | OD4: 193.13 | OE4: 142.4 | OF4: 186.43 | OG4: 314.91 | OH4: 155.06 | OI4: 117.18 | OJ4: 142.74 | OK4: 51.93 | OL4: 125.37 | OM4: 231.67 | ON4: 1238.28 | OO4: 29.46 | OP4: 56.91 | OQ4: 132.435 | OR4: 87.79 | OS4: 97.47 | OT4: 42.18 | OU4: 284.25 | OV4: 72.25 | OW4: 53.28 | OX4: 190.45 | OY4: 337.27 | OZ4: 48.4128 | PA4: 149.65 | PB4: 142.4 | PC4: 170.96 | PD4: 1073.77 | PE4: 104.64 | PF4: 109.63 | PG4: 34.09 | PH4: 31.93 | PI4: 184.54 | PJ4: 175.82 | PK4: 75.11 | PL4: 117.31 | PM4: 101.06 | PN4: 407.11 | PO4: 9.33 | PP4: 604.63 | PQ4: 219.11 | PR4: 695.31 | PS4: 99.16 | PT4: 59 | PU4: 95.67 | PV4: 89.15 | PW4: 30.5 | PX4: 61.48 | PY4: 92.16 | PZ4: 169.06 | QA4: 516.67 | QB4: 130.6 | QC4: 87.6 | QD4: 410.44 | QE4: 1020.83 | QF4: 152.03 | QG4: 91.4 | QH4: 39.4 | QI4: 365.14 | QJ4: 459.7 | QK4: 27.55 | QL4: 38.05 | QM4: 112.58 | QN4: 89.99 | QO4: 208.26 | QP4: 186.17 | QQ4: 77.28 | QR4: 36.59 | QS4: 207.25 | QT4: 252.84 | QU4: 163.31 | QV4: 959.97 | QW4: 181.74 | QX4: 294.49 | QY4: 50.42 | QZ4: 67.12 | RA4: 33.33 | RB4: 413.5 | RC4: 69.26 | RD4: 92.89 | RE4: 135.71 | RF4: 100.01 | RG4: 174.96 | RH4: 100.8 | RI4: 91.79 | RJ4: 252.4 | RK4: 350.65 | RL4: 31.54 | RM4: 17.45 | RN4: 41.74 | RO4: 61.55 | RP4: 32.68 | RQ4: 10.57 | RR4: 514.64 | RS4: 52.3 | RT4: 42.66 | RU4: 23.42 | RV4: 79.89 | RW4: 183.25 | RX4: 92.05 | RY4: 80.52 | RZ4: 213.4192 | SA4: 41.35 | SB4: 438.08 | SC4: 354.03 | SD4: 21.2 | SE4: 270.65
B5: 45664 | C5: 73.9 | D5: 302.02 | E5: 38.92 | F5: 1258.29 | G5: 228.64 | H5: 172.51 | I5: 363 | J5: 243.17 | K5: 149.59 | L5: 60.84 | M5: 179.53 | N5: 111.39 | O5: 347.63 | P5: 148.43 | Q5: 108.75 | R5: 115.19 | S5: 172.31 | T5: 33.67 | U5: 384.23 | V5: 624.87 | W5: 223.96 | X5: 146.23 | Y5: 393.46 | Z5: 289.34 | AA5: 101.02 | AB5: 132.77 | AC5: 121.63 | AD5: 46.08 | AE5: 27.13 | AF5: 161.3 | AG5: 22.2 | AH5: 241.68 | AI5: 114.8 | AJ5: 215.87 | AK5: 90.81 | AL5: 58.93 | AM5: 20.01 | AN5: 51.98 | AO5: 422.37 | AP5: 74.17 | AQ5: 279.93 | AR5: 27.81 | AS5: 73.68 | AT5: 72.59 | AU5: 51.46 | AV5: 308.21 | AW5: 53.61 | AX5: 22.28 | AY5: 113.4 | AZ5: 102.84 | BA5: 286.33 | BB5: 225.33 | BC5: 47.7925 | BD5: 611.29 | BE5: 49.43 | BF5: 470.18 | BG5: 288.4 | BH5: 273.52 | BI5: 3259.91 | BJ5: 186.69 | BK5: 591.33 | BL5: 53.69 | BM5: 562.03 | BN5: 71.23 | BO5: 77.96 | BP5: 29.58 | BQ5: 232.15 | BR5: 452.92 | BS5: 84.28 | BT5: 91.99 | BU5: 57.14 | BV5: 36.23 | BW5: 26.36 | BX5: 241.38 | BY5: 23.84 | BZ5: 143.32 | CA5: 41.07 | CB5: 159.7 | CC5: 202.1 | CD5: 65.71 | CE5: 87.39 | CF5: 228.45 | CG5: 26.63 | CH5: 88 | CI5: 47.85 | CJ5: 195.57 | CK5: 359.98 | CL5: 239.1 | CM5: 139.25 | CN5: 195.37 | CO5: 413.27 | CP5: 54.03 | CQ5: 121.41 | CR5: 187.98 | CS5: 57.36 | CT5: 119.81 | CU5: 106.81 | CV5: 70.16 | CW5: 343.91 | CX5: 231.44 | CY5: 116.6 | CZ5: 121.27 | DA5: 120.68 | DB5: 127.56 | DC5: 348.44 | DD5: 75.96 | DE5: 245.5 | DF5: 48.15 | DG5: 202.65 | DH5: 491.48 | DI5: 275 | DJ5: 101.07 | DK5: 9.76 | DL5: 70.43 | DM5: 19.74 | DN5: 208.55 | DO5: 38.74 | DP5: 79.35 | DQ5: 259.65 | DR5: 60.89 | DS5: 116.61 | DT5: 136.63 | DU5: 1062.75 | DV5: 27.75 | DW5: 203 | DX5: 19.91 | DY5: 265.65 | DZ5: 57.7444 | EA5: 165.52 | EB5: 66.58 | EC5: 30.14 | ED5: 279.77 | EE5: 58.29 | EF5: 30.87 | EG5: 267.21 | EH5: 309 | EI5: 248.59 | EJ5: 180.98 | EK5: 379.96 | EL5: 82.56 | EM5: 161 | EN5: 212.58 | EO5: 81.35 | EP5: 226.32 | EQ5: 21.97 | ER5: 162.03 | ES5: 59.14 | ET5: 133.14 | EU5: 773.29 | EV5: 347.63 | EW5: 82.95 | EX5: 246.57 | EY5: 433.96 | EZ5: 208 | FA5: 209.98 | FB5: 71.7 | FC5: 491.35 | FD5: 79.87 | FE5: 12 | FF5: 45.78 | FG5: 31.4021 | FH5: 101.91 | FI5: 455.15 | FJ5: 190.84 | FK5: 38.16 | FL5: 72.09 | FM5: 35.77 | FN5: 237.76 | FO5: 78.3 | FP5: 56.08 | FQ5: 452.39 | FR5: 71.59 | FS5: 121.28 | FT5: 51.55 | FU5: 84.63 | FV5: 101.61 | FW5: 158.98 | FX5: 19.98 | FY5: 635.23 | FZ5: 45.75 | GA5: 32 | GB5: 61.82 | GC5: 101.67 | GD5: 107.83 | GE5: 83.2 | GF5: 194.77 | GG5: 115.86 | GH5: 242.28 | GI5: 85.41 | GJ5: 77.38 | GK5: 39.37 | GL5: 72.26 | GM5: 334.4 | GN5: 332.53 | GO5: 107.47 | GP5: 335.66 | GQ5: 178.69 | GR5: 66.15 | GS5: 81.09 | GT5: 43.97 | GU5: 32.88 | GV5: 57.5 | GW5: 81.65 | GX5: 298.2 | GY5: 115.29 | GZ5: 74.55 | HA5: 57.03 | HB5: 192.21 | HC5: 75.6 | HD5: 545.65 | HE5: 120.14 | HF5: 111.49 | HG5: 79.17 | HH5: 428.27 | HI5: 230.54 | HJ5: 166.13 | HK5: 514.25 | HL5: 171.34 | HM5: 57.07 | HN5: 235.1 | HO5: 251.98 | HP5: 28.01 | HQ5: 55.55 | HR5: 93.19 | HS5: 422.63 | HT5: 163.37 | HU5: 12.95 | HV5: 111.4 | HW5: 262.06 | HX5: 242.21 | HY5: 290.82 | HZ5: 188.72 | IA5: 37.18 | IB5: 55.19 | IC5: 689.3 | ID5: 269.78 | IE5: 74.32 | IF5: 109.56 | IG5: 921.37 | IH5: 355.18 | II5: 55.58 | IJ5: 61.68 | IK5: 177.82 | IL5: 121.4 | IM5: 142.31 | IN5: 137.84 | IO5: 144.67 | IP5: 402.26 | IQ5: 1935.16 | IR5: 36.155 | IS5: 192.04 | IT5: 65.64 | IU5: 42.86 | IV5: 90.63 | IW5: 57.11 | IX5: 16.55 | IY5: 124.24 | IZ5: 153.15 | JA5: 102.75 | JB5: 225.98 | JC5: 139.26 | JD5: 160.52 | JE5: 151.56 | JF5: 427.26 | JG5: 92.84 | JH5: 17.19 | JI5: 49.23 | JJ5: 46.81 | JK5: 97.72 | JL5: 25.51 | JM5: 48.7 | JN5: 68.3 | JO5: 26.98 | JP5: 113.12 | JQ5: 203.39 | JR5: 218.51 | JS5: 17.15 | JT5: 615.43 | JU5: 126.88 | JV5: 57.47 | JW5: 359.93 | JX5: 268.76 | JY5: 72.69 | JZ5: 44.7 | KA5: 152.73 | KB5: 79.981 | KC5: 186.04 | KD5: 67.45 | KE5: 73.19 | KF5: 174.17 | KG5: 211.23 | KH5: 119.18 | KI5: 124.98 | KJ5: 206.49 | KK5: 585.24 | KL5: 463.96 | KM5: 234.24 | KN5: 181.89 | KO5: 377.03 | KP5: 205.43 | KQ5: 75.01 | KR5: 184.34 | KS5: 7897 | KT5: 117.18 | KU5: 180.64 | KV5: 152.69 | KW5: 109.02 | KX5: 100.69 | KY5: 74.17 | KZ5: 301.67 | LA5: 563.54 | LB5: 186 | LC5: 92.66 | LD5: 153.64 | LE5: 281.31 | LF5: 29.77 | LG5: 177.17 | LH5: 730.3 | LI5: 222.11 | LJ5: 171.34 | LK5: 242.52 | LL5: 70.33 | LM5: 71.46 | LN5: 111.66 | LO5: 123.99 | LP5: 487.62 | LQ5: 104.05 | LR5: 356.39 | LS5: 1252.13 | LT5: 128.55 | LU5: 106.58 | LV5: 39.31 | LW5: 209.22 | LX5: 319.81 | LY5: 71.67 | LZ5: 87.96 | MA5: 460.68 | MB5: 140.14 | MC5: 75.62 | MD5: 531.88 | ME5: 181.75 | MF5: 203.05 | MG5: 63.17 | MH5: 580.12 | MI5: 195.89 | MJ5: 84.23 | MK5: 464 | ML5: 62.73 | MM5: 4796.1 | MN5: 257.29 | MO5: 92.54 | MP5: 189.76 | MQ5: 34.69 | MR5: 74.77 | MS5: 195.49 | MT5: 127.42 | MU5: 87.919 | MV5: 137.41 | MW5: 72.02 | MX5: 380.75 | MY5: 227.01 | MZ5: 120.38 | NA5: 76.36 | NB5: 121.4 | NC5: 89.16 | ND5: 324.93 | NE5: 189.05 | NF5: 82.14 | NG5: 67.36 | NH5: 32.19 | NI5: 73.64 | NJ5: 528.83 | NK5: 396.11 | NL5: 103.13 | NM5: 110.31 | NN5: 128.64 | NO5: 511.4 | NP5: 141.4 | NQ5: 146.44 | NR5: 79.16 | NS5: 57.99 | NT5: 82.45 | NU5: 129.64 | NV5: 207 | NW5: 96.73 | NX5: 51.55 | NY5: 23.85 | NZ5: 25.25 | OA5: 182.33 | OB5: 88.75 | OC5: 147.3 | OD5: 196.71 | OE5: 141.81 | OF5: 197.73 | OG5: 311.67 | OH5: 148.26 | OI5: 115.78 | OJ5: 141.66 | OK5: 53.87 | OL5: 127.33 | OM5: 236.4 | ON5: 1254.99 | OO5: 29.25 | OP5: 56.24 | OQ5: 130.5049 | OR5: 89.98 | OS5: 95.93 | OT5: 47.53 | OU5: 270.06 | OV5: 70.36 | OW5: 52.51 | OX5: 189.14 | OY5: 327.97 | OZ5: 49.0173 | PA5: 145.4 | PB5: 143.76 | PC5: 172.42 | PD5: 1054.15 | PE5: 102.8 | PF5: 104.9 | PG5: 33.23 | PH5: 30.96 | PI5: 183.09 | PJ5: 176.48 | PK5: 77.52 | PL5: 117.3 | PM5: 98.68 | PN5: 408.32 | PO5: 9.5 | PP5: 617.89 | PQ5: 212.335 | PR5: 685.41 | PS5: 97.36 | PT5: 61.18 | PU5: 101.21 | PV5: 89.6 | PW5: 30.46 | PX5: 62.61 | PY5: 87.68 | PZ5: 162.45 | QA5: 508.65 | QB5: 138.82 | QC5: 87.97 | QD5: 394.36 | QE5: 980.76 | QF5: 146.62 | QG5: 92.25 | QH5: 39.41 | QI5: 371.02 | QJ5: 458.78 | QK5: 27.6 | QL5: 37.53 | QM5: 112.28 | QN5: 87.46 | QO5: 217.56 | QP5: 187.82 | QQ5: 77.81 | QR5: 36.49 | QS5: 205.1 | QT5: 249.68 | QU5: 163.49 | QV5: 940.07 | QW5: 179.88 | QX5: 296.48 | QY5: 49.5 | QZ5: 69.41 | RA5: 34.38 | RB5: 414.95 | RC5: 68.21 | RD5: 92.12 | RE5: 131.29 | RF5: 102.68 | RG5: 170 | RH5: 101.65 | RI5: 92.69 | RJ5: 255.63 | RK5: 330.005 | RL5: 30.68 | RM5: 17.05 | RN5: 39.95 | RO5: 60.54 | RP5: 32.4 | RQ5: 10.51 | RR5: 507.1 | RS5: 52.11 | RT5: 43.4 | RU5: 23.66 | RV5: 69.99 | RW5: 175.51 | RX5: 90.47 | RY5: 83.37 | RZ5: 207.8699 | SA5: 40.56 | SB5: 410.9 | SC5: 368.52 | SD5: 21.05 | SE5: 264.33
B6: 45665 | C6: 73.03 | D6: 302.85 | E6: 38.94 | F6: 1275.94 | G6: 229.31 | H6: 171.76 | I6: 361.07 | J6: 243.13 | K6: 150.3 | L6: 61.71 | M6: 178.5 | N6: 109.76 | O6: 357.42 | P6: 148.01 | Q6: 106.93 | R6: 116.25 | S6: 172.89 | T6: 33.45 | U6: 387.2 | V6: 620.96 | W6: 223.18 | X6: 142.27 | Y6: 392.92 | Z6: 286.9 | AA6: 99.85 | AB6: 134.53 | AC6: 122.61 | AD6: 46.21 | AE6: 26.86 | AF6: 162.1 | AG6: 22.18 | AH6: 242.77 | AI6: 115.92 | AJ6: 220.44 | AK6: 91.8 | AL6: 59.2 | AM6: 19.88 | AN6: 51 | AO6: 424.56 | AP6: 71.62 | AQ6: 279.32 | AR6: 28.29 | AS6: 73.26 | AT6: 71.43 | AU6: 51.49 | AV6: 311.25 | AW6: 54.68 | AX6: 22.03 | AY6: 114.25 | AZ6: 103.57 | BA6: 285.25 | BB6: 227.22 | BC6: 47.7225 | BD6: 625.57 | BE6: 49.84 | BF6: 475.86 | BG6: 291.89 | BH6: 280.42 | BI6: 3303.35 | BJ6: 187.71 | BK6: 602.23 | BL6: 53.46 | BM6: 577.34 | BN6: 70.13 | BO6: 77.95 | BP6: 29.59 | BQ6: 234.43 | BR6: 451.84 | BS6: 84.19 | BT6: 95.95 | BU6: 56.81 | BV6: 35.99 | BW6: 27.15 | BX6: 243.3 | BY6: 24.18 | BZ6: 143.5 | CA6: 41.22 | CB6: 160.63 | CC6: 199.42 | CD6: 66.3 | CE6: 87.46 | CF6: 228.51 | CG6: 26.6 | CH6: 89.01 | CI6: 47.73 | CJ6: 197.14 | CK6: 359.75 | CL6: 238.09 | CM6: 138.22 | CN6: 194.59 | CO6: 410 | CP6: 54.6 | CQ6: 121.52 | CR6: 187.22 | CS6: 58.2 | CT6: 116.48 | CU6: 108.23 | CV6: 70.15 | CW6: 345.11 | CX6: 234.57 | CY6: 116.42 | CZ6: 119.31 | DA6: 120.3 | DB6: 128.46 | DC6: 352.45 | DD6: 76.6 | DE6: 248.11 | DF6: 49 | DG6: 204.32 | DH6: 495.44 | DI6: 274.9 | DJ6: 102.53 | DK6: 9.74 | DL6: 70.66 | DM6: 19.8 | DN6: 211.39 | DO6: 39.74 | DP6: 80.09 | DQ6: 261.47 | DR6: 60.97 | DS6: 116.53 | DT6: 139.52 | DU6: 1068.84 | DV6: 27.03 | DW6: 207.15 | DX6: 20.32 | DY6: 270.36 | DZ6: 57.8198 | EA6: 162.22 | EB6: 65.79 | EC6: 30.44 | ED6: 285.5 | EE6: 58.29 | EF6: 31.17 | EG6: 268.13 | EH6: 314.15 | EI6: 247.61 | EJ6: 181.34 | EK6: 386.1 | EL6: 82.07 | EM6: 158.62 | EN6: 209.72 | EO6: 81.54 | EP6: 229.49 | EQ6: 22.04 | ER6: 163.14 | ES6: 58.9 | ET6: 133.54 | EU6: 787.22 | EV6: 349.32 | EW6: 83.53 | EX6: 246.89 | EY6: 434.77 | EZ6: 208.79 | FA6: 211.35 | FB6: 72.48 | FC6: 495.86 | FD6: 82.68 | FE6: 11.96 | FF6: 46.01 | FG6: 31.1386 | FH6: 99.41 | FI6: 462.73 | FJ6: 192.99 | FK6: 39.13 | FL6: 71.29 | FM6: 36.45 | FN6: 236.91 | FO6: 78.33 | FP6: 56.72 | FQ6: 462.21 | FR6: 71.57 | FS6: 118.18 | FT6: 51.19 | FU6: 84.14 | FV6: 102.85 | FW6: 159.38 | FX6: 19.25 | FY6: 641.5 | FZ6: 46.35 | GA6: 32.17 | GB6: 60.8 | GC6: 101.62 | GD6: 110.46 | GE6: 83.61 | GF6: 194.68 | GG6: 115.69 | GH6: 243.59 | GI6: 85.28 | GJ6: 69.5 | GK6: 38.81 | GL6: 73 | GM6: 337.54 | GN6: 336.91 | GO6: 105.43 | GP6: 336.82 | GQ6: 178.45 | GR6: 64.91 | GS6: 83.02 | GT6: 43.95 | GU6: 32.88 | GV6: 58.09 | GW6: 81.56 | GX6: 295.46 | GY6: 115.51 | GZ6: 74.85 | HA6: 57.15 | HB6: 191.66 | HC6: 76 | HD6: 544.93 | HE6: 121.65 | HF6: 114.12 | HG6: 80.04 | HH6: 415.14 | HI6: 231.82 | HJ6: 164.89 | HK6: 524.52 | HL6: 173.97 | HM6: 58.27 | HN6: 234.31 | HO6: 255.28 | HP6: 27.68 | HQ6: 56.39 | HR6: 94.75 | HS6: 419.58 | HT6: 160.81 | HU6: 12.4 | HV6: 112.89 | HW6: 264.21 | HX6: 242.7 | HY6: 296.37 | HZ6: 192.65 | IA6: 37.17 | IB6: 55.59 | IC6: 686.2 | ID6: 273.53 | IE6: 74.52 | IF6: 108.5 | IG6: 927.37 | IH6: 364.1 | II6: 55.46 | IJ6: 60.89 | IK6: 176.99 | IL6: 122.53 | IM6: 141.71 | IN6: 139.9 | IO6: 144.2 | IP6: 401.35 | IQ6: 1964.42 | IR6: 36.47 | IS6: 191.14 | IT6: 66.39 | IU6: 42.42 | IV6: 89.14 | IW6: 57.11 | IX6: 16.43 | IY6: 126.48 | IZ6: 150.75 | JA6: 102.22 | JB6: 228.54 | JC6: 140.25 | JD6: 159.08 | JE6: 154.63 | JF6: 432.36 | JG6: 92.6 | JH6: 17.11 | JI6: 48.97 | JJ6: 46.61 | JK6: 97.73 | JL6: 25.92 | JM6: 48.52 | JN6: 68.68 | JO6: 27.11 | JP6: 112.84 | JQ6: 206.58 | JR6: 219.28 | JS6: 17.12 | JT6: 626.05 | JU6: 127.86 | JV6: 56.38 | JW6: 358.72 | JX6: 266.65 | JY6: 72.74 | JZ6: 44.78 | KA6: 153.95 | KB6: 80.383 | KC6: 191.8 | KD6: 67.52 | KE6: 73.13 | KF6: 174.69 | KG6: 212.37 | KH6: 118.43 | KI6: 126.76 | KJ6: 209.43 | KK6: 590.26 | KL6: 468.85 | KM6: 237.83 | KN6: 180.14 | KO6: 374.2 | KP6: 202.09 | KQ6: 71.97 | KR6: 183.73 | KS6: 8005.95 | KT6: 118.09 | KU6: 179.58 | KV6: 153.96 | KW6: 109.42 | KX6: 102.85 | KY6: 73.66 | KZ6: 302.73 | LA6: 575.22 | LB6: 190.33 | LC6: 92.63 | LD6: 154.03 | LE6: 279.56 | LF6: 29.66 | LG6: 179.19 | LH6: 733.59 | LI6: 222.13 | LJ6: 173.45 | LK6: 243.05 | LL6: 69.93 | LM6: 71.83 | LN6: 115.05 | LO6: 125.19 | LP6: 502 | LQ6: 103.61 | LR6: 357.73 | LS6: 1282.32 | LT6: 127.74 | LU6: 105.5 | LV6: 39.77 | LW6: 211.67 | LX6: 312.2 | LY6: 71.06 | LZ6: 89.24 | MA6: 458.46 | MB6: 140.11 | MC6: 76.02 | MD6: 544.02 | ME6: 183.74 | MF6: 206.96 | MG6: 69.4 | MH6: 580.02 | MI6: 199.71 | MJ6: 82.82 | MK6: 472.1 | ML6: 58.31 | MM6: 4872.42 | MN6: 258.84 | MO6: 93.36 | MP6: 187.91 | MQ6: 35.15 | MR6: 75.19 | MS6: 193.95 | MT6: 128.4 | MU6: 87.5 | MV6: 137 | MW6: 72.54 | MX6: 383.24 | MY6: 229.3 | MZ6: 121.01 | NA6: 78.02 | NB6: 121.86 | NC6: 89.23 | ND6: 326.9 | NE6: 189.66 | NF6: 82.82 | NG6: 68.53 | NH6: 32.2 | NI6: 74.15 | NJ6: 534.93 | NK6: 397 | NL6: 101.54 | NM6: 111.04 | NN6: 129.78 | NO6: 516.4 | NP6: 141.88 | NQ6: 146.57 | NR6: 79.35 | NS6: 57.92 | NT6: 81.17 | NU6: 130.31 | NV6: 205.42 | NW6: 98.54 | NX6: 51.6 | NY6: 23.82 | NZ6: 24.68 | OA6: 182.62 | OB6: 87.01 | OC6: 145.75 | OD6: 195.39 | OE6: 142.34 | OF6: 191.13 | OG6: 312.6 | OH6: 149.34 | OI6: 115.91 | OJ6: 142.33 | OK6: 54.39 | OL6: 121.84 | OM6: 236.17 | ON6: 1246.51 | OO6: 28.83 | OP6: 56.78 | OQ6: 131.7421 | OR6: 87.38 | OS6: 96.04 | OT6: 43.17 | OU6: 272.64 | OV6: 71.34 | OW6: 52.51 | OX6: 191.27 | OY6: 324.79 | OZ6: 48.4053 | PA6: 146.54 | PB6: 143.7 | PC6: 170.99 | PD6: 1049.08 | PE6: 102.57 | PF6: 104.56 | PG6: 32.69 | PH6: 30.67 | PI6: 184.36 | PJ6: 177.83 | PK6: 77.04 | PL6: 118.28 | PM6: 99.47 | PN6: 412.11 | PO6: 9.55 | PP6: 610.72 | PQ6: 215.52 | PR6: 670 | PS6: 97.39 | PT6: 61.42 | PU6: 103.72 | PV6: 88.69 | PW6: 30.42 | PX6: 63.17 | PY6: 86.75 | PZ6: 161.98 | QA6: 517.25 | QB6: 137.15 | QC6: 87.94 | QD6: 394.94 | QE6: 986.1 | QF6: 148.24 | QG6: 92.66 | QH6: 38.92 | QI6: 368.43 | QJ6: 461.96 | QK6: 27.47 | QL6: 38.19 | QM6: 111.39 | QN6: 87.5 | QO6: 215.37 | QP6: 191.98 | QQ6: 77.38 | QR6: 36.34 | QS6: 207.52 | QT6: 254.69 | QU6: 165.02 | QV6: 951.04 | QW6: 180.87 | QX6: 298.99 | QY6: 49.15 | QZ6: 68.96 | RA6: 32.61 | RB6: 420.01 | RC6: 68.45 | RD6: 91.79 | RE6: 130.8 | RF6: 102.92 | RG6: 173.72 | RH6: 102 | RI6: 91.88 | RJ6: 243.84 | RK6: 329.2 | RL6: 31.12 | RM6: 16.96 | RN6: 39.23 | RO6: 60.91 | RP6: 31.86 | RQ6: 10.06 | RR6: 510.3 | RS6: 51.93 | RT6: 43.44 | RU6: 23.68 | RV6: 68.23 | RW6: 172.83 | RX6: 92.26 | RY6: 86.26 | RZ6: 207.4365 | SA6: 40.81 | SB6: 412.69 | SC6: 366.48 | SD6: 21.1 | SE6: 260.01
B7: 45671 | C7: 75.31 | D7: 300.36 | E7: 38.28 | F7: 1328.31 | G7: 224.7 | H7: 167.02 | I7: 371.57 | J7: 247.47 | K7: 156.9 | L7: 62.04 | M7: 175.55 | N7: 108.12 | O7: 358.42 | P7: 148.83 | Q7: 109.72 | R7: 117.27 | S7: 176.86 | T7: 32.67 | U7: 392.78 | V7: 589.86 | W7: 217.75 | X7: 144.75 | Y7: 388.74 | Z7: 281.58 | AA7: 99.65 | AB7: 137.21 | AC7: 122.52 | AD7: 45.78 | AE7: 26.41 | AF7: 159.74 | AG7: 21.8 | AH7: 236.93 | AI7: 119.47 | AJ7: 214.65 | AK7: 90.79 | AL7: 59.33 | AM7: 19.2 | AN7: 50.94 | AO7: 415.67 | AP7: 69.38 | AQ7: 285.03 | AR7: 29.12 | AS7: 73.5 | AT7: 72.59 | AU7: 51.36 | AV7: 305.79 | AW7: 55.42 | AX7: 22.54 | AY7: 113.02 | AZ7: 103.65 | BA7: 307.96 | BB7: 229.73 | BC7: 45.66 | BD7: 627.71 | BE7: 51.19 | BF7: 492.91 | BG7: 291.69 | BH7: 273.49 | BI7: 3227.8 | BJ7: 189.31 | BK7: 585.8 | BL7: 54.38 | BM7: 579.8 | BN7: 70.5 | BO7: 75.94 | BP7: 30.62 | BQ7: 235.8 | BR7: 450.03 | BS7: 82.8 | BT7: 95.65 | BU7: 55.74 | BV7: 34.44 | BW7: 28.86 | BX7: 244.97 | BY7: 24.51 | BZ7: 154.25 | CA7: 41.19 | CB7: 159.03 | CC7: 203.26 | CD7: 65.56 | CE7: 87.67 | CF7: 226.8 | CG7: 26.05 | CH7: 89.37 | CI7: 47.43 | CJ7: 197.48 | CK7: 364.25 | CL7: 237.62 | CM7: 136.47 | CN7: 192.6 | CO7: 432.31 | CP7: 53.69 | CQ7: 116.76 | CR7: 188.8 | CS7: 57.79 | CT7: 123.52 | CU7: 106.85 | CV7: 70.66 | CW7: 340.14 | CX7: 233.9 | CY7: 120.73 | CZ7: 109.06 | DA7: 119.79 | DB7: 135.77 | DC7: 362.65 | DD7: 77.56 | DE7: 252.34 | DF7: 50.69 | DG7: 197.96 | DH7: 499.8 | DI7: 277.62 | DJ7: 103.63 | DK7: 9.78 | DL7: 67.98 | DM7: 19.41 | DN7: 212.27 | DO7: 39.5 | DP7: 79.17 | DQ7: 265.12 | DR7: 58.78 | DS7: 117.02 | DT7: 140.72 | DU7: 1087.88 | DV7: 28.2 | DW7: 214.89 | DX7: 20.14 | DY7: 267.04 | DZ7: 58.2718 | EA7: 155.31 | EB7: 66.06 | EC7: 30.01 | ED7: 289.11 | EE7: 57.1 | EF7: 31.86 | EG7: 282.63 | EH7: 313.24 | EI7: 252.97 | EJ7: 186.56 | EK7: 382.71 | EL7: 83.67 | EM7: 160.5 | EN7: 210.63 | EO7: 81.43 | EP7: 227.12 | EQ7: 22.01 | ER7: 156.31 | ES7: 59.92 | ET7: 135.18 | EU7: 744.91 | EV7: 346.29 | EW7: 83.43 | EX7: 251.19 | EY7: 428.21 | EZ7: 214.54 | FA7: 213.37 | FB7: 75.86 | FC7: 484.47 | FD7: 85.25 | FE7: 11.72 | FF7: 51.57 | FG7: 31.4858 | FH7: 97.36 | FI7: 460.84 | FJ7: 193.37 | FK7: 40.16 | FL7: 71.17 | FM7: 36.73 | FN7: 239.24 | FO7: 78.84 | FP7: 55.98 | FQ7: 475.5 | FR7: 71.19 | FS7: 121.75 | FT7: 52.08 | FU7: 84.76 | FV7: 106.04 | FW7: 156.72 | FX7: 16.22 | FY7: 647.01 | FZ7: 46.85 | GA7: 31.98 | GB7: 61.47 | GC7: 104.88 | GD7: 112.5 | GE7: 83.24 | GF7: 195.71 | GG7: 116.53 | GH7: 239.76 | GI7: 85.06 | GJ7: 58.43 | GK7: 39.87 | GL7: 72.34 | GM7: 341.64 | GN7: 328.96 | GO7: 101.91 | GP7: 340.31 | GQ7: 179.15 | GR7: 64.84 | GS7: 82.05 | GT7: 43.91 | GU7: 33.13 | GV7: 58.59 | GW7: 82.36 | GX7: 289.98 | GY7: 114.91 | GZ7: 73.94 | HA7: 60.89 | HB7: 193.5 | HC7: 78.04 | HD7: 556.99 | HE7: 119.24 | HF7: 114.03 | HG7: 80.21 | HH7: 404.06 | HI7: 229.38 | HJ7: 164.26 | HK7: 543.74 | HL7: 169.32 | HM7: 58.1 | HN7: 234.5 | HO7: 260.07 | HP7: 28.96 | HQ7: 58.06 | HR7: 94.58 | HS7: 412.71 | HT7: 170.51 | HU7: 11.85 | HV7: 111.24 | HW7: 267.1 | HX7: 233.28 | HY7: 286.87 | HZ7: 192.28 | IA7: 36.38 | IB7: 54.19 | IC7: 701.26 | ID7: 276.43 | IE7: 71.89 | IF7: 110.2 | IG7: 917.23 | IH7: 362.8 | II7: 55.46 | IJ7: 59.82 | IK7: 173.65 | IL7: 124.03 | IM7: 139.49 | IN7: 143.16 | IO7: 141.75 | IP7: 399.78 | IQ7: 1949.53 | IR7: 36.87 | IS7: 195.02 | IT7: 64.08 | IU7: 42.89 | IV7: 91 | IW7: 56.62 | IX7: 16.59 | IY7: 126.87 | IZ7: 143.06 | JA7: 101.63 | JB7: 232.65 | JC7: 141.71 | JD7: 159.53 | JE7: 149.12 | JF7: 418.63 | JG7: 93.07 | JH7: 17.48 | JI7: 48.82 | JJ7: 46.54 | JK7: 95.44 | JL7: 26 | JM7: 49.06 | JN7: 71.25 | JO7: 27.14 | JP7: 112.11 | JQ7: 207.17 | JR7: 182.2 | JS7: 16.58 | JT7: 623.8 | JU7: 124.62 | JV7: 56.88 | JW7: 348.04 | JX7: 265.51 | JY7: 70.2 | JZ7: 45.7 | KA7: 155.97 | KB7: 80.289 | KC7: 186.81 | KD7: 69.92 | KE7: 71.93 | KF7: 173.57 | KG7: 218.21 | KH7: 117.61 | KI7: 125.84 | KJ7: 207.57 | KK7: 593.73 | KL7: 484.46 | KM7: 240.05 | KN7: 184.72 | KO7: 404.93 | KP7: 207.41 | KQ7: 70.17 | KR7: 182.04 | KS7: 8143.64 | KT7: 116.69 | KU7: 183.62 | KV7: 162 | KW7: 109.39 | KX7: 104.04 | KY7: 73.87 | KZ7: 294.19 | LA7: 570.27 | LB7: 184.16 | LC7: 91.57 | LD7: 152.98 | LE7: 276.98 | LF7: 28.71 | LG7: 178.8 | LH7: 690.87 | LI7: 217.76 | LJ7: 172.37 | LK7: 237.53 | LL7: 70.29 | LM7: 70.27 | LN7: 119.19 | LO7: 134.06 | LP7: 490.36 | LQ7: 102.84 | LR7: 348.99 | LS7: 1300.73 | LT7: 124.71 | LU7: 108.12 | LV7: 39.17 | LW7: 209 | LX7: 319.89 | LY7: 71.27 | LZ7: 89.4 | MA7: 454.17 | MB7: 131.76 | MC7: 77.17 | MD7: 538.88 | ME7: 180.03 | MF7: 207 | MG7: 64.41 | MH7: 571.53 | MI7: 195.02 | MJ7: 78.11 | MK7: 462.58 | ML7: 55.18 | MM7: 4778.81 | MN7: 258.11 | MO7: 90.58 | MP7: 178.08 | MQ7: 37.18 | MR7: 74.73 | MS7: 189.66 | MT7: 129.75 | MU7: 82.84 | MV7: 143.43 | MW7: 71.56 | MX7: 393.16 | MY7: 231.73 | MZ7: 119.43 | NA7: 76.25 | NB7: 118.47 | NC7: 89.4 | ND7: 323.54 | NE7: 197.43 | NF7: 83.83 | NG7: 67.66 | NH7: 32.14 | NI7: 71.04 | NJ7: 526.67 | NK7: 394.4 | NL7: 104.71 | NM7: 112.52 | NN7: 124.91 | NO7: 509.02 | NP7: 139.16 | NQ7: 145.25 | NR7: 78.35 | NS7: 56.44 | NT7: 81.8 | NU7: 131.28 | NV7: 204.74 | NW7: 99.79 | NX7: 50.1 | NY7: 24 | NZ7: 27.14 | OA7: 183.19 | OB7: 94.99 | OC7: 152.76 | OD7: 191.05 | OE7: 143.11 | OF7: 185.35 | OG7: 309.09 | OH7: 151.37 | OI7: 115.42 | OJ7: 149.42 | OK7: 53.18 | OL7: 116.09 | OM7: 228.83 | ON7: 1271.36 | OO7: 28.97 | OP7: 56.22 | OQ7: 133.7712 | OR7: 92.63 | OS7: 92.49 | OT7: 34.46 | OU7: 284.46 | OV7: 69.61 | OW7: 53.15 | OX7: 198.1 | OY7: 339.68 | OZ7: 47.4078 | PA7: 144.95 | PB7: 142.9 | PC7: 177.68 | PD7: 1031.29 | PE7: 105.28 | PF7: 103.97 | PG7: 33.1 | PH7: 30.93 | PI7: 185.5 | PJ7: 181.62 | PK7: 75.06 | PL7: 125.58 | PM7: 100.28 | PN7: 411.66 | PO7: 9.52 | PP7: 594.25 | PQ7: 214.18 | PR7: 729.86 | PS7: 97.81 | PT7: 66.29 | PU7: 107.67 | PV7: 91.23 | PW7: 30.41 | PX7: 63.4 | PY7: 82.42 | PZ7: 159.33 | QA7: 517.68 | QB7: 134.18 | QC7: 87.18 | QD7: 396.36 | QE7: 963.17 | QF7: 143.65 | QG7: 91.99 | QH7: 40.08 | QI7: 358.34 | QJ7: 465.93 | QK7: 27.55 | QL7: 37.92 | QM7: 108.1 | QN7: 86.67 | QO7: 210.46 | QP7: 201.38 | QQ7: 81.61 | QR7: 37.29 | QS7: 206.14 | QT7: 246.03 | QU7: 164.41 | QV7: 898.09 | QW7: 173.89 | QX7: 294.03 | QY7: 45 | QZ7: 70.19 | RA7: 30.53 | RB7: 427.29 | RC7: 68.4 | RD7: 91.78 | RE7: 127.6 | RF7: 104.12 | RG7: 169.33 | RH7: 102.37 | RI7: 89.11 | RJ7: 288.87 | RK7: 321.09 | RL7: 31.14 | RM7: 17.28 | RN7: 38.81 | RO7: 61.21 | RP7: 31.69 | RQ7: 9.73 | RR7: 510.69 | RS7: 52.93 | RT7: 45.07 | RU7: 24.85 | RV7: 65.91 | RW7: 170.58 | RX7: 94.5 | RY7: 84.13 | RZ7: 205.8631 | SA7: 41.76 | SB7: 416.08 | SC7: 382.26 | SD7: 21.03 | SE7: 255.37
B8: 45672 | C8: 76.08 | D8: 312.32 | E8: 38.18 | F8: 1374.99 | G8: 228 | H8: 166.2 | I8: 374.89 | J8: 252.35 | K8: 158.33 | L8: 61.77 | M8: 171.35 | N8: 108.18 | O8: 362.23 | P8: 149.49 | Q8: 111.51 | R8: 119 | S8: 180.29 | T8: 32.79 | U8: 406.09 | V8: 602.41 | W8: 220.03 | X8: 144.97 | Y8: 376.66 | Z8: 282.3 | AA8: 100.09 | AB8: 137.78 | AC8: 123.53 | AD8: 47.1 | AE8: 26.22 | AF8: 159.65 | AG8: 21.91 | AH8: 239.98 | AI8: 119.09 | AJ8: 218.22 | AK8: 91.34 | AL8: 59.98 | AM8: 19.72 | AN8: 51.7 | AO8: 426.31 | AP8: 68.57 | AQ8: 284.58 | AR8: 29.44 | AS8: 78.27 | AT8: 73.07 | AU8: 51.04 | AV8: 306.25 | AW8: 55.66 | AX8: 23.3 | AY8: 111.1 | AZ8: 104.79 | BA8: 306.9 | BB8: 232.48 | BC8: 46.4625 | BD8: 630.76 | BE8: 51.14 | BF8: 502.02 | BG8: 293.37 | BH8: 273.81 | BI8: 3206.05 | BJ8: 190.23 | BK8: 601 | BL8: 54.26 | BM8: 580 | BN8: 70.23 | BO8: 82.04 | BP8: 30.21 | BQ8: 232.59 | BR8: 458.51 | BS8: 83.21 | BT8: 96.89 | BU8: 55.91 | BV8: 33.69 | BW8: 29.06 | BX8: 243.92 | BY8: 24.94 | BZ8: 161.54 | CA8: 41.04 | CB8: 158.3 | CC8: 205.35 | CD8: 66.61 | CE8: 87.86 | CF8: 228.74 | CG8: 25.51 | CH8: 90.23 | CI8: 48.81 | CJ8: 199.17 | CK8: 360.8 | CL8: 237.97 | CM8: 134.53 | CN8: 198.53 | CO8: 428.88 | CP8: 53.65 | CQ8: 119.68 | CR8: 190.74 | CS8: 58.47 | CT8: 125.14 | CU8: 106.45 | CV8: 71.17 | CW8: 342.58 | CX8: 236.55 | CY8: 118.95 | CZ8: 109.23 | DA8: 120.72 | DB8: 137.06 | DC8: 361.18 | DD8: 78.99 | DE8: 263.53 | DF8: 52.44 | DG8: 196.1 | DH8: 509.28 | DI8: 276.59 | DJ8: 103.68 | DK8: 9.95 | DL8: 69.29 | DM8: 19.63 | DN8: 213.45 | DO8: 40.03 | DP8: 80.4 | DQ8: 266.09 | DR8: 58.31 | DS8: 117.38 | DT8: 141.08 | DU8: 1093.36 | DV8: 28.91 | DW8: 214.14 | DX8: 20.32 | DY8: 264.38 | DZ8: 58.6711 | EA8: 151.75 | EB8: 68.11 | EC8: 29.6 | ED8: 290.19 | EE8: 56.64 | EF8: 31.87 | EG8: 279.49 | EH8: 313.35 | EI8: 253.8 | EJ8: 187.46 | EK8: 385.55 | EL8: 84.17 | EM8: 160.14 | EN8: 213.56 | EO8: 81.19 | EP8: 228.09 | EQ8: 22.03 | ER8: 158.31 | ES8: 58.69 | ET8: 138.57 | EU8: 746.74 | EV8: 348 | EW8: 84.8 | EX8: 256.72 | EY8: 428.93 | EZ8: 214.53 | FA8: 212.59 | FB8: 77.09 | FC8: 496.52 | FD8: 85.4 | FE8: 11.39 | FF8: 52.14 | FG8: 31.8873 | FH8: 103.19 | FI8: 460.08 | FJ8: 192.41 | FK8: 41.37 | FL8: 71.07 | FM8: 36.91 | FN8: 240.36 | FO8: 80.08 | FP8: 56.61 | FQ8: 472.3 | FR8: 75.95 | FS8: 123.08 | FT8: 52.7 | FU8: 85.5 | FV8: 106.88 | FW8: 161.4 | FX8: 16.87 | FY8: 656.32 | FZ8: 47.01 | GA8: 32.11 | GB8: 60.89 | GC8: 105.48 | GD8: 115.97 | GE8: 84.41 | GF8: 200.44 | GG8: 117.57 | GH8: 242.47 | GI8: 86.27 | GJ8: 61.3 | GK8: 40.64 | GL8: 73.66 | GM8: 346.93 | GN8: 329.01 | GO8: 100.52 | GP8: 346.12 | GQ8: 180.06 | GR8: 67.02 | GS8: 82.34 | GT8: 45.39 | GU8: 32.8 | GV8: 59.94 | GW8: 83.39 | GX8: 290.49 | GY8: 116.1 | GZ8: 74 | HA8: 60.92 | HB8: 197.51 | HC8: 78.56 | HD8: 551.47 | HE8: 119.11 | HF8: 116.18 | HG8: 79.44 | HH8: 407.38 | HI8: 230.86 | HJ8: 165.34 | HK8: 543.42 | HL8: 175.14 | HM8: 58.05 | HN8: 237.3 | HO8: 268.19 | HP8: 29.56 | HQ8: 58.01 | HR8: 95.57 | HS8: 417.28 | HT8: 169.17 | HU8: 11.77 | HV8: 111.45 | HW8: 268.94 | HX8: 237.87 | HY8: 290.94 | HZ8: 195.7 | IA8: 36.5 | IB8: 54.47 | IC8: 716.25 | ID8: 276.05 | IE8: 71.78 | IF8: 109.63 | IG8: 923.5 | IH8: 368.61 | II8: 55.76 | IJ8: 59.02 | IK8: 178.38 | IL8: 124.71 | IM8: 141.24 | IN8: 145.41 | IO8: 142.13 | IP8: 400.18 | IQ8: 2030.47 | IR8: 37.135 | IS8: 200.87 | IT8: 64.94 | IU8: 44 | IV8: 92.38 | IW8: 56.16 | IX8: 17.04 | IY8: 126.59 | IZ8: 141 | JA8: 106.12 | JB8: 235.2 | JC8: 144.27 | JD8: 164.41 | JE8: 149.01 | JF8: 422.92 | JG8: 93.08 | JH8: 18.14 | JI8: 48.54 | JJ8: 46.18 | JK8: 99.77 | JL8: 26.02 | JM8: 50.9 | JN8: 70.95 | JO8: 27.57 | JP8: 113.32 | JQ8: 208 | JR8: 180.72 | JS8: 17.05 | JT8: 621.45 | JU8: 130.55 | JV8: 57 | JW8: 362.02 | JX8: 268.41 | JY8: 68.75 | JZ8: 47.08 | KA8: 158.17 | KB8: 80.269 | KC8: 188.03 | KD8: 69.46 | KE8: 72.46 | KF8: 171.75 | KG8: 217.11 | KH8: 120.06 | KI8: 127.47 | KJ8: 206.66 | KK8: 583.45 | KL8: 483.97 | KM8: 237.67 | KN8: 190.68 | KO8: 397.7 | KP8: 211.48 | KQ8: 70.34 | KR8: 180.83 | KS8: 8259.08 | KT8: 119.36 | KU8: 186.86 | KV8: 162.36 | KW8: 111.23 | KX8: 106.18 | KY8: 74.52 | KZ8: 300.72 | LA8: 571.88 | LB8: 183.59 | LC8: 92.28 | LD8: 150.33 | LE8: 276.11 | LF8: 28.73 | LG8: 180.32 | LH8: 703.43 | LI8: 223.35 | LJ8: 171.97 | LK8: 236.72 | LL8: 72 | LM8: 70.95 | LN8: 121.86 | LO8: 137.91 | LP8: 507.19 | LQ8: 103.03 | LR8: 349.73 | LS8: 1293.53 | LT8: 125.77 | LU8: 107.85 | LV8: 39.22 | LW8: 210.1 | LX8: 329.42 | LY8: 71.15 | LZ8: 91.12 | MA8: 453.98 | MB8: 136.24 | MC8: 77.78 | MD8: 580.11 | ME8: 181.32 | MF8: 209.76 | MG8: 65.11 | MH8: 605.92 | MI8: 197.23 | MJ8: 82.42 | MK8: 471.35 | ML8: 55.23 | MM8: 4829.64 | MN8: 262.3 | MO8: 90.52 | MP8: 173.91 | MQ8: 38.43 | MR8: 75.13 | MS8: 195.55 | MT8: 130.93 | MU8: 84.826 | MV8: 142.23 | MW8: 72.72 | MX8: 389.29 | MY8: 227.88 | MZ8: 120.61 | NA8: 76.98 | NB8: 118.51 | NC8: 90.53 | ND8: 321.16 | NE8: 198.7 | NF8: 84.93 | NG8: 67.65 | NH8: 32.46 | NI8: 70.28 | NJ8: 537.25 | NK8: 400.25 | NL8: 106.51 | NM8: 111.84 | NN8: 131.3 | NO8: 522.35 | NP8: 140.95 | NQ8: 148.24 | NR8: 78.04 | NS8: 57.37 | NT8: 82.41 | NU8: 133.37 | NV8: 209.02 | NW8: 104.07 | NX8: 49.26 | NY8: 24.7 | NZ8: 27.02 | OA8: 186.52 | OB8: 96.37 | OC8: 155.25 | OD8: 196.98 | OE8: 143.91 | OF8: 186.82 | OG8: 316.28 | OH8: 149.46 | OI8: 116.09 | OJ8: 151.95 | OK8: 53.1 | OL8: 119.96 | OM8: 233.38 | ON8: 1279.73 | OO8: 28.76 | OP8: 56.4 | OQ8: 134.8303 | OR8: 95.15 | OS8: 93.06 | OT8: 34.77 | OU8: 282.85 | OV8: 73.22 | OW8: 53.17 | OX8: 200.29 | OY8: 344.57 | OZ8: 48.836 | PA8: 144.78 | PB8: 143.47 | PC8: 179.56 | PD8: 1054.13 | PE8: 103.44 | PF8: 104.02 | PG8: 33 | PH8: 30.5 | PI8: 185.37 | PJ8: 186.55 | PK8: 76.15 | PL8: 130.06 | PM8: 101.57 | PN8: 424.26 | PO8: 9.61 | PP8: 617.12 | PQ8: 214.2 | PR8: 741.49 | PS8: 98.43 | PT8: 65.5 | PU8: 104.96 | PV8: 94.34 | PW8: 30.49 | PX8: 63.15 | PY8: 84.79 | PZ8: 164.85 | QA8: 531.29 | QB8: 134.93 | QC8: 89.64 | QD8: 428.22 | QE8: 1013.18 | QF8: 150.5 | QG8: 93.62 | QH8: 40.4 | QI8: 357.89 | QJ8: 468.98 | QK8: 27.56 | QL8: 38.02 | QM8: 109.02 | QN8: 86.64 | QO8: 215.78 | QP8: 205.5 | QQ8: 80.44 | QR8: 37.82 | QS8: 203.73 | QT8: 248.57 | QU8: 167.17 | QV8: 900.01 | QW8: 174.91 | QX8: 288.18 | QY8: 44.2 | QZ8: 72.03 | RA8: 30.99 | RB8: 427.98 | RC8: 68.8 | RD8: 92.25 | RE8: 132.52 | RF8: 105.24 | RG8: 171.19 | RH8: 102.55 | RI8: 90.68 | RJ8: 300.77 | RK8: 335.03 | RL8: 30.97 | RM8: 17.32 | RN8: 38.69 | RO8: 61.68 | RP8: 32.07 | RQ8: 9.79 | RR8: 517.96 | RS8: 52.95 | RT8: 45.72 | RU8: 25.45 | RV8: 68.14 | RW8: 174.19 | RX8: 95.12 | RY8: 83.66 | RZ8: 206.8429 | SA8: 45.56 | SB8: 413.93 | SC8: 387.03 | SD8: 20.85 | SE8: 274.93
B9: 45673 | C9: 76.63 | D9: 311.48 | E9: 38.34 | F9: 1392.99 | G9: 229.41 | H9: 168.93 | I9: 380.55 | J9: 254.27 | K9: 159.38 | L9: 62.25 | M9: 173.7 | N9: 106.46 | O9: 370 | P9: 151.6 | Q9: 111.32 | R9: 119.63 | S9: 179.74 | T9: 32.35 | U9: 409.33 | V9: 596.66 | W9: 222.66 | X9: 147.77 | Y9: 370.99 | Z9: 279.74 | AA9: 100.7 | AB9: 139.18 | AC9: 126.36 | AD9: 46.64 | AE9: 26.49 | AF9: 160.5 | AG9: 22.02 | AH9: 242.37 | AI9: 120.46 | AJ9: 215.02 | AK9: 91.3 | AL9: 59.82 | AM9: 19.67 | AN9: 51.84 | AO9: 424.58 | AP9: 69.26 | AQ9: 280.97 | AR9: 30.06 | AS9: 78.51 | AT9: 74.61 | AU9: 51.16 | AV9: 309.44 | AW9: 56.26 | AX9: 23.41 | AY9: 113.91 | AZ9: 105.93 | BA9: 312.06 | BB9: 233.28 | BC9: 47.04 | BD9: 642.86 | BE9: 51.01 | BF9: 510.99 | BG9: 296.23 | BH9: 278.47 | BI9: 3193.96 | BJ9: 191.24 | BK9: 609.97 | BL9: 54.25 | BM9: 585.84 | BN9: 70.18 | BO9: 82.25 | BP9: 30.95 | BQ9: 236.3 | BR9: 462.81 | BS9: 82.21 | BT9: 98.17 | BU9: 56.38 | BV9: 34.08 | BW9: 29.83 | BX9: 246.65 | BY9: 25.05 | BZ9: 160.66 | CA9: 41.39 | CB9: 160.47 | CC9: 207.96 | CD9: 68.02 | CE9: 88.56 | CF9: 229.09 | CG9: 25.79 | CH9: 92.22 | CI9: 49.24 | CJ9: 200.85 | CK9: 366.33 | CL9: 241.9 | CM9: 133.25 | CN9: 199.13 | CO9: 439.11 | CP9: 55.06 | CQ9: 120.84 | CR9: 194.48 | CS9: 60.07 | CT9: 125 | CU9: 109.06 | CV9: 71.66 | CW9: 345.19 | CX9: 239.15 | CY9: 119.53 | CZ9: 110.11 | DA9: 123.29 | DB9: 138.05 | DC9: 368.11 | DD9: 81.31 | DE9: 264.24 | DF9: 53.78 | DG9: 197.66 | DH9: 512.06 | DI9: 277.37 | DJ9: 105.95 | DK9: 10.01 | DL9: 71.37 | DM9: 19.4 | DN9: 214.56 | DO9: 40.03 | DP9: 84.84 | DQ9: 268.83 | DR9: 59.16 | DS9: 119.42 | DT9: 144.94 | DU9: 1110.35 | DV9: 29.27 | DW9: 218.48 | DX9: 20.7 | DY9: 272.86 | DZ9: 59.2888 | EA9: 154.02 | EB9: 67.81 | EC9: 29.89 | ED9: 295.79 | EE9: 58 | EF9: 32.8 | EG9: 275.8 | EH9: 322.12 | EI9: 255.93 | EJ9: 187.79 | EK9: 388.86 | EL9: 84.44 | EM9: 160.28 | EN9: 210.76 | EO9: 81.56 | EP9: 231.04 | EQ9: 22.29 | ER9: 159.54 | ES9: 58.62 | ET9: 140.69 | EU9: 757.6 | EV9: 346.68 | EW9: 86.08 | EX9: 258.78 | EY9: 433.92 | EZ9: 217.27 | FA9: 216.29 | FB9: 77.55 | FC9: 505.16 | FD9: 87.16 | FE9: 11.34 | FF9: 51.96 | FG9: 32.063 | FH9: 102.6 | FI9: 462.7 | FJ9: 193.92 | FK9: 41.65 | FL9: 71.11 | FM9: 38.03 | FN9: 247.11 | FO9: 81.14 | FP9: 58.12 | FQ9: 481.19 | FR9: 75.95 | FS9: 123.36 | FT9: 52.3 | FU9: 85.84 | FV9: 108.66 | FW9: 164.9 | FX9: 16.95 | FY9: 658.66 | FZ9: 48.3 | GA9: 33.17 | GB9: 61.33 | GC9: 105.61 | GD9: 116.93 | GE9: 86.44 | GF9: 196.54 | GG9: 119.6 | GH9: 245.54 | GI9: 88.48 | GJ9: 61.16 | GK9: 41.09 | GL9: 75.51 | GM9: 354.17 | GN9: 337.2 | GO9: 102.54 | GP9: 345.6 | GQ9: 180.86 | GR9: 68.58 | GS9: 83.89 | GT9: 44.98 | GU9: 32.16 | GV9: 60.37 | GW9: 83.97 | GX9: 297.7 | GY9: 118.13 | GZ9: 73.22 | HA9: 61.63 | HB9: 187.37 | HC9: 78.84 | HD9: 561.71 | HE9: 121.38 | HF9: 117.24 | HG9: 80.46 | HH9: 413.33 | HI9: 234.89 | HJ9: 165.08 | HK9: 510.59 | HL9: 176.72 | HM9: 58.36 | HN9: 238.77 | HO9: 269.17 | HP9: 30.03 | HQ9: 59.18 | HR9: 98.39 | HS9: 426.93 | HT9: 174 | HU9: 12 | HV9: 111.21 | HW9: 269.43 | HX9: 228.26 | HY9: 290.08 | HZ9: 198.05 | IA9: 36.31 | IB9: 54.98 | IC9: 747.26 | ID9: 276 | IE9: 73.62 | IF9: 109.48 | IG9: 919.75 | IH9: 381.79 | II9: 56.02 | IJ9: 59.07 | IK9: 186.48 | IL9: 127.03 | IM9: 142.91 | IN9: 146.6 | IO9: 141.4 | IP9: 405.66 | IQ9: 1969.68 | IR9: 37.385 | IS9: 196.1 | IT9: 66.2 | IU9: 43.27 | IV9: 91.65 | IW9: 57.74 | IX9: 16.84 | IY9: 128.73 | IZ9: 141.23 | JA9: 106.49 | JB9: 235.32 | JC9: 146.84 | JD9: 161.43 | JE9: 149 | JF9: 428.62 | JG9: 94.43 | JH9: 17.84 | JI9: 48.32 | JJ9: 45.94 | JK9: 100.49 | JL9: 26.44 | JM9: 48.03 | JN9: 71.4 | JO9: 27.32 | JP9: 112.13 | JQ9: 211.01 | JR9: 184.57 | JS9: 16.87 | JT9: 607.27 | JU9: 135.81 | JV9: 56.19 | JW9: 363.38 | JX9: 273.53 | JY9: 69.97 | JZ9: 46.8 | KA9: 161.73 | KB9: 80.315 | KC9: 191.1 | KD9: 70.25 | KE9: 72.47 | KF9: 172.71 | KG9: 217.9 | KH9: 118.4 | KI9: 129.94 | KJ9: 210.15 | KK9: 595.19 | KL9: 486.86 | KM9: 240.89 | KN9: 188.44 | KO9: 405.43 | KP9: 213.82 | KQ9: 71.08 | KR9: 181.06 | KS9: 8355.81 | KT9: 119.98 | KU9: 189.92 | KV9: 164.85 | KW9: 112.47 | KX9: 110.25 | KY9: 78.07 | KZ9: 298.9 | LA9: 575.43 | LB9: 184.06 | LC9: 91.44 | LD9: 151.66 | LE9: 280.96 | LF9: 28.97 | LG9: 190.07 | LH9: 693.23 | LI9: 220.66 | LJ9: 172.5 | LK9: 237.72 | LL9: 72.44 | LM9: 69.86 | LN9: 122.98 | LO9: 139.37 | LP9: 515.81 | LQ9: 102.69 | LR9: 350.56 | LS9: 1322.02 | LT9: 126.24 | LU9: 110.93 | LV9: 40.08 | LW9: 210.685 | LX9: 336.19 | LY9: 71.75 | LZ9: 93.86 | MA9: 459.97 | MB9: 133.57 | MC9: 77.43 | MD9: 584.08 | ME9: 183.37 | MF9: 211.92 | MG9: 65.06 | MH9: 612.99 | MI9: 204.18 | MJ9: 83.99 | MK9: 479 | ML9: 53.51 | MM9: 4865 | MN9: 263.86 | MO9: 90.5 | MP9: 165.8 | MQ9: 38.42 | MR9: 76.1 | MS9: 192.91 | MT9: 132.62 | MU9: 84.237 | MV9: 144.72 | MW9: 73.9 | MX9: 385.26 | MY9: 232.31 | MZ9: 122.99 | NA9: 78.39 | NB9: 119.8 | NC9: 90.75 | ND9: 320 | NE9: 201.02 | NF9: 85.89 | NG9: 69.63 | NH9: 32.97 | NI9: 69.86 | NJ9: 546.43 | NK9: 402.72 | NL9: 108.94 | NM9: 112.65 | NN9: 134.75 | NO9: 523.14 | NP9: 136.79 | NQ9: 150.23 | NR9: 78.71 | NS9: 58.36 | NT9: 82.5 | NU9: 133.56 | NV9: 211.68 | NW9: 106 | NX9: 49.65 | NY9: 24.52 | NZ9: 26.72 | OA9: 188.67 | OB9: 97.25 | OC9: 155.09 | OD9: 194.41 | OE9: 141.8 | OF9: 190.89 | OG9: 317.25 | OH9: 150.63 | OI9: 118.95 | OJ9: 151.7 | OK9: 53.53 | OL9: 118.44 | OM9: 237.13 | ON9: 1297.52 | OO9: 29.28 | OP9: 56.4 | OQ9: 136.9188 | OR9: 94.32 | OS9: 94.05 | OT9: 33.76 | OU9: 283.75 | OV9: 73.42 | OW9: 54.58 | OX9: 199.35 | OY9: 349.54 | OZ9: 48.5488 | PA9: 146.54 | PB9: 143.69 | PC9: 179.12 | PD9: 1057.16 | PE9: 106.27 | PF9: 105.39 | PG9: 33.13 | PH9: 31.08 | PI9: 186.97 | PJ9: 186.2 | PK9: 79.22 | PL9: 128.72 | PM9: 102.58 | PN9: 416.96 | PO9: 9.7 | PP9: 611.3 | PQ9: 215.75 | PR9: 757.42 | PS9: 100.09 | PT9: 66.18 | PU9: 106.11 | PV9: 95.07 | PW9: 30.4 | PX9: 62.87 | PY9: 86.38 | PZ9: 165.92 | QA9: 531.23 | QB9: 137.57 | QC9: 88.92 | QD9: 413.82 | QE9: 995.72 | QF9: 153.24 | QG9: 96.1 | QH9: 40.87 | QI9: 360.24 | QJ9: 472.08 | QK9: 27.5 | QL9: 39.34 | QM9: 109.1 | QN9: 90.65 | QO9: 218.91 | QP9: 212.95 | QQ9: 79.4 | QR9: 38.39 | QS9: 208.22 | QT9: 250.7 | QU9: 169.37 | QV9: 919.89 | QW9: 180.1 | QX9: 282.6 | QY9: 43.98 | QZ9: 72.69 | RA9: 31.12 | RB9: 432.49 | RC9: 69.74 | RD9: 93.2 | RE9: 132.16 | RF9: 107.78 | RG9: 170.85 | RH9: 104.05 | RI9: 92.04 | RJ9: 315.24 | RK9: 332.01 | RL9: 31.28 | RM9: 17.07 | RN9: 39.26 | RO9: 62.93 | RP9: 32.72 | RQ9: 9.47 | RR9: 519.1 | RS9: 52.22 | RT9: 46.33 | RU9: 25.15 | RV9: 69.24 | RW9: 177.17 | RX9: 96.82 | RY9: 85 | RZ9: 209.8107 | SA9: 46.08 | SB9: 418.91 | SC9: 391 | SD9: 21.19 | SE9: 281.63
B10: 45674 | C10: 77.3 | D10: 312.56 | E10: 38.78 | F10: 1412.8 | G10: 237.44 | H10: 171.09 | I10: 386.02 | J10: 259.16 | K10: 161.47 | L10: 62.71 | M10: 171.56 | N10: 107.02 | O10: 370.79 | P10: 150.6 | Q10: 112.32 | R10: 120.53 | S10: 182.85 | T10: 32.51 | U10: 409.38 | V10: 625.82 | W10: 224.79 | X10: 147.03 | Y10: 373.7 | Z10: 280.95 | AA10: 97.92 | AB10: 141.03 | AC10: 126.6 | AD10: 46.53 | AE10: 26.3 | AF10: 161.13 | AG10: 22.29 | AH10: 239.52 | AI10: 121.11 | AJ10: 219.16 | AK10: 91.94 | AL10: 60.23 | AM10: 21.49 | AN10: 50.97 | AO10: 429.03 | AP10: 68.44 | AQ10: 283.99 | AR10: 30.31 | AS10: 79.99 | AT10: 75.09 | AU10: 51.86 | AV10: 310.45 | AW10: 56.93 | AX10: 23.14 | AY10: 113.48 | AZ10: 106.49 | BA10: 317.8 | BB10: 241.81 | BC10: 47.5225 | BD10: 647.46 | BE10: 51.29 | BF10: 506.47 | BG10: 296.18 | BH10: 278.55 | BI10: 3228.4 | BJ10: 191.32 | BK10: 612.02 | BL10: 54.29 | BM10: 593.89 | BN10: 69.62 | BO10: 83.29 | BP10: 30.98 | BQ10: 237.38 | BR10: 467.95 | BS10: 81.9 | BT10: 98.66 | BU10: 56.29 | BV10: 34.29 | BW10: 29.47 | BX10: 246.61 | BY10: 25.85 | BZ10: 164.12 | CA10: 41.2 | CB10: 160.28 | CC10: 209.18 | CD10: 68.08 | CE10: 88.69 | CF10: 229.08 | CG10: 25.82 | CH10: 93.65 | CI10: 49.84 | CJ10: 200.91 | CK10: 366.34 | CL10: 238.36 | CM10: 133.61 | CN10: 202.83 | CO10: 455.44 | CP10: 55.28 | CQ10: 124.42 | CR10: 195.08 | CS10: 60.55 | CT10: 125.83 | CU10: 109.26 | CV10: 71.22 | CW10: 346.28 | CX10: 237.42 | CY10: 118.39 | CZ10: 109.64 | DA10: 124.53 | DB10: 136.58 | DC10: 366.17 | DD10: 81.99 | DE10: 262.87 | DF10: 52.96 | DG10: 197.36 | DH10: 515.7 | DI10: 275.1 | DJ10: 105.55 | DK10: 10.18 | DL10: 70.76 | DM10: 19.56 | DN10: 215.7 | DO10: 40.22 | DP10: 84.38 | DQ10: 266.67 | DR10: 59.63 | DS10: 118.52 | DT10: 145.37 | DU10: 1113.6 | DV10: 29.9 | DW10: 218.16 | DX10: 20.78 | DY10: 275.81 | DZ10: 59.447 | EA10: 152.87 | EB10: 68.75 | EC10: 29.93 | ED10: 294.82 | EE10: 57.86 | EF10: 32.56 | EG10: 282.63 | EH10: 320.65 | EI10: 256.38 | EJ10: 188.73 | EK10: 389.19 | EL10: 84.89 | EM10: 161.24 | EN10: 215.36 | EO10: 81.78 | EP10: 230.4 | EQ10: 22.29 | ER10: 161.03 | ES10: 58.36 | ET10: 141.54 | EU10: 725.72 | EV10: 351.37 | EW10: 86.25 | EX10: 261.06 | EY10: 437.38 | EZ10: 215.69 | FA10: 215.23 | FB10: 78.2 | FC10: 501.86 | FD10: 88.08 | FE10: 11.3 | FF10: 52.62 | FG10: 32.4018 | FH10: 105.75 | FI10: 464.86 | FJ10: 194.78 | FK10: 41.67 | FL10: 70.84 | FM10: 38.11 | FN10: 245.34 | FO10: 81.66 | FP10: 57.87 | FQ10: 482.38 | FR10: 77.08 | FS10: 124.53 | FT10: 51.97 | FU10: 85.38 | FV10: 108.96 | FW10: 167.01 | FX10: 17.01 | FY10: 669.46 | FZ10: 48.43 | GA10: 33.25 | GB10: 61.16 | GC10: 105.85 | GD10: 117.03 | GE10: 86.64 | GF10: 198.54 | GG10: 120.24 | GH10: 243.68 | GI10: 88.14 | GJ10: 62.7 | GK10: 43.58 | GL10: 76.41 | GM10: 353.98 | GN10: 336.34 | GO10: 102.14 | GP10: 348.5 | GQ10: 180.73 | GR10: 67.34 | GS10: 83.9 | GT10: 47.65 | GU10: 32.1 | GV10: 59.5 | GW10: 84.27 | GX10: 296.07 | GY10: 119.95 | GZ10: 73.07 | HA10: 62.32 | HB10: 192.42 | HC10: 79.16 | HD10: 559.65 | HE10: 121.85 | HF10: 118.3 | HG10: 81.14 | HH10: 405.01 | HI10: 234.26 | HJ10: 165.69 | HK10: 509.76 | HL10: 179.95 | HM10: 58.9 | HN10: 238.56 | HO10: 270.1 | HP10: 30.2 | HQ10: 59.14 | HR10: 99.03 | HS10: 429.99 | HT10: 170.86 | HU10: 11.82 | HV10: 110.35 | HW10: 272.11 | HX10: 229.98 | HY10: 291.45 | HZ10: 198.31 | IA10: 36.58 | IB10: 55.23 | IC10: 757.47 | ID10: 277.18 | IE10: 73.31 | IF10: 110.33 | IG10: 943.19 | IH10: 383.42 | II10: 55.71 | IJ10: 60.08 | IK10: 192.05 | IL10: 126.27 | IM10: 140.66 | IN10: 147.65 | IO10: 142 | IP10: 405.57 | IQ10: 1900.54 | IR10: 38.04 | IS10: 196.76 | IT10: 66.72 | IU10: 44.34 | IV10: 91.84 | IW10: 57.34 | IX10: 17.01 | IY10: 129.34 | IZ10: 140.55 | JA10: 106.87 | JB10: 237.87 | JC10: 146.29 | JD10: 164.56 | JE10: 149.15 | JF10: 419.26 | JG10: 95.13 | JH10: 18.3 | JI10: 48 | JJ10: 45.66 | JK10: 97.63 | JL10: 27.17 | JM10: 48.36 | JN10: 71.81 | JO10: 27.52 | JP10: 113.21 | JQ10: 211.71 | JR10: 184.31 | JS10: 17.2 | JT10: 604.13 | JU10: 137.87 | JV10: 57.97 | JW10: 357 | JX10: 269.48 | JY10: 69.73 | JZ10: 47.54 | KA10: 162.9 | KB10: 81.119 | KC10: 188.9 | KD10: 69.77 | KE10: 71.93 | KF10: 174.14 | KG10: 218.14 | KH10: 119.01 | KI10: 129.73 | KJ10: 209.62 | KK10: 592.57 | KL10: 490.32 | KM10: 242.05 | KN10: 190.97 | KO10: 404 | KP10: 216.38 | KQ10: 72.07 | KR10: 181.75 | KS10: 8362.86 | KT10: 122.09 | KU10: 189.55 | KV10: 166.24 | KW10: 111.93 | KX10: 109.22 | KY10: 77.86 | KZ10: 305.6 | LA10: 569.33 | LB10: 184.8 | LC10: 93.64 | LD10: 151.2 | LE10: 286.6 | LF10: 29.27 | LG10: 190.39 | LH10: 681.58 | LI10: 225.94 | LJ10: 173.16 | LK10: 240.46 | LL10: 73.19 | LM10: 69.42 | LN10: 125.3 | LO10: 141.05 | LP10: 526.7 | LQ10: 103.58 | LR10: 352.59 | LS10: 1340.02 | LT10: 125.32 | LU10: 109.48 | LV10: 39.89 | LW10: 209.72 | LX10: 337.46 | LY10: 73.22 | LZ10: 94.17 | MA10: 462.99 | MB10: 137.71 | MC10: 77.81 | MD10: 592.64 | ME10: 186.41 | MF10: 213.73 | MG10: 66.19 | MH10: 625.94 | MI10: 203.61 | MJ10: 85.18 | MK10: 475.85 | ML10: 54.63 | MM10: 4926.8 | MN10: 263.95 | MO10: 91.01 | MP10: 163.5 | MQ10: 37.95 | MR10: 75.83 | MS10: 196 | MT10: 133.59 | MU10: 85.81 | MV10: 147.36 | MW10: 74.92 | MX10: 385.29 | MY10: 232.71 | MZ10: 123.66 | NA10: 78.83 | NB10: 121.59 | NC10: 91.88 | ND10: 324.56 | NE10: 202.55 | NF10: 86.78 | NG10: 71.39 | NH10: 32.73 | NI10: 69.78 | NJ10: 552.19 | NK10: 405.71 | NL10: 109.56 | NM10: 112.6 | NN10: 136.91 | NO10: 524.7 | NP10: 138.4 | NQ10: 149.11 | NR10: 78.78 | NS10: 57.52 | NT10: 84.67 | NU10: 135.61 | NV10: 211.59 | NW10: 104.51 | NX10: 49.42 | NY10: 24.2 | NZ10: 27.14 | OA10: 187.28 | OB10: 97.01 | OC10: 155.18 | OD10: 197.55 | OE10: 142.2 | OF10: 192.88 | OG10: 319.62 | OH10: 150.52 | OI10: 119.66 | OJ10: 152.7 | OK10: 53.66 | OL10: 121.46 | OM10: 239.78 | ON10: 1295.43 | OO10: 29.35 | OP10: 56.9 | OQ10: 137.8393 | OR10: 97.49 | OS10: 94.23 | OT10: 34.06 | OU10: 283.41 | OV10: 73.85 | OW10: 54.62 | OX10: 201.69 | OY10: 350.26 | OZ10: 49.1458 | PA10: 148.25 | PB10: 145.72 | PC10: 180.18 | PD10: 1071.48 | PE10: 106.47 | PF10: 105.39 | PG10: 32.85 | PH10: 31.32 | PI10: 187.79 | PJ10: 172.45 | PK10: 80.3 | PL10: 129.27 | PM10: 103.02 | PN10: 422 | PO10: 9.7 | PP10: 612.77 | PQ10: 218.97 | PR10: 771 | PS10: 101.79 | PT10: 65.82 | PU10: 107.38 | PV10: 97.67 | PW10: 30.4 | PX10: 62.25 | PY10: 86.96 | PZ10: 166.99 | QA10: 542.56 | QB10: 138.4 | QC10: 91.81 | QD10: 426.5 | QE10: 1004.96 | QF10: 157.57 | QG10: 95.51 | QH10: 41.04 | QI10: 362.17 | QJ10: 473.89 | QK10: 27.43 | QL10: 39.42 | QM10: 108.42 | QN10: 91.06 | QO10: 224.23 | QP10: 215.72 | QQ10: 79.54 | QR10: 38.46 | QS10: 209.91 | QT10: 249.64 | QU10: 165.89 | QV10: 915.59 | QW10: 178.43 | QX10: 286.21 | QY10: 44.4 | QZ10: 73.51 | RA10: 30.82 | RB10: 436 | RC10: 69.66 | RD10: 94.77 | RE10: 135.12 | RF10: 106.36 | RG10: 174.48 | RH10: 102.94 | RI10: 93.27 | RJ10: 316.36 | RK10: 342.34 | RL10: 31.62 | RM10: 17.06 | RN10: 38.98 | RO10: 63.16 | RP10: 32.74 | RQ10: 9.52 | RR10: 522.32 | RS10: 52.96 | RT10: 46.54 | RU10: 24.4 | RV10: 71.77 | RW10: 177.11 | RX10: 97.25 | RY10: 84.74 | RZ10: 209.7071 | SA10: 48.15 | SB10: 427.35 | SC10: 401.41 | SD10: 21.1 | SE10: 295.48
B11: 45679 | C11: 77.08 | D11: 322.25 | E11: 38.95 | F11: 1415.68 | G11: 240.91 | H11: 174.8 | I11: 397.61 | J11: 262.84 | K11: 156.41 | L11: 61.78 | M11: 169.2 | N11: 108.81 | O11: 373.41 | P11: 150.07 | Q11: 109.53 | R11: 118.55 | S11: 188.36 | T11: 33.13 | U11: 410.1 | V11: 689.42 | W11: 223.26 | X11: 145.27 | Y11: 382.82 | Z11: 281.35 | AA11: 95.68 | AB11: 149.12 | AC11: 121.68 | AD11: 45.79 | AE11: 26.01 | AF11: 164.74 | AG11: 22.32 | AH11: 246.72 | AI11: 124.38 | AJ11: 224.08 | AK11: 93.23 | AL11: 61.63 | AM11: 21.86 | AN11: 52.76 | AO11: 446.2 | AP11: 70.72 | AQ11: 289.04 | AR11: 30.78 | AS11: 81.69 | AT11: 74.75 | AU11: 50.81 | AV11: 319.51 | AW11: 58.19 | AX11: 24.42 | AY11: 117.78 | AZ11: 104.3 | BA11: 316.99 | BB11: 236.16 | BC11: 52.445 | BD11: 663.31 | BE11: 50.52 | BF11: 535.99 | BG11: 296.36 | BH11: 279.35 | BI11: 3326.01 | BJ11: 190.53 | BK11: 613 | BL11: 54.33 | BM11: 607.6 | BN11: 69.9 | BO11: 84.33 | BP11: 31.83 | BQ11: 237.92 | BR11: 460.51 | BS11: 83.92 | BT11: 100.31 | BU11: 57.09 | BV11: 33.03 | BW11: 29.18 | BX11: 248 | BY11: 25.25 | BZ11: 165.78 | CA11: 40.5 | CB11: 158.73 | CC11: 207.57 | CD11: 66.6 | CE11: 87.55 | CF11: 235.42 | CG11: 25.31 | CH11: 90.77 | CI11: 54.01 | CJ11: 204.3 | CK11: 366 | CL11: 244.18 | CM11: 135.77 | CN11: 212.11 | CO11: 459.75 | CP11: 52.93 | CQ11: 120.69 | CR11: 198.81 | CS11: 59.09 | CT11: 122.885 | CU11: 108.82 | CV11: 71.13 | CW11: 371.23 | CX11: 241.63 | CY11: 122.78 | CZ11: 115.12 | DA11: 129.94 | DB11: 134.02 | DC11: 367.31 | DD11: 82.59 | DE11: 271.88 | DF11: 53.4 | DG11: 205.42 | DH11: 524.82 | DI11: 270.43 | DJ11: 105.19 | DK11: 10.03 | DL11: 68.49 | DM11: 19.87 | DN11: 216.2 | DO11: 39.09 | DP11: 87.09 | DQ11: 268.84 | DR11: 59.32 | DS11: 117.66 | DT11: 141.69 | DU11: 1122.93 | DV11: 28.48 | DW11: 220.06 | DX11: 20.55 | DY11: 278.89 | DZ11: 60.4188 | EA11: 151.12 | EB11: 70.49 | EC11: 30.35 | ED11: 293.5 | EE11: 56.31 | EF11: 32.44 | EG11: 284.92 | EH11: 320.67 | EI11: 259.14 | EJ11: 194.3 | EK11: 399.56 | EL11: 85.49 | EM11: 158.72 | EN11: 216.09 | EO11: 81.64 | EP11: 234.95 | EQ11: 22.22 | ER11: 184.22 | ES11: 58.76 | ET11: 136.13 | EU11: 753.98 | EV11: 352.8 | EW11: 84.48 | EX11: 258 | EY11: 456.86 | EZ11: 219.99 | FA11: 217.34 | FB11: 78.59 | FC11: 510.96 | FD11: 87.84 | FE11: 11.14 | FF11: 52.99 | FG11: 32.4645 | FH11: 109.23 | FI11: 471.92 | FJ11: 197.73 | FK11: 41.68 | FL11: 74.04 | FM11: 37.78 | FN11: 251.85 | FO11: 81.66 | FP11: 55.79 | FQ11: 502.41 | FR11: 77.54 | FS11: 122.09 | FT11: 50.2 | FU11: 86.13 | FV11: 106.3 | FW11: 170.5 | FX11: 16.44 | FY11: 674.49 | FZ11: 48.46 | GA11: 32.66 | GB11: 62.73 | GC11: 103.06 | GD11: 116.89 | GE11: 85.96 | GF11: 196.3 | GG11: 122.87 | GH11: 239.17 | GI11: 88.21 | GJ11: 58.29 | GK11: 41.63 | GL11: 80.6 | GM11: 357.74 | GN11: 347.87 | GO11: 102.15 | GP11: 351.6 | GQ11: 188.7 | GR11: 67.82 | GS11: 82.52 | GT11: 47.01 | GU11: 31.86 | GV11: 59.05 | GW11: 86.3 | GX11: 290.75 | GY11: 129.82 | GZ11: 73.42 | HA11: 62.51 | HB11: 197.05 | HC11: 78.41 | HD11: 574.59 | HE11: 122.57 | HF11: 120.53 | HG11: 82.1 | HH11: 418.44 | HI11: 235.8 | HJ11: 172.72 | HK11: 519.72 | HL11: 182.77 | HM11: 58.36 | HN11: 242.45 | HO11: 274.38 | HP11: 29.76 | HQ11: 59.2 | HR11: 97.58 | HS11: 437.32 | HT11: 186.86 | HU11: 11.13 | HV11: 112.32 | HW11: 273.44 | HX11: 223.83 | HY11: 301.45 | HZ11: 199.02 | IA11: 37.11 | IB11: 54.88 | IC11: 771.91 | ID11: 280.41 | IE11: 73.24 | IF11: 109.84 | IG11: 944.7 | IH11: 390.49 | II11: 55.6 | IJ11: 60.87 | IK11: 195.51 | IL11: 128.75 | IM11: 138.01 | IN11: 146.93 | IO11: 142.35 | IP11: 377.7 | IQ11: 1880.32 | IR11: 37.8 | IS11: 195.6 | IT11: 66.98 | IU11: 43.93 | IV11: 93.04 | IW11: 57.25 | IX11: 16.86 | IY11: 131.15 | IZ11: 142.75 | JA11: 107.39 | JB11: 239.8 | JC11: 144.775 | JD11: 170.24 | JE11: 149.79 | JF11: 430.59 | JG11: 97.73 | JH11: 17.3 | JI11: 48.14 | JJ11: 45.78 | JK11: 97.17 | JL11: 26.26 | JM11: 48.63 | JN11: 70.97 | JO11: 27.48 | JP11: 113.54 | JQ11: 211.44 | JR11: 178.96 | JS11: 17.42 | JT11: 611.68 | JU11: 136 | JV11: 58.48 | JW11: 377.98 | JX11: 268.32 | JY11: 71.19 | JZ11: 47.03 | KA11: 168.97 | KB11: 82.755 | KC11: 185.25 | KD11: 68.38 | KE11: 72.41 | KF11: 172.9 | KG11: 214.41 | KH11: 117.35 | KI11: 132.55 | KJ11: 218.58 | KK11: 584.38 | KL11: 499.34 | KM11: 246.96 | KN11: 200.93 | KO11: 408.35 | KP11: 219.41 | KQ11: 71.97 | KR11: 185.65 | KS11: 8381.5 | KT11: 126.05 | KU11: 188.79 | KV11: 168.45 | KW11: 111.56 | KX11: 109.98 | KY11: 79.7 | KZ11: 321.49 | LA11: 586.03 | LB11: 187.03 | LC11: 92 | LD11: 151.51 | LE11: 288.95 | LF11: 29.07 | LG11: 185.29 | LH11: 680.03 | LI11: 235.01 | LJ11: 173.54 | LK11: 250.42 | LL11: 72.73 | LM11: 77.84 | LN11: 126.71 | LO11: 135.08 | LP11: 544.7 | LQ11: 105.25 | LR11: 359.11 | LS11: 1354 | LT11: 126.22 | LU11: 115.13 | LV11: 39.42 | LW11: 207.13 | LX11: 357.33 | LY11: 74.78 | LZ11: 93.35 | MA11: 464.77 | MB11: 147.07 | MC11: 79.05 | MD11: 610.45 | ME11: 187.99 | MF11: 212.48 | MG11: 63.88 | MH11: 632.73 | MI11: 198.4 | MJ11: 82.8 | MK11: 484.63 | ML11: 56.03 | MM11: 4619.21 | MN11: 272.08 | MO11: 95.11 | MP11: 168.22 | MQ11: 36.46 | MR11: 78.71 | MS11: 198.37 | MT11: 132.18 | MU11: 95.399 | MV11: 152.6 | MW11: 77.4 | MX11: 390.73 | MY11: 232.53 | MZ11: 120.23 | NA11: 80.83 | NB11: 122.89 | NC11: 94.23 | ND11: 332.62 | NE11: 205.17 | NF11: 85.76 | NG11: 73.34 | NH11: 33.24 | NI11: 69.04 | NJ11: 561.53 | NK11: 420.57 | NL11: 109.72 | NM11: 110.98 | NN11: 139.44 | NO11: 527.18 | NP11: 140.12 | NQ11: 154.17 | NR11: 78.52 | NS11: 55.9 | NT11: 85.16 | NU11: 138.54 | NV11: 207.22 | NW11: 110.35 | NX11: 49.21 | NY11: 24.32 | NZ11: 27.8 | OA11: 173.65 | OB11: 93.51 | OC11: 161.11 | OD11: 200.03 | OE11: 142.93 | OF11: 171.9 | OG11: 323.56 | OH11: 147.13 | OI11: 121.64 | OJ11: 147.61 | OK11: 57.47 | OL11: 123.75 | OM11: 247.33 | ON11: 1324.68 | OO11: 29.45 | OP11: 57.66 | OQ11: 140.195 | OR11: 90.25 | OS11: 98.24 | OT11: 38.5 | OU11: 279.9 | OV11: 74.01 | OW11: 53.96 | OX11: 206.98 | OY11: 359.93 | OZ11: 51.8585 | PA11: 148.09 | PB11: 155.09 | PC11: 177.59 | PD11: 1125.17 | PE11: 106.7 | PF11: 104.47 | PG11: 32.81 | PH11: 30.74 | PI11: 187.93 | PJ11: 174.905 | PK11: 83.25 | PL11: 130.62 | PM11: 104.69 | PN11: 428 | PO11: 9.72 | PP11: 623.5 | PQ11: 218.18 | PR11: 782.53 | PS11: 100.63 | PT11: 67.78 | PU11: 107.97 | PV11: 108.18 | PW11: 31.12 | PX11: 63.53 | PY11: 87.48 | PZ11: 168.9 | QA11: 549.68 | QB11: 134.8 | QC11: 89.85 | QD11: 415.11 | QE11: 1006.34 | QF11: 161.51 | QG11: 93.21 | QH11: 40.82 | QI11: 363.71 | QJ11: 511.67 | QK11: 27.82 | QL11: 39.22 | QM11: 108.52 | QN11: 88.43 | QO11: 232.14 | QP11: 211.27 | QQ11: 77.91 | QR11: 39.02 | QS11: 214.92 | QT11: 253.48 | QU11: 166.63 | QV11: 925.23 | QW11: 182.44 | QX11: 302.67 | QY11: 44 | QZ11: 73.66 | RA11: 33.86 | RB11: 442.6 | RC11: 70.03 | RD11: 95.39 | RE11: 132.5 | RF11: 107.06 | RG11: 177.68 | RH11: 102.71 | RI11: 95.18 | RJ11: 332.47 | RK11: 361.72 | RL11: 31.495 | RM11: 17.29 | RN11: 38.3 | RO11: 62.87 | RP11: 32.58 | RQ11: 10.05 | RR11: 534.45 | RS11: 55.35 | RT11: 45.81 | RU11: 23.36 | RV11: 76.87 | RW11: 187.7 | RX11: 97.49 | RY11: 87.33 | RZ11: 210.1876 | SA11: 50.16 | SB11: 442.12 | SC11: 427.1 | SD11: 20.75 | SE11: 295.85
B12: 45680 | C12: 77.36 | D12: 325.87 | E12: 39.18 | F12: 1405.3 | G12: 240.28 | H12: 178.5 | I12: 406.4 | J12: 265.95 | K12: 156.01 | L12: 61.53 | M12: 170.67 | N12: 111.04 | O12: 377.37 | P12: 151.5 | Q12: 110.15 | R12: 122.62 | S12: 200.8 | T12: 33.38 | U12: 414.39 | V12: 698.79 | W12: 226.04 | X12: 146.64 | Y12: 387.85 | Z12: 284.43 | AA12: 96.63 | AB12: 149.63 | AC12: 121.81 | AD12: 46.39 | AE12: 26.44 | AF12: 166.15 | AG12: 22.53 | AH12: 241.51 | AI12: 126.29 | AJ12: 228.35 | AK12: 93.81 | AL12: 62.23 | AM12: 21.57 | AN12: 54.22 | AO12: 446.71 | AP12: 71.33 | AQ12: 294.99 | AR12: 30.48 | AS12: 81.98 | AT12: 74.6 | AU12: 51.21 | AV12: 325.36 | AW12: 58.6 | AX12: 24.36 | AY12: 123.22 | AZ12: 104.47 | BA12: 324 | BB12: 238.15 | BC12: 52.1375 | BD12: 666.93 | BE12: 50.66 | BF12: 531.8 | BG12: 295.8 | BH12: 277.98 | BI12: 3373.57 | BJ12: 193.36 | BK12: 615.96 | BL12: 55.18 | BM12: 613.38 | BN12: 70 | BO12: 84.73 | BP12: 32.45 | BQ12: 240.47 | BR12: 459.83 | BS12: 85.63 | BT12: 101.64 | BU12: 59.14 | BV12: 33.15 | BW12: 29.23 | BX12: 250.11 | BY12: 25.61 | BZ12: 168.12 | CA12: 40.32 | CB12: 160.82 | CC12: 205.25 | CD12: 65.86 | CE12: 87.91 | CF12: 245.3 | CG12: 25.34 | CH12: 90.76 | CI12: 53.98 | CJ12: 207.19 | CK12: 368.91 | CL12: 245.66 | CM12: 137.25 | CN12: 211.74 | CO12: 474.72 | CP12: 53.21 | CQ12: 119.14 | CR12: 199.15 | CS12: 58.69 | CT12: 122.37 | CU12: 109.34 | CV12: 71.07 | CW12: 369.69 | CX12: 242.92 | CY12: 123.03 | CZ12: 114.22 | DA12: 131.17 | DB12: 133.98 | DC12: 364.67 | DD12: 81.9 | DE12: 268.88 | DF12: 53.58 | DG12: 206 | DH12: 524.75 | DI12: 270.03 | DJ12: 105.23 | DK12: 10.16 | DL12: 69.23 | DM12: 19.99 | DN12: 215.58 | DO12: 38.5 | DP12: 87.7 | DQ12: 268.56 | DR12: 59.56 | DS12: 118.32 | DT12: 139.56 | DU12: 1121.41 | DV12: 27.97 | DW12: 219.79 | DX12: 20.65 | DY12: 277.2 | DZ12: 60.449 | EA12: 149.89 | EB12: 70.44 | EC12: 30.86 | ED12: 288 | EE12: 56.96 | EF12: 32.44 | EG12: 293.8 | EH12: 319 | EI12: 259.9 | EJ12: 197.49 | EK12: 400.29 | EL12: 86.46 | EM12: 156.34 | EN12: 219.88 | EO12: 81.77 | EP12: 236.76 | EQ12: 22.69 | ER12: 186.47 | ES12: 58.57 | ET12: 134.51 | EU12: 766.6 | EV12: 359.96 | EW12: 83.93 | EX12: 261.32 | EY12: 453.79 | EZ12: 222.05 | FA12: 217.43 | FB12: 79.44 | FC12: 513.54 | FD12: 89.25 | FE12: 11.14 | FF12: 53.82 | FG12: 32.7113 | FH12: 104.84 | FI12: 476.05 | FJ12: 201.61 | FK12: 41.95 | FL12: 74.29 | FM12: 37.6 | FN12: 256.14 | FO12: 81.87 | FP12: 56.23 | FQ12: 499.77 | FR12: 77.43 | FS12: 122.06 | FT12: 50.34 | FU12: 86.15 | FV12: 104.89 | FW12: 171.55 | FX12: 16.24 | FY12: 680.09 | FZ12: 48.62 | GA12: 32.74 | GB12: 63.92 | GC12: 103.99 | GD12: 116.52 | GE12: 85.37 | GF12: 197.65 | GG12: 123.48 | GH12: 239.51 | GI12: 88.17 | GJ12: 57.28 | GK12: 42.03 | GL12: 82.08 | GM12: 361.11 | GN12: 343.99 | GO12: 102.51 | GP12: 350.81 | GQ12: 190.43 | GR12: 68.3 | GS12: 82.26 | GT12: 46.76 | GU12: 31.93 | GV12: 56.93 | GW12: 88.49 | GX12: 291.59 | GY12: 129.12 | GZ12: 73.7 | HA12: 64.19 | HB12: 200.61 | HC12: 78.21 | HD12: 574.85 | HE12: 122.6 | HF12: 118.37 | HG12: 82.03 | HH12: 418.55 | HI12: 248.05 | HJ12: 173.17 | HK12: 529.77 | HL12: 185.52 | HM12: 59.44 | HN12: 244.32 | HO12: 274.83 | HP12: 29.94 | HQ12: 59.49 | HR12: 97.31 | HS12: 437.28 | HT12: 191.89 | HU12: 11.53 | HV12: 114.3 | HW12: 277.88 | HX12: 223.66 | HY12: 301.08 | HZ12: 197.8 | IA12: 37.47 | IB12: 54.04 | IC12: 760.95 | ID12: 285.07 | IE12: 74.76 | IF12: 110.06 | IG12: 942.16 | IH12: 393.5 | II12: 56.07 | IJ12: 60.51 | IK12: 190.7 | IL12: 129.3 | IM12: 136.07 | IN12: 145.24 | IO12: 118.58 | IP12: 377.62 | IQ12: 1854.6 | IR12: 37.73 | IS12: 196.98 | IT12: 66.06 | IU12: 43.85 | IV12: 92.92 | IW12: 57.54 | IX12: 16.9 | IY12: 132.24 | IZ12: 143.67 | JA12: 109.54 | JB12: 239.24 | JC12: 144.75 | JD12: 174.36 | JE12: 148.61 | JF12: 432.34 | JG12: 97.99 | JH12: 17.47 | JI12: 48.56 | JJ12: 46.03 | JK12: 97.54 | JL12: 26.42 | JM12: 48.43 | JN12: 71.27 | JO12: 27.49 | JP12: 113.38 | JQ12: 210.1 | JR12: 179.5 | JS12: 17.58 | JT12: 598.3 | JU12: 137.8 | JV12: 59.57 | JW12: 377.7 | JX12: 266.5 | JY12: 70.7 | JZ12: 47.34 | KA12: 171.24 | KB12: 84.108 | KC12: 184.66 | KD12: 68.19 | KE12: 72.53 | KF12: 174.86 | KG12: 213.8 | KH12: 116.89 | KI12: 133.61 | KJ12: 217.2 | KK12: 597.17 | KL12: 497.28 | KM12: 247.94 | KN12: 204.03 | KO12: 412.8 | KP12: 219.49 | KQ12: 71.14 | KR12: 186.17 | KS12: 8345.35 | KT12: 126.3 | KU12: 191.54 | KV12: 169.9 | KW12: 110.89 | KX12: 111.31 | KY12: 80.11 | KZ12: 324.52 | LA12: 593.47 | LB12: 189.9 | LC12: 92.52 | LD12: 151.85 | LE12: 290.7 | LF12: 29.07 | LG12: 186.39 | LH12: 694.64 | LI12: 235.42 | LJ12: 174.12 | LK12: 256.52 | LL12: 71.86 | LM12: 78.55 | LN12: 127.74 | LO12: 140.71 | LP12: 551.54 | LQ12: 107 | LR12: 363.26 | LS12: 1349.98 | LT12: 127.01 | LU12: 118.54 | LV12: 39.02 | LW12: 206.65 | LX12: 354.75 | LY12: 74.75 | LZ12: 93.31 | MA12: 464.38 | MB12: 147.22 | MC12: 79.68 | MD12: 608.66 | ME12: 183.82 | MF12: 212.27 | MG12: 64.75 | MH12: 639.5 | MI12: 198.69 | MJ12: 82.81 | MK12: 486.12 | ML12: 56.26 | MM12: 4818.14 | MN12: 272.91 | MO12: 95.89 | MP12: 166.86 | MQ12: 36.45 | MR12: 76.91 | MS12: 197.98 | MT12: 133.25 | MU12: 98.486 | MV12: 152.45 | MW12: 77.49 | MX12: 401.36 | MY12: 233.38 | MZ12: 119.51 | NA12: 81.03 | NB12: 125.43 | NC12: 94.06 | ND12: 334.66 | NE12: 204.14 | NF12: 86.76 | NG12: 73.62 | NH12: 33.67 | NI12: 68.93 | NJ12: 563.41 | NK12: 421.11 | NL12: 111.01 | NM12: 110.01 | NN12: 141.02 | NO12: 534.22 | NP12: 140.2 | NQ12: 157.68 | NR12: 79.29 | NS12: 57.56 | NT12: 85.08 | NU12: 139.18 | NV12: 207.4 | NW12: 110.54 | NX12: 48.11 | NY12: 24.26 | NZ12: 28.8 | OA12: 176.89 | OB12: 95.24 | OC12: 148.91 | OD12: 199.58 | OE12: 151.97 | OF12: 174.11 | OG12: 328.21 | OH12: 146.9 | OI12: 121.58 | OJ12: 154.31 | OK12: 57.38 | OL12: 123.04 | OM12: 248.88 | ON12: 1335.29 | OO12: 29.29 | OP12: 57.61 | OQ12: 140.1356 | OR12: 89.8 | OS12: 97.45 | OT12: 42.39 | OU12: 277.63 | OV12: 74.38 | OW12: 54.13 | OX12: 208.99 | OY12: 362.06 | OZ12: 51.8963 | PA12: 148.62 | PB12: 156.98 | PC12: 176.63 | PD12: 1134.2 | PE12: 106.29 | PF12: 105.09 | PG12: 33.12 | PH12: 30.52 | PI12: 189.07 | PJ12: 170.28 | PK12: 81.23 | PL12: 130.83 | PM12: 104.35 | PN12: 439.73 | PO12: 9.77 | PP12: 636.45 | PQ12: 216.04 | PR12: 788.57 | PS12: 100.45 | PT12: 67.45 | PU12: 103 | PV12: 108.42 | PW12: 31.33 | PX12: 65.12 | PY12: 87.8 | PZ12: 169.75 | QA12: 548.77 | QB12: 131.83 | QC12: 89.73 | QD12: 412.38 | QE12: 1017.73 | QF12: 165.34 | QG12: 93.02 | QH12: 41.47 | QI12: 363.25 | QJ12: 515.08 | QK12: 27.87 | QL12: 39.24 | QM12: 107.86 | QN12: 88.64 | QO12: 234.89 | QP12: 211.39 | QQ12: 78.67 | QR12: 38.64 | QS12: 218.57 | QT12: 255.3 | QU12: 166.96 | QV12: 940.93 | QW12: 183.51 | QX12: 306.36 | QY12: 43.45 | QZ12: 73.6 | RA12: 33.41 | RB12: 440.83 | RC12: 69.88 | RD12: 96.2 | RE12: 133.24 | RF12: 106 | RG12: 183.13 | RH12: 103.27 | RI12: 95.68 | RJ12: 346.22 | RK12: 362.52 | RL12: 31.05 | RM12: 17.43 | RN12: 38.59 | RO12: 63.06 | RP12: 33.26 | RQ12: 10.28 | RR12: 533.24 | RS12: 55.27 | RT12: 45.66 | RU12: 23.51 | RV12: 78.98 | RW12: 187.32 | RX12: 97.47 | RY12: 88.16 | RZ12: 212.609 | SA12: 50.36 | SB12: 447.76 | SC12: 437.71 | SD12: 20.75 | SE12: 296.01
B13: 45681 | C13: 77.36 | D13: 321.34 | E13: 39.54 | F13: 1360.06 | G13: 244.7 | H13: 176.06 | I13: 407.63 | J13: 264.84 | K13: 155.65 | L13: 61.92 | M13: 170.3 | N13: 112.16 | O13: 379.29 | P13: 152.03 | Q13: 108.66 | R13: 121.86 | S13: 196.75 | T13: 32.73 | U13: 414.5 | V13: 678.43 | W13: 224.8 | X13: 146.82 | Y13: 400.03 | Z13: 285.46 | AA13: 95.55 | AB13: 149.43 | AC13: 121.63 | AD13: 46.52 | AE13: 26.09 | AF13: 164.12 | AG13: 22.72 | AH13: 241.86 | AI13: 125.31 | AJ13: 217.37 | AK13: 94.76 | AL13: 62.23 | AM13: 20.83 | AN13: 53.91 | AO13: 444.06 | AP13: 71.78 | AQ13: 293.64 | AR13: 30.27 | AS13: 81.48 | AT13: 73.78 | AU13: 52.05 | AV13: 313.07 | AW13: 60.09 | AX13: 24.37 | AY13: 125.03 | AZ13: 104.91 | BA13: 329.26 | BB13: 232.1 | BC13: 54.7475 | BD13: 662.63 | BE13: 50.51 | BF13: 531.65 | BG13: 297.1 | BH13: 278.93 | BI13: 3332.53 | BJ13: 191.52 | BK13: 620.72 | BL13: 55 | BM13: 610.32 | BN13: 71.02 | BO13: 85.79 | BP13: 32.45 | BQ13: 243.45 | BR13: 463.19 | BS13: 84.73 | BT13: 101.94 | BU13: 59.67 | BV13: 33.92 | BW13: 29.02 | BX13: 247.73 | BY13: 25.42 | BZ13: 166.76 | CA13: 40.64 | CB13: 159.27 | CC13: 207.5 | CD13: 65.82 | CE13: 87.88 | CF13: 252.43 | CG13: 25.78 | CH13: 90.6 | CI13: 54.25 | CJ13: 207.3 | CK13: 367.62 | CL13: 245.8 | CM13: 137.89 | CN13: 213.6 | CO13: 478.77 | CP13: 53.48 | CQ13: 119.96 | CR13: 198.71 | CS13: 58.77 | CT13: 122.35 | CU13: 109.86 | CV13: 71.77 | CW13: 368.98 | CX13: 242.06 | CY13: 123.15 | CZ13: 113.73 | DA13: 130.6 | DB13: 131.82 | DC13: 369.16 | DD13: 82.52 | DE13: 268.82 | DF13: 53.68 | DG13: 204.33 | DH13: 528.53 | DI13: 273.29 | DJ13: 106 | DK13: 10.12 | DL13: 72.83 | DM13: 20.09 | DN13: 214.23 | DO13: 37.81 | DP13: 88.75 | DQ13: 266.43 | DR13: 60.38 | DS13: 117.23 | DT13: 139.51 | DU13: 1121.57 | DV13: 27.8 | DW13: 218.65 | DX13: 20.83 | DY13: 280.35 | DZ13: 60.6599 | EA13: 150.71 | EB13: 70.63 | EC13: 30.88 | ED13: 289.51 | EE13: 57.42 | EF13: 32.36 | EG13: 294.63 | EH13: 322.37 | EI13: 259.9 | EJ13: 195.13 | EK13: 400.86 | EL13: 85.85 | EM13: 157.43 | EN13: 213.43 | EO13: 81.87 | EP13: 237.35 | EQ13: 22.92 | ER13: 183.6 | ES13: 58.7 | ET13: 132.36 | EU13: 785.41 | EV13: 367.58 | EW13: 84.88 | EX13: 262.2 | EY13: 455.26 | EZ13: 219.97 | FA13: 218.96 | FB13: 79.25 | FC13: 513.75 | FD13: 90.19 | FE13: 11.2 | FF13: 54.55 | FG13: 32.3557 | FH13: 103.19 | FI13: 479.18 | FJ13: 200.18 | FK13: 42.04 | FL13: 73.57 | FM13: 37.76 | FN13: 254.67 | FO13: 81.83 | FP13: 56.32 | FQ13: 497.02 | FR13: 77.32 | FS13: 122.17 | FT13: 49.29 | FU13: 86.56 | FV13: 104.53 | FW13: 172.64 | FX13: 16.54 | FY13: 679.34 | FZ13: 48.37 | GA13: 32.88 | GB13: 63.43 | GC13: 101.83 | GD13: 115.69 | GE13: 85.74 | GF13: 199.53 | GG13: 122.78 | GH13: 238.82 | GI13: 88.05 | GJ13: 58.87 | GK13: 42.25 | GL13: 81.83 | GM13: 360.15 | GN13: 345 | GO13: 103.71 | GP13: 350.48 | GQ13: 187.98 | GR13: 68.56 | GS13: 83.48 | GT13: 47 | GU13: 32.17 | GV13: 57.52 | GW13: 88.16 | GX13: 292.19 | GY13: 129.17 | GZ13: 74.77 | HA13: 63.96 | HB13: 185.52 | HC13: 77.2 | HD13: 574.82 | HE13: 122.73 | HF13: 119.34 | HG13: 81.6 | HH13: 417.83 | HI13: 248.78 | HJ13: 172.88 | HK13: 532.51 | HL13: 186.74 | HM13: 60.82 | HN13: 246 | HO13: 277.54 | HP13: 29.99 | HQ13: 59.57 | HR13: 98.01 | HS13: 435.38 | HT13: 191.11 | HU13: 11.6 | HV13: 112.99 | HW13: 275.42 | HX13: 222.78 | HY13: 300.83 | HZ13: 197.39 | IA13: 37.62 | IB13: 55.16 | IC13: 749.82 | ID13: 284.11 | IE13: 74.89 | IF13: 109.9 | IG13: 939.68 | IH13: 394.31 | II13: 56.44 | IJ13: 60.59 | IK13: 186.75 | IL13: 128.83 | IM13: 137.24 | IN13: 142.92 | IO13: 116.56 | IP13: 386.98 | IQ13: 1814.85 | IR13: 37.765 | IS13: 198.95 | IT13: 66.61 | IU13: 44.18 | IV13: 93.07 | IW13: 57.42 | IX13: 17.2 | IY13: 136.75 | IZ13: 146.2 | JA13: 110.92 | JB13: 240.27 | JC13: 146.11 | JD13: 172.11 | JE13: 149.28 | JF13: 435.33 | JG13: 98.81 | JH13: 17.68 | JI13: 49.07 | JJ13: 46.55 | JK13: 99.06 | JL13: 25.68 | JM13: 49.07 | JN13: 70.57 | JO13: 27.44 | JP13: 114.21 | JQ13: 209.43 | JR13: 183.1 | JS13: 17.63 | JT13: 597.95 | JU13: 137.82 | JV13: 56.39 | JW13: 374.92 | JX13: 266.7 | JY13: 71.02 | JZ13: 47.46 | KA13: 173.33 | KB13: 83.6 | KC13: 186.07 | KD13: 68.25 | KE13: 72.59 | KF13: 174.25 | KG13: 214.75 | KH13: 117.31 | KI13: 133.03 | KJ13: 217.01 | KK13: 591.58 | KL13: 496.96 | KM13: 248.48 | KN13: 203.53 | KO13: 411.3 | KP13: 218.07 | KQ13: 72.48 | KR13: 187.61 | KS13: 8200.56 | KT13: 126 | KU13: 190.81 | KV13: 170.28 | KW13: 111.49 | KX13: 111.05 | KY13: 82.48 | KZ13: 320.48 | LA13: 591.93 | LB13: 185.77 | LC13: 91.2 | LD13: 155.28 | LE13: 288.43 | LF13: 29.31 | LG13: 185.08 | LH13: 675.79 | LI13: 234.85 | LJ13: 173.88 | LK13: 256 | LL13: 73.56 | LM13: 77.19 | LN13: 127.03 | LO13: 139.63 | LP13: 546.19 | LQ13: 108.16 | LR13: 362.41 | LS13: 1341.82 | LT13: 128.26 | LU13: 118.93 | LV13: 39.21 | LW13: 210.73 | LX13: 358.03 | LY13: 74.97 | LZ13: 94.12 | MA13: 467.12 | MB13: 142.62 | MC13: 80.05 | MD13: 584.05 | ME13: 185.49 | MF13: 211.83 | MG13: 64.81 | MH13: 636.9 | MI13: 196.83 | MJ13: 82.71 | MK13: 489.65 | ML13: 54.5 | MM13: 4764.89 | MN13: 272.99 | MO13: 97.7 | MP13: 164.97 | MQ13: 35.96 | MR13: 77.05 | MS13: 200.21 | MT13: 132.53 | MU13: 97.759 | MV13: 151.44 | MW13: 77.42 | MX13: 400.96 | MY13: 234.68 | MZ13: 119.1 | NA13: 81.15 | NB13: 127.28 | NC13: 93.11 | ND13: 333.88 | NE13: 202.72 | NF13: 86.03 | NG13: 74.65 | NH13: 32.69 | NI13: 68.99 | NJ13: 563.58 | NK13: 414.61 | NL13: 110.81 | NM13: 110.64 | NN13: 141.13 | NO13: 533.49 | NP13: 140.99 | NQ13: 157.47 | NR13: 79.23 | NS13: 56.7 | NT13: 84.99 | NU13: 140.74 | NV13: 210.9 | NW13: 112.37 | NX13: 48.28 | NY13: 24.47 | NZ13: 28.21 | OA13: 171.23 | OB13: 88.1 | OC13: 145.59 | OD13: 201.9 | OE13: 153.08 | OF13: 168.25 | OG13: 330.2 | OH13: 148.41 | OI13: 121.57 | OJ13: 151.61 | OK13: 57.94 | OL13: 122.84 | OM13: 250.51 | ON13: 1331.1 | OO13: 29.6 | OP13: 57.7 | OQ13: 139.5813 | OR13: 88.76 | OS13: 96.9 | OT13: 41.41 | OU13: 277.93 | OV13: 74.16 | OW13: 54.34 | OX13: 208.86 | OY13: 353.74 | OZ13: 50.9366 | PA13: 149.12 | PB13: 154.69 | PC13: 173.26 | PD13: 1124.98 | PE13: 106.25 | PF13: 106.54 | PG13: 32.89 | PH13: 30.51 | PI13: 188.96 | PJ13: 169.96 | PK13: 79.68 | PL13: 125.3 | PM13: 103.01 | PN13: 439.62 | PO13: 9.76 | PP13: 647.49 | PQ13: 218.57 | PR13: 789.56 | PS13: 101.63 | PT13: 67.18 | PU13: 105 | PV13: 108.19 | PW13: 31.58 | PX13: 64.58 | PY13: 88.67 | PZ13: 172.06 | QA13: 548.56 | QB13: 129.92 | QC13: 89.11 | QD13: 406.58 | QE13: 1020.45 | QF13: 165.53 | QG13: 92.76 | QH13: 41.37 | QI13: 365.14 | QJ13: 514.41 | QK13: 28.08 | QL13: 39.38 | QM13: 109.05 | QN13: 88.49 | QO13: 233.3 | QP13: 209.07 | QQ13: 77.19 | QR13: 38.34 | QS13: 217.16 | QT13: 258.28 | QU13: 168.61 | QV13: 940.85 | QW13: 180.5 | QX13: 304.33 | QY13: 43.5 | QZ13: 74.99 | RA13: 33.27 | RB13: 439.25 | RC13: 70.12 | RD13: 96.67 | RE13: 127.09 | RF13: 106 | RG13: 183.32 | RH13: 101.75 | RI13: 97.7 | RJ13: 347.44 | RK13: 363.1 | RL13: 31.15 | RM13: 16.94 | RN13: 38.98 | RO13: 63.52 | RP13: 34.06 | RQ13: 10.25 | RR13: 531.37 | RS13: 56.02 | RT13: 45.55 | RU13: 23.32 | RV13: 78.98 | RW13: 187.7 | RX13: 98.18 | RY13: 88.67 | RZ13: 208.699 | SA13: 51.12 | SB13: 434.23 | SC13: 420.49 | SD13: 20.78 | SE13: 298
B14: 45685 | C14: 78.31 | D14: 317.04 | E14: 40.4 | F14: 1275.23 | G14: 207.36 | H14: 177.78 | I14: 390.29 | J14: 267.14 | K14: 156.21 | L14: 62.36 | M14: 174.81 | N14: 112.14 | O14: 378.85 | P14: 155.1 | Q14: 108.04 | R14: 121.18 | S14: 194.43 | T14: 32.74 | U14: 418.83 | V14: 617.57 | W14: 225.66 | X14: 150.38 | Y14: 409.42 | Z14: 291.15 | AA14: 97.45 | AB14: 151.4 | AC14: 126.33 | AD14: 46.84 | AE14: 26.75 | AF14: 166.19 | AG14: 24.4 | AH14: 248.43 | AI14: 128.35 | AJ14: 209.52 | AK14: 97.29 | AL14: 59.43 | AM14: 19.8 | AN14: 50.04 | AO14: 447.2 | AP14: 72.71 | AQ14: 302.82 | AR14: 27.46 | AS14: 79.94 | AT14: 75.17 | AU14: 52.6 | AV14: 328.7 | AW14: 59.12 | AX14: 21.46 | AY14: 127.39 | AZ14: 107.28 | BA14: 327 | BB14: 265.25 | BC14: 51.9375 | BD14: 662.59 | BE14: 50.59 | BF14: 438.27 | BG14: 298.31 | BH14: 281.85 | BI14: 3318.58 | BJ14: 193.3 | BK14: 628.34 | BL14: 55.59 | BM14: 637.53 | BN14: 74.08 | BO14: 86.34 | BP14: 32.69 | BQ14: 249.08 | BR14: 469.97 | BS14: 86.78 | BT14: 102.32 | BU14: 58.76 | BV14: 33.06 | BW14: 27.9 | BX14: 253.66 | BY14: 27.77 | BZ14: 169.52 | CA14: 41.29 | CB14: 159.5 | CC14: 213.75 | CD14: 65.61 | CE14: 89.86 | CF14: 255.14 | CG14: 25.61 | CH14: 93.39 | CI14: 51.23 | CJ14: 214.35 | CK14: 350.27 | CL14: 247.84 | CM14: 141.06 | CN14: 214.7 | CO14: 479.99 | CP14: 55.31 | CQ14: 120.56 | CR14: 198.08 | CS14: 58.87 | CT14: 127.05 | CU14: 111.31 | CV14: 72.53 | CW14: 312.67 | CX14: 249.52 | CY14: 125.59 | CZ14: 101.29 | DA14: 130 | DB14: 130.25 | DC14: 371.48 | DD14: 77.62 | DE14: 273.35 | DF14: 49.9 | DG14: 203.43 | DH14: 542.54 | DI14: 278.65 | DJ14: 105.02 | DK14: 10.08 | DL14: 70.54 | DM14: 20.28 | DN14: 217.78 | DO14: 35.84 | DP14: 88.35 | DQ14: 262.57 | DR14: 59.8 | DS14: 117.31 | DT14: 141.46 | DU14: 1131.28 | DV14: 26.65 | DW14: 213.3 | DX14: 20.66 | DY14: 275.97 | DZ14: 60.562 | EA14: 149.73 | EB14: 66.66 | EC14: 30.46 | ED14: 293.41 | EE14: 56.91 | EF14: 32.31 | EG14: 303.11 | EH14: 326.07 | EI14: 258.71 | EJ14: 194.76 | EK14: 365.76 | EL14: 86.54 | EM14: 149.19 | EN14: 213.43 | EO14: 81.8 | EP14: 237.91 | EQ14: 22.93 | ER14: 164 | ES14: 60.37 | ET14: 136.03 | EU14: 804.99 | EV14: 365.38 | EW14: 85.75 | EX14: 264.41 | EY14: 413.36 | EZ14: 221.17 | FA14: 220.88 | FB14: 80.4 | FC14: 520.45 | FD14: 91.98 | FE14: 11.2 | FF14: 57.33 | FG14: 31.9249 | FH14: 88.25 | FI14: 465.24 | FJ14: 203.63 | FK14: 41.35 | FL14: 74.39 | FM14: 36.42 | FN14: 252.32 | FO14: 82.89 | FP14: 57.69 | FQ14: 486.64 | FR14: 77.88 | FS14: 126.55 | FT14: 49 | FU14: 87.21 | FV14: 100.6 | FW14: 171.51 | FX14: 15.96 | FY14: 666.23 | FZ14: 49.32 | GA14: 32.84 | GB14: 62.8 | GC14: 101.38 | GD14: 115.05 | GE14: 86.49 | GF14: 201.72 | GG14: 123.01 | GH14: 245.05 | GI14: 81.74 | GJ14: 56.11 | GK14: 41.32 | GL14: 81.7 | GM14: 364.17 | GN14: 343.29 | GO14: 105.33 | GP14: 352.59 | GQ14: 182.89 | GR14: 68.07 | GS14: 83.54 | GT14: 47.27 | GU14: 31.85 | GV14: 59.34 | GW14: 88.84 | GX14: 297.48 | GY14: 106.54 | GZ14: 72.28 | HA14: 64.28 | HB14: 180.57 | HC14: 76.82 | HD14: 584.29 | HE14: 124.34 | HF14: 121.61 | HG14: 76.12 | HH14: 413.24 | HI14: 249.16 | HJ14: 167.92 | HK14: 542.48 | HL14: 185.59 | HM14: 60.83 | HN14: 248.51 | HO14: 275.1 | HP14: 30.77 | HQ14: 55.2 | HR14: 98.92 | HS14: 442.84 | HT14: 149.64 | HU14: 11.01 | HV14: 114.19 | HW14: 280.3 | HX14: 238.26 | HY14: 309.93 | HZ14: 200.43 | IA14: 37.55 | IB14: 54.9 | IC14: 702.92 | ID14: 288.64 | IE14: 76.69 | IF14: 107.25 | IG14: 958.67 | IH14: 395.15 | II14: 56.48 | IJ14: 60.33 | IK14: 172.85 | IL14: 127.73 | IM14: 139.42 | IN14: 143.95 | IO14: 116.53 | IP14: 406.73 | IQ14: 1851.1 | IR14: 37.395 | IS14: 199.82 | IT14: 66.43 | IU14: 44.78 | IV14: 93.85 | IW14: 58.29 | IX14: 17.23 | IY14: 137.15 | IZ14: 145.49 | JA14: 112.41 | JB14: 238.41 | JC14: 147.48 | JD14: 171.55 | JE14: 147.92 | JF14: 417.86 | JG14: 100.41 | JH14: 17.65 | JI14: 50.04 | JJ14: 47.58 | JK14: 100.4 | JL14: 28.44 | JM14: 48.44 | JN14: 69.87 | JO14: 27.8 | JP14: 115.65 | JQ14: 213.65 | JR14: 183.09 | JS14: 19.34 | JT14: 600.66 | JU14: 138.54 | JV14: 56.28 | JW14: 408.68 | JX14: 272.27 | JY14: 71.77 | JZ14: 47.35 | KA14: 161.72 | KB14: 85.223 | KC14: 190.96 | KD14: 69.26 | KE14: 73.15 | KF14: 175.62 | KG14: 219.35 | KH14: 121.18 | KI14: 135.42 | KJ14: 221.06 | KK14: 602.95 | KL14: 457.45 | KM14: 255.1 | KN14: 203.12 | KO14: 413.48 | KP14: 220.5 | KQ14: 74.95 | KR14: 192.4 | KS14: 8064.09 | KT14: 119.53 | KU14: 189.99 | KV14: 173.21 | KW14: 113.42 | KX14: 98.78 | KY14: 82.97 | KZ14: 299.3 | LA14: 619.85 | LB14: 188.71 | LC14: 89.81 | LD14: 157.13 | LE14: 282.24 | LF14: 29.59 | LG14: 186.93 | LH14: 686.33 | LI14: 238.15 | LJ14: 175.15 | LK14: 257.45 | LL14: 73.18 | LM14: 68.58 | LN14: 126.41 | LO14: 138.13 | LP14: 526.12 | LQ14: 109.82 | LR14: 378.39 | LS14: 1329.48 | LT14: 129.24 | LU14: 120.21 | LV14: 40.19 | LW14: 213.17 | LX14: 293.98 | LY14: 76.1 | LZ14: 93.22 | MA14: 470.62 | MB14: 128.99 | MC14: 80.96 | MD14: 574.14 | ME14: 187.14 | MF14: 216.06 | MG14: 67.19 | MH14: 637.8 | MI14: 201.67 | MJ14: 81.75 | MK14: 493 | ML14: 53.87 | MM14: 4684.68 | MN14: 269.72 | MO14: 100.54 | MP14: 163.64 | MQ14: 34.88 | MR14: 74.6 | MS14: 195.3 | MT14: 132.11 | MU14: 97.183 | MV14: 150.34 | MW14: 75.27 | MX14: 405.4 | MY14: 234.39 | MZ14: 118.6 | NA14: 81.19 | NB14: 128.96 | NC14: 90.94 | ND14: 359.95 | NE14: 195.77 | NF14: 85.68 | NG14: 73.79 | NH14: 32.68 | NI14: 72.56 | NJ14: 571.84 | NK14: 405.59 | NL14: 111.86 | NM14: 112.59 | NN14: 142.6 | NO14: 547.36 | NP14: 151.89 | NQ14: 158.84 | NR14: 80.36 | NS14: 57.83 | NT14: 84.33 | NU14: 142.43 | NV14: 215.71 | NW14: 100.87 | NX14: 48.65 | NY14: 24.75 | NZ14: 28.18 | OA14: 171.77 | OB14: 90.25 | OC14: 141.49 | OD14: 197.07 | OE14: 158.44 | OF14: 160.24 | OG14: 334.48 | OH14: 151.41 | OI14: 121.34 | OJ14: 150.64 | OK14: 57.38 | OL14: 114.17 | OM14: 249.94 | ON14: 1352.82 | OO14: 30.01 | OP14: 57.31 | OQ14: 135.9883 | OR14: 85.9 | OS14: 99.83 | OT14: 44.94 | OU14: 281.2 | OV14: 76.12 | OW14: 54.98 | OX14: 205.06 | OY14: 350.15 | OZ14: 47.5061 | PA14: 150.25 | PB14: 148.45 | PC14: 169.25 | PD14: 1170.39 | PE14: 107.53 | PF14: 108.71 | PG14: 33.5 | PH14: 31.09 | PI14: 190.93 | PJ14: 172.66 | PK14: 74.51 | PL14: 124.39 | PM14: 102.73 | PN14: 440.68 | PO14: 9.81 | PP14: 674.33 | PQ14: 221.14 | PR14: 766.95 | PS14: 97.25 | PT14: 67.65 | PU14: 106.34 | PV14: 100.27 | PW14: 31.65 | PX14: 64.72 | PY14: 88.64 | PZ14: 169.31 | QA14: 542.17 | QB14: 121.945 | QC14: 88.19 | QD14: 398.09 | QE14: 1051.2 | QF14: 167.05 | QG14: 95.21 | QH14: 41.42 | QI14: 367.47 | QJ14: 509.18 | QK14: 28.15 | QL14: 39.81 | QM14: 110.38 | QN14: 89.75 | QO14: 226.17 | QP14: 202.37 | QQ14: 77.26 | QR14: 38.13 | QS14: 215.92 | QT14: 270.43 | QU14: 170.42 | QV14: 906.81 | QW14: 162.14 | QX14: 307.42 | QY14: 43.23 | QZ14: 74.88 | RA14: 28.18 | RB14: 435.51 | RC14: 67.3 | RD14: 95.87 | RE14: 131.05 | RF14: 102.13 | RG14: 184.49 | RH14: 103.45 | RI14: 98.5 | RJ14: 278.8 | RK14: 360.75 | RL14: 31.34 | RM14: 17.05 | RN14: 39.35 | RO14: 63.21 | RP14: 35.42 | RQ14: 10.25 | RR14: 549.62 | RS14: 54.34 | RT14: 43.28 | RU14: 23.34 | RV14: 80.23 | RW14: 192.94 | RX14: 100 | RY14: 87.78 | RZ14: 207.9358 | SA14: 49.4 | SB14: 429.81 | SC14: 355.12 | SD14: 21.36 | SE14: 281.82
B15: 45686 | C15: 77.86 | D15: 315.25 | E15: 40.28 | F15: 1271.99 | G15: 206.35 | H15: 173.66 | I15: 393.23 | J15: 266.58 | K15: 155.69 | L15: 62.83 | M15: 175.26 | N15: 113.19 | O15: 381.22 | P15: 153.02 | Q15: 108.67 | R15: 122.16 | S15: 199.1 | T15: 32.61 | U15: 413.42 | V15: 618.76 | W15: 228.63 | X15: 151.15 | Y15: 411.16 | Z15: 290.11 | AA15: 98.28 | AB15: 151.54 | AC15: 124.25 | AD15: 46.75 | AE15: 26.62 | AF15: 166.23 | AG15: 24.23 | AH15: 249.52 | AI15: 125.13 | AJ15: 209.91 | AK15: 97.5 | AL15: 59.55 | AM15: 19.75 | AN15: 49.78 | AO15: 442.33 | AP15: 72.04 | AQ15: 303.31 | AR15: 27.3 | AS15: 80.63 | AT15: 75.41 | AU15: 52.66 | AV15: 327.62 | AW15: 57.98 | AX15: 21.66 | AY15: 127.86 | AZ15: 107.62 | BA15: 327.31 | BB15: 269.09 | BC15: 52.8125 | BD15: 604.33 | BE15: 51.66 | BF15: 439.41 | BG15: 300.57 | BH15: 282.59 | BI15: 3314.05 | BJ15: 192.91 | BK15: 593.05 | BL15: 55.33 | BM15: 639.97 | BN15: 71.4 | BO15: 86.04 | BP15: 32.78 | BQ15: 246.9 | BR15: 469.26 | BS15: 85.09 | BT15: 102.71 | BU15: 59.05 | BV15: 32.62 | BW15: 28.24 | BX15: 253.93 | BY15: 27.91 | BZ15: 168.62 | CA15: 40.79 | CB15: 157.81 | CC15: 206.47 | CD15: 65.77 | CE15: 89.57 | CF15: 251.85 | CG15: 25.9 | CH15: 92.57 | CI15: 49.8 | CJ15: 213.91 | CK15: 354.02 | CL15: 223.73 | CM15: 140.09 | CN15: 216.7 | CO15: 478.16 | CP15: 55.1 | CQ15: 122.59 | CR15: 197.36 | CS15: 58.59 | CT15: 129.17 | CU15: 110.62 | CV15: 71.33 | CW15: 317.6 | CX15: 246.93 | CY15: 123.52 | CZ15: 103.1 | DA15: 128.85 | DB15: 130.23 | DC15: 366.74 | DD15: 79.24 | DE15: 271.18 | DF15: 50.62 | DG15: 198.07 | DH15: 537.99 | DI15: 275.06 | DJ15: 103.17 | DK15: 10.21 | DL15: 70.89 | DM15: 20.05 | DN15: 214.34 | DO15: 36.28 | DP15: 86.43 | DQ15: 251.45 | DR15: 59.9 | DS15: 116.34 | DT15: 141.03 | DU15: 1114.01 | DV15: 26.37 | DW15: 211.95 | DX15: 20.21 | DY15: 277.11 | DZ15: 60.7578 | EA15: 149.23 | EB15: 68.77 | EC15: 30.18 | ED15: 294.1 | EE15: 57.13 | EF15: 32.3 | EG15: 294.23 | EH15: 324.54 | EI15: 256.38 | EJ15: 195.53 | EK15: 364 | EL15: 86 | EM15: 148.12 | EN15: 213.01 | EO15: 81.77 | EP15: 235.56 | EQ15: 22.42 | ER15: 162.02 | ES15: 61.06 | ET15: 132.23 | EU15: 804.08 | EV15: 359.33 | EW15: 86.02 | EX15: 261.73 | EY15: 417.71 | EZ15: 218.88 | FA15: 219.31 | FB15: 79.69 | FC15: 517.22 | FD15: 91.41 | FE15: 11.33 | FF15: 56.9 | FG15: 31.9877 | FH15: 89.01 | FI15: 463.41 | FJ15: 204.02 | FK15: 41.59 | FL15: 76.58 | FM15: 36.64 | FN15: 256.74 | FO15: 83.38 | FP15: 57.28 | FQ15: 481.54 | FR15: 78.37 | FS15: 126.87 | FT15: 48.83 | FU15: 86.81 | FV15: 100.38 | FW15: 172.02 | FX15: 15.79 | FY15: 665.81 | FZ15: 48.75 | GA15: 32.73 | GB15: 62.68 | GC15: 101.56 | GD15: 112.99 | GE15: 85.9 | GF15: 202.18 | GG15: 122.38 | GH15: 246.4 | GI15: 81.7 | GJ15: 55.8 | GK15: 40.94 | GL15: 82.06 | GM15: 360.41 | GN15: 339.57 | GO15: 105.89 | GP15: 353.04 | GQ15: 182.52 | GR15: 66.75 | GS15: 82.83 | GT15: 47.44 | GU15: 31.65 | GV15: 58.67 | GW15: 88.39 | GX15: 294.26 | GY15: 107.84 | GZ15: 71.92 | HA15: 65 | HB15: 180.27 | HC15: 76.22 | HD15: 568.23 | HE15: 124.21 | HF15: 121.95 | HG15: 76.28 | HH15: 410.66 | HI15: 249.55 | HJ15: 168.33 | HK15: 538.1 | HL15: 185.38 | HM15: 59.6 | HN15: 246.22 | HO15: 272.2 | HP15: 30.54 | HQ15: 55.33 | HR15: 98.03 | HS15: 441.68 | HT15: 155.21 | HU15: 11.15 | HV15: 114.3 | HW15: 281.68 | HX15: 239.36 | HY15: 304.17 | HZ15: 198.56 | IA15: 37.36 | IB15: 54.95 | IC15: 712.97 | ID15: 289.66 | IE15: 76.93 | IF15: 110.89 | IG15: 964.02 | IH15: 391.07 | II15: 56.6 | IJ15: 61.51 | IK15: 175.28 | IL15: 127.76 | IM15: 138.27 | IN15: 141.93 | IO15: 117.1 | IP15: 393.91 | IQ15: 1860.21 | IR15: 37.04 | IS15: 200.36 | IT15: 66.07 | IU15: 44.17 | IV15: 95.59 | IW15: 58.55 | IX15: 17.17 | IY15: 134.93 | IZ15: 144.41 | JA15: 112.6 | JB15: 215.12 | JC15: 146.89 | JD15: 171.71 | JE15: 150.15 | JF15: 418.75 | JG15: 108.58 | JH15: 17.67 | JI15: 50.43 | JJ15: 47.85 | JK15: 100.85 | JL15: 28.46 | JM15: 47.66 | JN15: 69.22 | JO15: 27.63 | JP15: 114.31 | JQ15: 209.55 | JR15: 182.23 | JS15: 19 | JT15: 592.99 | JU15: 138.71 | JV15: 56.03 | JW15: 397.07 | JX15: 275.83 | JY15: 71.41 | JZ15: 47.62 | KA15: 160.98 | KB15: 85.872 | KC15: 190.81 | KD15: 68.48 | KE15: 73.72 | KF15: 173.63 | KG15: 214.95 | KH15: 122.33 | KI15: 133.78 | KJ15: 220.28 | KK15: 603.18 | KL15: 454.36 | KM15: 255.94 | KN15: 203.91 | KO15: 404.17 | KP15: 217.97 | KQ15: 74.2 | KR15: 193.8 | KS15: 7965.01 | KT15: 120.28 | KU15: 185.84 | KV15: 173.77 | KW15: 113.5 | KX15: 100.61 | KY15: 82.28 | KZ15: 289.88 | LA15: 607.41 | LB15: 187.18 | LC15: 90.16 | LD15: 155.44 | LE15: 278.9 | LF15: 29.66 | LG15: 183.63 | LH15: 687.27 | LI15: 237.07 | LJ15: 172.91 | LK15: 256.81 | LL15: 68.84 | LM15: 69.38 | LN15: 126.36 | LO15: 139.48 | LP15: 512.71 | LQ15: 107.93 | LR15: 374.42 | LS15: 1338.92 | LT15: 129.17 | LU15: 119.17 | LV15: 39.67 | LW15: 213.78 | LX15: 297.8 | LY15: 79.87 | LZ15: 92.79 | MA15: 464.63 | MB15: 123.7 | MC15: 81.19 | MD15: 572.71 | ME15: 190.09 | MF15: 212.31 | MG15: 66 | MH15: 637.38 | MI15: 198.1 | MJ15: 81.98 | MK15: 490.32 | ML15: 53.77 | MM15: 4721.86 | MN15: 300.46 | MO15: 100.41 | MP15: 161.64 | MQ15: 35.07 | MR15: 71.83 | MS15: 195.41 | MT15: 131 | MU15: 97.815 | MV15: 147.09 | MW15: 74.77 | MX15: 400.3 | MY15: 232.5 | MZ15: 117.6 | NA15: 81.73 | NB15: 129.59 | NC15: 91.2 | ND15: 354 | NE15: 192.89 | NF15: 86.64 | NG15: 74.39 | NH15: 32.98 | NI15: 71.13 | NJ15: 575.13 | NK15: 399.59 | NL15: 111.05 | NM15: 110.58 | NN15: 141.64 | NO15: 548.8 | NP15: 145.72 | NQ15: 157.22 | NR15: 80.64 | NS15: 58.27 | NT15: 84.11 | NU15: 142.47 | NV15: 216.91 | NW15: 100.57 | NX15: 49.1 | NY15: 24.58 | NZ15: 28.68 | OA15: 171.27 | OB15: 92.52 | OC15: 140.27 | OD15: 197.18 | OE15: 156.92 | OF15: 166.01 | OG15: 335.88 | OH15: 148.56 | OI15: 121.25 | OJ15: 151.39 | OK15: 57.16 | OL15: 117.35 | OM15: 252.86 | ON15: 1335.5 | OO15: 29.64 | OP15: 57.32 | OQ15: 135.8597 | OR15: 86.28 | OS15: 99.33 | OT15: 40.72 | OU15: 276.62 | OV15: 75.65 | OW15: 54.06 | OX15: 206.81 | OY15: 344.7 | OZ15: 47.4532 | PA15: 150.37 | PB15: 147.71 | PC15: 170.86 | PD15: 1143.63 | PE15: 106.77 | PF15: 107.18 | PG15: 34.01 | PH15: 30.67 | PI15: 189.08 | PJ15: 171.93 | PK15: 75.15 | PL15: 125.94 | PM15: 101.65 | PN15: 441.52 | PO15: 9.75 | PP15: 676.49 | PQ15: 235.15 | PR15: 758.39 | PS15: 95.79 | PT15: 68.43 | PU15: 108.26 | PV15: 99.38 | PW15: 31.69 | PX15: 63.91 | PY15: 90.03 | PZ15: 171.1 | QA15: 539.84 | QB15: 122.05 | QC15: 88.76 | QD15: 389.1 | QE15: 1052.61 | QF15: 166.3 | QG15: 93.82 | QH15: 41.05 | QI15: 351.51 | QJ15: 508.75 | QK15: 28.2 | QL15: 39.57 | QM15: 110.32 | QN15: 87.89 | QO15: 224.45 | QP15: 202.86 | QQ15: 78.22 | QR15: 37.84 | QS15: 218.9 | QT15: 265.4 | QU15: 170.22 | QV15: 908.23 | QW15: 161.73 | QX15: 304.28 | QY15: 43.43 | QZ15: 74.5 | RA15: 27.8 | RB15: 438.32 | RC15: 64.8 | RD15: 94.65 | RE15: 132.58 | RF15: 102.57 | RG15: 185.78 | RH15: 102.85 | RI15: 98 | RJ15: 291.89 | RK15: 366.34 | RL15: 31.86 | RM15: 16.59 | RN15: 38.67 | RO15: 63.02 | RP15: 35.18 | RQ15: 10.43 | RR15: 543.02 | RS15: 53.56 | RT15: 43.07 | RU15: 23.18 | RV15: 79.76 | RW15: 185.42 | RX15: 98.05 | RY15: 87.85 | RZ15: 208.2656 | SA15: 51.15 | SB15: 427.78 | SC15: 353.25 | SD15: 21.31 | SE15: 291
... B239: 45994 | C239: 46.03 | D239: 368.13 | E239: 40.67 | F239: 914.72 | G239: 380.61 | H239: 202.54 | I239: 591.49 | J239: 312.13 | K239: 151.59 | L239: 70.81 | M239: 230.24 | N239: 105.74 | O239: 299.89 | P239: 132.24 | Q239: 117.8 | R239: 139.85 | S239: 288.49 | T239: 25.19 | U239: 357.91 | V239: 958.02 | W239: 302.62 | X239: 205.33 | Y239: 182.3 | Z239: 307.71 | AA239: 102.27 | AB239: 173.09 | AC239: 130.97 | AD239: 54.09 | AE239: 25.57 | AF239: 146.71 | AG239: 25.32 | AH239: 284.27 | AI239: 168.45 | AJ239: 278.24 | AK239: 114.41 | AL239: 77.75 | AM239: 43.76 | AN239: 74.69 | AO239: 477.73 | AP239: 109.89 | AQ239: 270.32 | AR239: 27.17 | AS239: 106.72 | AT239: 77.07 | AU239: 58.41 | AV239: 486.77 | AW239: 39.22 | AX239: 22.26 | AY239: 125.29 | AZ239: 109.04 | BA239: 260.35 | BB239: 265.77 | BC239: 64.96 | BD239: 500.01 | BE239: 59.8 | BF239: 612 | BG239: 260.22 | BH239: 224.48 | BI239: 3822.92 | BJ239: 175.59 | BK239: 545.56 | BL239: 48.78 | BM239: 543.55 | BN239: 69.1 | BO239: 113.09 | BP239: 18.89 | BQ239: 193.57 | BR239: 503.6 | BS239: 74.38 | BT239: 98.57 | BU239: 50.96 | BV239: 30.09 | BW239: 27.16 | BX239: 280.24 | BY239: 26.04 | BZ239: 114.44 | CA239: 35.75 | CB239: 105.17 | CC239: 164.56 | CD239: 72.19 | CE239: 78.2 | CF239: 200 | CG239: 17.16 | CH239: 96.45 | CI239: 83.55 | CJ239: 130.08 | CK239: 507.81 | CL239: 228.46 | CM239: 90.92 | CN239: 178.34 | CO239: 481.82 | CP239: 60.03 | CQ239: 38.61 | CR239: 190.27 | CS239: 66.38 | CT239: 171.5 | CU239: 118.62 | CV239: 69.935 | CW239: 335.57 | CX239: 264.33 | CY239: 103.26 | CZ239: 133.63 | DA239: 134.89 | DB239: 111.51 | DC239: 344.45 | DD239: 94.24 | DE239: 209.75 | DF239: 61.17 | DG239: 227.24 | DH239: 231.91 | DI239: 270.45 | DJ239: 79.65 | DK239: 13.09 | DL239: 84.95 | DM239: 23.01 | DN239: 199.46 | DO239: 44.53 | DP239: 64.85 | DQ239: 338.08 | DR239: 46.2 | DS239: 129.47 | DT239: 171.15 | DU239: 971.16 | DV239: 27.4 | DW239: 277.74 | DX239: 17.29 | DY239: 307.56 | DZ239: 53.45 | EA239: 180.63 | EB239: 79.15 | EC239: 23.27 | ED239: 245.36 | EE239: 56.03 | EF239: 38.38 | EG239: 256.92 | EH239: 316.53 | EI239: 250.04 | EJ239: 143.68 | EK239: 409.07 | EL239: 67.12 | EM239: 159.17 | EN239: 227.56 | EO239: 83.14 | EP239: 230.46 | EQ239: 20.41 | ER239: 207.73 | ES239: 66.2 | ET239: 133.13 | EU239: 1033.56 | EV239: 199.955 | EW239: 105.75 | EX239: 246.94 | EY239: 429.34 | EZ239: 178.21 | FA239: 183.87 | FB239: 64.62 | FC239: 499.88 | FD239: 101.97 | FE239: 10.84 | FF239: 75 | FG239: 39.66 | FH239: 234.16 | FI239: 375.69 | FJ239: 253.9 | FK239: 89.65 | FL239: 65.65 | FM239: 41.88 | FN239: 294.05 | FO239: 85.94 | FP239: 65.97 | FQ239: 553.32 | FR239: 89.35 | FS239: 164.71 | FT239: 42.45 | FU239: 71 | FV239: 74.89 | FW239: 158.79 | FX239: 15.23 | FY239: 869.2 | FZ239: 60.62 | GA239: 34.81 | GB239: 78.09 | GC239: 91.81 | GD239: 130.33 | GE239: 88.62 | GF239: 198 | GG239: 101.34 | GH239: 227.18 | GI239: 80.54 | GJ239: 57.3 | GK239: 37.55 | GL239: 93.99 | GM239: 339.24 | GN239: 284.31 | GO239: 100.36 | GP239: 344.34 | GQ239: 199.22 | GR239: 90.68 | GS239: 87.98 | GT239: 47.42 | GU239: 35.68 | GV239: 71.65 | GW239: 72.53 | GX239: 278.25 | GY239: 127.8 | GZ239: 73.36 | HA239: 65.3 | HB239: 182.6 | HC239: 83.7 | HD239: 580.45 | HE239: 150.06 | HF239: 130.82 | HG239: 114.22 | HH239: 544.52 | HI239: 235.23 | HJ239: 206.61 | HK239: 339.71 | HL239: 151.52 | HM239: 80 | HN239: 265.76 | HO239: 292.59 | HP239: 21.87 | HQ239: 61.55 | HR239: 107.29 | HS239: 326.78 | HT239: 171.65 | HU239: 13.71 | HV239: 148.09 | HW239: 345.42 | HX239: 284.15 | HY239: 307.24 | HZ239: 184.71 | IA239: 27.43 | IB239: 46.24 | IC239: 1211.75 | ID239: 306.65 | IE239: 64.12 | IF239: 108.54 | IG239: 922.26 | IH239: 365.95 | II239: 56.78 | IJ239: 60.49 | IK239: 268.63 | IL239: 199.71 | IM239: 162.83 | IN239: 165 | IO239: 203.21 | IP239: 296.21 | IQ239: 1762.35 | IR239: 41.22 | IS239: 195.63 | IT239: 78.39 | IU239: 44.93 | IV239: 125 | IW239: 82.47 | IX239: 17.04 | IY239: 201.92 | IZ239: 180.75 | JA239: 132.16 | JB239: 197.95 | JC239: 113.39 | JD239: 175.07 | JE239: 178 | JF239: 725.93 | JG239: 87.11 | JH239: 18.75 | JI239: 66.45 | JJ239: 59.33 | JK239: 120.9 | JL239: 18.83 | JM239: 50.93 | JN239: 67.32 | JO239: 27.19 | JP239: 105.05 | JQ239: 216.15 | JR239: 138.08 | JS239: 24.39 | JT239: 647.68 | JU239: 173.72 | JV239: 63.61 | JW239: 524.17 | JX239: 295.05 | JY239: 75.01 | JZ239: 55.68 | KA239: 214.05 | KB239: 98.61 | KC239: 208.62 | KD239: 62.03 | KE239: 101.5 | KF239: 182.3 | KG239: 181.52 | KH239: 109.57 | KI239: 98.21 | KJ239: 259.4 | KK239: 805.37 | KL239: 446.8 | KM239: 335.31 | KN239: 227.24 | KO239: 397.62 | KP239: 238.59 | KQ239: 112.92 | KR239: 177.32 | KS239: 7679.42 | KT239: 114.66 | KU239: 150.945 | KV239: 118.25 | KW239: 133.04 | KX239: 84.28 | KY239: 102.03 | KZ239: 336.11 | LA239: 461.84 | LB239: 230.15 | LC239: 69.37 | LD239: 182.61 | LE239: 400.37 | LF239: 25.03 | LG239: 176.18 | LH239: 723.67 | LI239: 232.38 | LJ239: 176.13 | LK239: 358.15 | LL239: 71.15 | LM239: 138.65 | LN239: 194.29 | LO239: 177.05 | LP239: 466.44 | LQ239: 159.54 | LR239: 272.85 | LS239: 1337.33 | LT239: 148.52 | LU239: 129.19 | LV239: 45.23 | LW239: 249.94 | LX239: 456.02 | LY239: 72.88 | LZ239: 101.47 | MA239: 279.15 | MB239: 179.59 | MC239: 79.24 | MD239: 569.71 | ME239: 244.95 | MF239: 215.37 | MG239: 82 | MH239: 836.57 | MI239: 187.34 | MJ239: 90.73 | MK239: 492.01 | ML239: 57.15 | MM239: 5047.21 | MN239: 240.63 | MO239: 87.97 | MP239: 184.67 | MQ239: 37.69 | MR239: 63.82 | MS239: 319.63 | MT239: 164.03 | MU239: 103.96 | MV239: 149.26 | MW239: 82.335 | MX239: 330.75 | MY239: 274.34 | MZ239: 133.18 | NA239: 88.32 | NB239: 151.71 | NC239: 79.75 | ND239: 238.72 | NE239: 309.23 | NF239: 77.51 | NG239: 111.92 | NH239: 35.95 | NI239: 83.98 | NJ239: 470.11 | NK239: 259.34 | NL239: 93.1 | NM239: 105.56 | NN239: 162.28 | NO239: 553.73 | NP239: 155.83 | NQ239: 156.85 | NR239: 65.66 | NS239: 33.93 | NT239: 131.53 | NU239: 136.01 | NV239: 222.33 | NW239: 166.77 | NX239: 73.985 | NY239: 26.2 | NZ239: 24.21 | OA239: 262.42 | OB239: 79.29 | OC239: 188.44 | OD239: 320.62 | OE239: 194.9 | OF239: 256.06 | OG239: 329.61 | OH239: 134.52 | OI239: 140.89 | OJ239: 189.43 | OK239: 54.07 | OL239: 217.6 | OM239: 251.44 | ON239: 1434.88 | OO239: 28.3 | OP239: 38.85 | OQ239: 138.73 | OR239: 126.49 | OS239: 82.76 | OT239: 25.18 | OU239: 259.78 | OV239: 69.02 | OW239: 58.09 | OX239: 213.45 | OY239: 245.98 | OZ239: 155.59 | PA239: 148.06 | PB239: 230.8 | PC239: 158.38 | PD239: 832.9 | PE239: 83.91 | PF239: 97.88 | PG239: 35.54 | PH239: 27.66 | PI239: 177.37 | PJ239: 187.92 | PK239: 159.75 | PL239: 115.21 | PM239: 106.47 | PN239: 463.13 | PO239: 8.46 | PP239: 639.6 | PQ239: 208.51 | PR239: 813.66 | PS239: 48.42 | PT239: 67.49 | PU239: 108.48 | PV239: 258.67 | PW239: 29.01 | PX239: 38.81 | PY239: 61.11 | PZ239: 134.5 | QA239: 615.87 | QB239: 195.08 | QC239: 61.24 | QD239: 446.74 | QE239: 1079.87 | QF239: 126.48 | QG239: 92.72 | QH239: 23.76 | QI239: 314.03 | QJ239: 503.96 | QK239: 25.56 | QL239: 44.54 | QM239: 79.96 | QN239: 88.33 | QO239: 155 | QP239: 175.72 | QQ239: 95.29 | QR239: 29.34 | QS239: 94.97 | QT239: 214.84 | QU239: 122.57 | QV239: 732.72 | QW239: 159.69 | QX239: 149.09 | QY239: 66.88 | QZ239: 85.25 | RA239: 33.68 | RB239: 409.15 | RC239: 54.62 | RD239: 86.94 | RE239: 120.13 | RF239: 122.89 | RG239: 222.48 | RH239: 102.18 | RI239: 75.98 | RJ239: 361.26 | RK239: 662.21 | RL239: 28.33 | RM239: 17.66 | RN239: 29.84 | RO239: 74.29 | RP239: 33.63 | RQ239: 24.57 | RR239: 445.89 | RS239: 36.12 | RT239: 50.49 | RU239: 26.95 | RV239: 176.08 | RW239: 193.63 | RX239: 118.06 | RY239: 83.59 | RZ239: 193.47 | SA239: 133.64 | SB239: 431.69 | SC239: 601.97 | SD239: 16.97 | SE239: 276.92

Sheet Data
A1: =LN('Raw Data'!C4/'Raw Data'!C3) -> -0.020403319 | B1: =LN('Raw Data'!D4/'Raw Data'!D3) -> 0.020971979 | C1: =LN('Raw Data'!E4/'Raw Data'!E3) -> 0.0067289974 | D1: =LN('Raw Data'!F4/'Raw Data'!F3) -> 0.090757501 | E1: =LN('Raw Data'!G4/'Raw Data'!G3) -> 0.0030577771 | F1: =LN('Raw Data'!H4/'Raw Data'!H3) -> -0.040939704 | G1: =LN('Raw Data'!I4/'Raw Data'!I3) -> 0.0028353195 | H1: =LN('Raw Data'!J4/'Raw Data'!J3) -> 0.014783184 | ... SC1: =LN('Raw Data'!SE4/'Raw Data'!SE3) -> 0.086188781
A2: =LN('Raw Data'!C5/'Raw Data'!C4) -> 0.015409046 | B2: =LN('Raw Data'!D5/'Raw Data'!D4) -> -0.0035035567 | C2: =LN('Raw Data'!E5/'Raw Data'!E4) -> -0.033850163 | D2: =LN('Raw Data'!F5/'Raw Data'!F4) -> 0.038282419 | E2: =LN('Raw Data'!G5/'Raw Data'!G4) -> -0.016956541 | F2: =LN('Raw Data'!H5/'Raw Data'!H4) -> 0.015245177 | G2: =LN('Raw Data'!I5/'Raw Data'!I4) -> -0.0021739438 | H2: =LN('Raw Data'!J5/'Raw Data'!J4) -> -0.00045225615 | ... SC2: =LN('Raw Data'!SE5/'Raw Data'!SE4) -> -0.023628151
A3: =LN('Raw Data'!C6/'Raw Data'!C5) -> -0.011842512 | B3: =LN('Raw Data'!D6/'Raw Data'!D5) -> 0.0027443931 | C3: =LN('Raw Data'!E6/'Raw Data'!E5) -> 0.00051374263 | D3: =LN('Raw Data'!F6/'Raw Data'!F5) -> 0.013929506 | E3: =LN('Raw Data'!G6/'Raw Data'!G5) -> 0.0029260857 | F3: =LN('Raw Data'!H6/'Raw Data'!H5) -> -0.0043570522 | G3: =LN('Raw Data'!I6/'Raw Data'!I5) -> -0.0053309889 | H3: =LN('Raw Data'!J6/'Raw Data'!J5) -> -0.00016450751 | ... SC3: =LN('Raw Data'!SE6/'Raw Data'!SE5) -> -0.016478231
A4: =LN('Raw Data'!C7/'Raw Data'!C6) -> 0.030742612 | B4: =LN('Raw Data'!D7/'Raw Data'!D6) -> -0.0082558782 | C4: =LN('Raw Data'!E7/'Raw Data'!E6) -> -0.017094433 | D4: =LN('Raw Data'!F7/'Raw Data'!F6) -> 0.040224296 | E4: =LN('Raw Data'!G7/'Raw Data'!G6) -> -0.020308621 | F4: =LN('Raw Data'!H7/'Raw Data'!H6) -> -0.027984588 | G4: =LN('Raw Data'!I7/'Raw Data'!I6) -> 0.028665426 | H4: =LN('Raw Data'!J7/'Raw Data'!J6) -> 0.017693083 | ... SC4: =LN('Raw Data'!SE7/'Raw Data'!SE6) -> -0.018006618
A5: =LN('Raw Data'!C8/'Raw Data'!C7) -> 0.01017249 | B5: =LN('Raw Data'!D8/'Raw Data'!D7) -> 0.039046548 | C5: =LN('Raw Data'!E8/'Raw Data'!E7) -> -0.0026157483 | D5: =LN('Raw Data'!F8/'Raw Data'!F7) -> 0.034539001 | E5: =LN('Raw Data'!G8/'Raw Data'!G7) -> 0.01457945 | F5: =LN('Raw Data'!H8/'Raw Data'!H7) -> -0.0049216833 | G5: =LN('Raw Data'!I8/'Raw Data'!I7) -> 0.0088953779 | H5: =LN('Raw Data'!J8/'Raw Data'!J7) -> 0.01952765 | ... SC5: =LN('Raw Data'!SE8/'Raw Data'!SE7) -> 0.073803046
A6: =LN('Raw Data'!C9/'Raw Data'!C8) -> 0.0072032267 | B6: =LN('Raw Data'!D9/'Raw Data'!D8) -> -0.0026931725 | C6: =LN('Raw Data'!E9/'Raw Data'!E8) -> 0.0041819193 | D6: =LN('Raw Data'!F9/'Raw Data'!F8) -> 0.013006058 | E6: =LN('Raw Data'!G9/'Raw Data'!G8) -> 0.0061651668 | F6: =LN('Raw Data'!H9/'Raw Data'!H8) -> 0.016292546 | G6: =LN('Raw Data'!I9/'Raw Data'!I8) -> 0.014984925 | H6: =LN('Raw Data'!J9/'Raw Data'!J8) -> 0.0075796818 | ... SC6: =LN('Raw Data'!SE9/'Raw Data'!SE8) -> 0.024077633
A7: =LN('Raw Data'!C10/'Raw Data'!C9) -> 0.0087053106 | B7: =LN('Raw Data'!D10/'Raw Data'!D9) -> 0.00346132 | C7: =LN('Raw Data'!E10/'Raw Data'!E9) -> 0.011410912 | D7: =LN('Raw Data'!F10/'Raw Data'!F9) -> 0.014121035 | E7: =LN('Raw Data'!G10/'Raw Data'!G9) -> 0.034404164 | F7: =LN('Raw Data'!H10/'Raw Data'!H9) -> 0.012705306 | G7: =LN('Raw Data'!I10/'Raw Data'!I9) -> 0.014271607 | H7: =LN('Raw Data'!J10/'Raw Data'!J9) -> 0.019048937 | ... SC7: =LN('Raw Data'!SE10/'Raw Data'!SE9) -> 0.048007
A8: =LN('Raw Data'!C11/'Raw Data'!C10) -> -0.002850112 | B8: =LN('Raw Data'!D11/'Raw Data'!D10) -> 0.030531191 | C8: =LN('Raw Data'!E11/'Raw Data'!E10) -> 0.0043741225 | D8: =LN('Raw Data'!F11/'Raw Data'!F10) -> 0.0020364302 | E8: =LN('Raw Data'!G11/'Raw Data'!G10) -> 0.01450846 | F8: =LN('Raw Data'!H11/'Raw Data'!H10) -> 0.021452729 | G8: =LN('Raw Data'!I11/'Raw Data'!I10) -> 0.029582444 | H8: =LN('Raw Data'!J11/'Raw Data'!J10) -> 0.01409985 | ... SC8: =LN('Raw Data'!SE11/'Raw Data'!SE10) -> 0.0012514165
A9: =LN('Raw Data'!C12/'Raw Data'!C11) -> 0.0036260076 | B9: =LN('Raw Data'!D12/'Raw Data'!D11) -> 0.011170887 | C9: =LN('Raw Data'!E12/'Raw Data'!E11) -> 0.0058876402 | D9: =LN('Raw Data'!F12/'Raw Data'!F11) -> -0.0073591779 | E9: =LN('Raw Data'!G12/'Raw Data'!G11) -> -0.0026185098 | F9: =LN('Raw Data'!H12/'Raw Data'!H11) -> 0.020946138 | G9: =LN('Raw Data'!I12/'Raw Data'!I11) -> 0.021866271 | H9: =LN('Raw Data'!J12/'Raw Data'!J11) -> 0.011762839 | ... SC9: =LN('Raw Data'!SE12/'Raw Data'!SE11) -> 0.00054066841
A10: =LN('Raw Data'!C13/'Raw Data'!C12) -> 0 | B10: =LN('Raw Data'!D13/'Raw Data'!D12) -> -0.013998776 | C10: =LN('Raw Data'!E13/'Raw Data'!E12) -> 0.0091464052 | D10: =LN('Raw Data'!F13/'Raw Data'!F12) -> -0.032721987 | E10: =LN('Raw Data'!G13/'Raw Data'!G12) -> 0.01822806 | F10: =LN('Raw Data'!H13/'Raw Data'!H12) -> -0.013763755 | G10: =LN('Raw Data'!I13/'Raw Data'!I12) -> 0.0030220039 | H10: =LN('Raw Data'!J13/'Raw Data'!J12) -> -0.0041824511 | ... SC10: =LN('Raw Data'!SE13/'Raw Data'!SE12) -> 0.006700249
A11: =LN('Raw Data'!C14/'Raw Data'!C13) -> 0.012205458 | B11: =LN('Raw Data'!D14/'Raw Data'!D13) -> -0.013471804 | C11: =LN('Raw Data'!E14/'Raw Data'!E13) -> 0.021516967 | D11: =LN('Raw Data'!F14/'Raw Data'!F13) -> -0.064402262 | E11: =LN('Raw Data'!G14/'Raw Data'!G13) -> -0.16557656 | F11: =LN('Raw Data'!H14/'Raw Data'!H13) -> 0.0097219848 | G11: =LN('Raw Data'!I14/'Raw Data'!I13) -> -0.043469848 | H11: =LN('Raw Data'!J14/'Raw Data'!J13) -> 0.0086469955 | ... SC11: =LN('Raw Data'!SE14/'Raw Data'!SE13) -> -0.055824917
A12: =LN('Raw Data'!C15/'Raw Data'!C14) -> -0.0057629666 | B12: =LN('Raw Data'!D15/'Raw Data'!D14) -> -0.005661974 | C12: =LN('Raw Data'!E15/'Raw Data'!E14) -> -0.0029747171 | D12: =LN('Raw Data'!F15/'Raw Data'!F14) -> -0.0025439512 | E12: =LN('Raw Data'!G15/'Raw Data'!G14) -> -0.004882657 | F12: =LN('Raw Data'!H15/'Raw Data'!H14) -> -0.023447466 | G12: =LN('Raw Data'!I15/'Raw Data'!I14) -> 0.0075046299 | H12: =LN('Raw Data'!J15/'Raw Data'!J14) -> -0.0020984794 | ... SC12: =LN('Raw Data'!SE15/'Raw Data'!SE14) -> 0.032054698
... A236: =LN('Raw Data'!C239/'Raw Data'!C238) -> -0.037313784 | B236: =LN('Raw Data'!D239/'Raw Data'!D238) -> 0.020389549 | C236: =LN('Raw Data'!E239/'Raw Data'!E238) -> 0.0014763782 | D236: =LN('Raw Data'!F239/'Raw Data'!F238) -> 0.056270076 | E236: =LN('Raw Data'!G239/'Raw Data'!G238) -> -0.0025190913 | F236: =LN('Raw Data'!H239/'Raw Data'!H238) -> -0.013924524 | G236: =LN('Raw Data'!I239/'Raw Data'!I238) -> 0.015367095 | H236: =LN('Raw Data'!J239/'Raw Data'!J238) -> 0.013709671 | ... SC236: =LN('Raw Data'!SE239/'Raw Data'!SE238) -> 0.050586519

Sheet Qualitative Data
A1: Ticker | B1: Security | C1: Sector | D1: Market Cap (billions)
A2: LYB UN Equity | B2: LyondellBasell Industries NV | C2: Basic Materials | D2: 13.863069
A3: AXP UN Equity | B3: American Express Co | C3: Financial | D3: 255.5433
A4: VZ UN Equity | B4: Verizon Communications Inc | C4: Communications | D4: 173.80106
A5: TPL UN Equity | B5: Texas Pacific Land Corp | C5: Energy | D5: 21.210225
A6: AVGO UW Equity | B6: Broadcom Inc | C6: Technology | D6: 1798.7016
A7: BA UN Equity | B7: Boeing Co/The | C7: Industrial | D7: 153.6571
A8: CAT UN Equity | B8: Caterpillar Inc | C8: Industrial | D8: 280.75032
A9: JPM UN Equity | B9: JPMorgan Chase & Co | C9: Financial | D9: 859.98988
A10: CVX UN Equity | B10: Chevron Corp | C10: Energy | D10: 306.17609
A11: KO UN Equity | B11: Coca-Cola Co/The | C11: Consumer, Non-cyclical | D11: 303.00533
A12: ABBV UN Equity | B12: AbbVie Inc | C12: Consumer, Non-cyclical | D12: 403.84739
A13: DIS UN Equity | B13: Walt Disney Co/The | C13: Communications | D13: 188.34797
... A498: COIN UW Equity | B498: Coinbase Global Inc | C498: Financial | D498: 74.292264
